Workbook

Sheet README
B2: Nordic Orphan Drug Market Access Analysis
B3: Sweden, Denmark, Norway | 51 drugs x 3 countries = 174 evaluation records | Finland excluded (see section 1b) | Rebuilt 2026-06-22
B5: 1. Data sources & provenance
B6: PRIMARY SOURCE (high confidence): "Rare Diseases Database.xlsx" - a structured HTA tracking spreadsheet covering 51 orphan/rare-disease drugs evaluated by Sweden (TLV/NT-radet), Denmark (Medicinradet/Amgros), and Norway (DMP/Nye Metoder/Beslutningsforum). All 174 records in the Master Data sheet originate here unless flagged otherwise in the Data_Source column. Three drugs (Strensiq, Myalepta, Luxturna) were added 2026-06-22 from primary TLV/DMP/Medicinradet/Beslutningsforum documents supplied by the user and independently web-verified (see section 1c).
B7: SUPPLEMENTARY SOURCE (lower confidence, Finland only): "Skysona_merged.pdf" - a 139-page AI-assisted research compilation. This source was used only for Finland data, which is now excluded from this analysis entirely (section 1b) - so this supplementary source no longer feeds any row in Master Data. It is retained in the source folder for provenance/audit purposes only.
B8: All judgment-based classifications below should be treated as best-available analytical estimates pending independent verification against primary TLV / Medicinradet / Nye Metoder publications - NOT as verified primary-source facts.
B10: 1b. Finland exclusion - rationale
B11: Finland is deliberately excluded from this analysis, not merely filtered out as a zero-result row. The reason is a data-completeness/reliability asymmetry, not a finding about Finnish HTA practice: unlike Sweden (TLV), Denmark (Medicinradet/Amgros) and Norway (DMP/Beslutningsforum), no comparable set of primary-source Finnish HTA documents (Fimea assessment reports, PALKO/HILA decisions) was ever assembled for this project. The only Finland data available came from an AI-assisted research compilation (Skysona_merged.pdf), which is demonstrably a secondary/derived source (it contains a self-referential note to a prior AI tool's "follow-up suggestion") rather than a primary HTA publication.
B12: Carrying Finland forward on that basis would silently mix one fundamentally lower-confidence evidence tier into every cross-country comparison in this workbook (rates, trends, restriction levels, Fisher's-exact tests), without a way to flag the difference in a live pivot/COUNTIFS table. The scientifically defensible choice is to exclude Finland entirely until primary Fimea/PALKO/HILA source documents are obtained, rather than report findings that imply a confidence level the underlying Finland data does not support. This mirrors standard HTA evidence-synthesis practice of excluding, rather than downweighting in place, sources that fail a minimum evidentiary-quality bar.
B13: If primary Finnish HTA documents become available, Finland can be reintroduced by re-adding country block data to Rare Diseases Database.xlsx and removing it from the EXCLUDED_COUNTRIES set in the build pipeline (build_master.py) - no other structural change is required.
B15: 1c. Web-verification of newly added drugs (2026-06-22)
B16: Strensiq, Myalepta and Luxturna were added from primary-source PDFs (TLV beslut, DMP metodevurdering/Beslutningsforum sakspapirer, Medicinradet anbefaling) supplied directly by the user. Each drug's key facts (decision outcome, date, case/diary number) were independently checked against public web sources on 2026-06-22; no contradictions were found. Two facts remain genuinely unconfirmed in any source checked (document or web) and are reported as such rather than guessed: (1) the outcome of Myalepta's January 2023 Beslutningsforum vote restricted to the GL (generalised lipodystrophy) subgroup in Norway; (2) any Strensiq decision in Norway after the 27 Sept 2021 "not recommended / under renegotiation" status. Both are recorded with Decision Status "Not recommended / Under renegotiation" reflecting the last confirmed state, not an assumption of a later outcome.
... B46: Every column in Master Data is evaluable (non-null/non-trivial) for at least one country per drug where an HTA process occurred; "Not Evaluated" rows correctly carry blank decision-specific fields (Decision_Date, Comparator, ICER, etc.) rather than placeholder text, by design (see Access_Outcome). The Evidence_Type column is the one parameter with a structural coverage gap: most source records do not describe trial design explicitly, so most rows are coded "Not specified/unclear" - this is a genuine source-data limitation, not a classifier defect, and is flagged here rather than silently presented as a usable cross-tab dimension. The 3-tier Severity_Tier scheme is a simplification that fits most drugs cleanly but is a coarse fit for a few atypical cases (e.g. Luxturna, a one-time gene therapy for a non-immediately-fatal but vision-threatening pediatric condition, sits awkwardly between "Severe" and "Serious"); it is retained for cross-drug comparability but should not be read as a precise clinical grading.

Sheet Master Data
A1: Drug | B1: INN | C1: Disease | D1: Applicant | E1: Parent_Company | F1: Technology | G1: Therapeutic_Area | H1: Severity_Tier | I1: Country | J1: Decision_Type | K1: Evaluation_Raw | L1: Decision_Status_Raw | M1: Access_Outcome | N1: Restriction_Level | O1: Reason_Category | P1: Decision_Year | Q1: Decision_Date_Raw | R1: Comparator_Category | S1: Comparator_Raw | T1: Evidence_Type | U1: Reason_Text | V1: ICER_Raw | W1: Main_Uncertainty | X1: Conditions | Y1: Notes | Z1: Comments | AA1: Data_Source | AB1: Row_Ref | AC1: Is_Positive | AD1: Is_Assessed | AE1: ICER_Min_SEK_per_QALY (Sweden only, curated) | AF1: ICER_Max_SEK_per_QALY (Sweden only, curated) | AG1: ICER_Basis_Note (Sweden only) | AH1: Technology_Group | AI1: Drug_Any_Positive (helper) | AJ1: Drug_First_Positive_Year (helper)
A2: Zolgensma | B2: Onasemnogene abeparvovec | C2: 5q Spinal muscular atrophy (SMA) | D2: Novartis Gene Therapies | E2: Novartis | F2: Gene therapy (in vivo AAV) | G2: Neuromuscular | H2: Ultra-severe (immediately life-threatening) | I2: Sweden | J2: Full / standard HTA | K2: Health Economic Assessment with Scenario Analysis | L2: Not Recommended (Uncertainty) | M2: Negative | N2: Not Applicable | O2: Clinical evidence uncertainty | P2: 2021 | Q2: 2021-02-24 00:00:00 | R2: Active comparator drug(s) | S2: Spinraza + BSC or BSC | T2: Not specified / unclear | U2: Clinical evidence uncertainty | V2: SEK 850,000 - 3.2 million/QALY vs Spinraza + BSC or SEK 2.9–5.7 million/QALY vs BSC alone | W2: Very high uncertainty about long-term effects, how long the treatment effect lasts and uncertainty due to model based on muldtiple linked data sources | X2: Patients with 5q SMA with biallelic SMN1 mutation and either a clinical diagnosis of SMA type 1, or up to 3 copies of the SMN2 gene. TLV's economic scenarios mainly apply to symptomatic SMA type 1. No conclusions or results were presented for presymptomaic patients or symptomatic SMA type 2/3 due to uncertaintly in relative effectiveness. | Y2: Health Economic Assessment completed by TLV - no base-case scenario established for some patient groups due to uncertainty | Z2: TLV presents multiple scenario analyses wather than one base case for symptomatic SMA type 1. No results are presented for presymptomatic patients or symptomatic SMA type 2/3 because TLV considers relative effectiveness vs Spinraza too uncertain. Patient follow-up is considered important. | AA2: Primary xlsx database | AB2: 4 | AC2: =IF(OR($M2="Positive",$M2="Restricted Positive"),1,0) -> 0 | AD2: =IF($M2="Not Evaluated",0,1) -> 1 | AE2: 850000 | AF2: 5700000 | AG2: range (vs Spinraza+BSC: 0.85-3.2M; vs BSC alone: 2.9-5.7M) | AH2: Gene therapy | AI2: =IF(COUNTIFS($A$2:$A$175,$A2,$C$2:$C$175,$C2,$AC$2:$AC$175,1)>0,1,0) -> 1 | AJ2: =IFERROR(_xludf.MINIFS($P$2:$P$175,$A$2:$A$175,$A2,$C$2:$C$175,$C2,$AC$2:$AC$175,1),"")
A3: Zolgensma | B3: Onasemnogene abeparvovec | C3: 5q Spinal muscular atrophy (SMA) | D3: Novartis Gene Therapies | E3: Novartis | F3: Gene therapy (in vivo AAV) | G3: Neuromuscular | H3: Ultra-severe (immediately life-threatening) | I3: Denmark | J3: Full / standard HTA | K3: Clinical Value assessment + health economic assessment - Cost Minimization Approach | L3: Recommended | M3: Positive | N3: Broad | O3: N/A | P3: 2021 | Q3: Original recommendation: 26 May 2021; follow-up maintained: 23 Aug 2023; replaced by SMA guidance: 31 Aug 2023 | R3: Active comparator drug(s) | S3: Nusinersen/Spinraza, given continuously every 4 months | T3: Not specified / unclear | U3: Clinical evidence uncertainty + Price / cost-effectiveness | V3: No ICER reported. Medicinrådet used cost-minimisation because Zolgensma and nusinersen were considered clinically equivalent. Costs per patient were expected to equalise after 8–15 years, with substantial uncertainty; using AIP, equalisation was around 9 years | W3: Long-term effect and long-term safety of one-time Zolgensma treatment. Uncertainty about how long nusinersen treatment would continue. Uncertainty around when costs equalize. | X3: Infants with SMA type 1 treated before 6 months old and not in permanent ventilation >16h/day, also presymptomatic infants born with SMA. Switching from comparator may be considered only in special cases if the child weights <13.5kg, is not severely muscle-weak and can breathe independently. | Y3: Medicinrådet considered Zolgensma clinically equivalent to nusinersen overall. The applicant’s full health economic model was only used to a limited extent because assumptions about effect, disease progression and mortality were not sufficiently supported by data. Medicinrådet instead used a simplified cost-minimisation approach | Z3: Zolgensma was not recommended in combination with nusinersen. The recommendation did not mean Zolgensma should automatically be first choice for all patients, switching from well-functioning nusinersen generally requires a specific clinical reason | AA3: Primary xlsx database | AB3: 4 | AC3: =IF(OR($M3="Positive",$M3="Restricted Positive"),1,0) -> 1 | AD3: =IF($M3="Not Evaluated",0,1) -> 1 | AH3: Gene therapy | AI3: =IF(COUNTIFS($A$2:$A$175,$A3,$C$2:$C$175,$C3,$AC$2:$AC$175,1)>0,1,0) -> 1 | AJ3: =IFERROR(_xludf.MINIFS($P$2:$P$175,$A$2:$A$175,$A3,$C$2:$C$175,$C3,$AC$2:$AC$175,1),"")
A4: Zolgensma | B4: Onasemnogene abeparvovec | C4: 5q Spinal muscular atrophy (SMA) | D4: Novartis Gene Therapies | E4: Novartis | F4: Gene therapy (in vivo AAV) | G4: Neuromuscular | H4: Ultra-severe (immediately life-threatening) | I4: Norway | J4: Rapid / simplified HTA | K4: Simplified method assessment: effect, safety and cost assessment + managed-access negotiation | L4: Introduced by Beslutningsforum for treatment of SMA - currently under reassessment because updated follow-up documentation was not submitted on time | M4: Positive | N4: Broad | O4: N/A | P4: 2021 | Q4: Final introduction: 25 Oct 2021; reassessment request: 19 Jan 2026; deadline extended to 15 Jun 2026 on 27 Apr 2026 | R4: Active comparator drug(s) | S4: Nusinersen/Spinraza | T4: Real-world / registry / natural history | U4: Clinical evidence uncertainty + Price / cost-effectiveness | V4: No standard ICER/cost per QALY reported. Cost comparison only; Zolgensma had a very high one-time cost, around NOK 27 million before possible discounts | W4: Sparse evidence base, short follow-up, major uncertainty about long-term effect, uncertainty about comparison with Spinraza and long-term costs | X4: Infants <6 months with manifest 5q SMA type 1 and biallelic SMN1 mutation, without clear symptoms at birth/type 0 and without ventilation support >16 h/day, presymptomatic infants <6 months with biallelic SMN1 mutation and 2 or 3 SMN2 copies, elected 6–18 month children <13.5 kg may switch from Spinraza in special cases if not severely weak and able to breathe independently, <6 month patients already started on Spinraza before Zolgensma availability could convert | Y4: Simplified HTA assessing effect, safety and costs. Zolgensma was compared with Spinraza. Final introduction was possible after negotiations and a result-based price agreement | Z4: First result-based agreement for a medicine in Norway. Treatment centralised at Oslo University Hospital, registry follow-up required, no combination with Spinraza or other disease-modifying treatment. In 2026, caution advised for new patients pending reassessment | AA4: Primary xlsx database | AB4: 4 | AC4: =IF(OR($M4="Positive",$M4="Restricted Positive"),1,0) -> 1 | AD4: =IF($M4="Not Evaluated",0,1) -> 1 | AH4: Gene therapy | AI4: =IF(COUNTIFS($A$2:$A$175,$A4,$C$2:$C$175,$C4,$AC$2:$AC$175,1)>0,1,0) -> 1 | AJ4: =IFERROR(_xludf.MINIFS($P$2:$P$175,$A$2:$A$175,$A4,$C$2:$C$175,$C4,$AC$2:$AC$175,1),"")
A5: Evrysdi | B5: Risdiplam | C5: 5q Spinal muscular atrophy (SMA) | D5: Roche AB | E5: Roche | F5: Small molecule | G5: Neuromuscular | H5: Ultra-severe (immediately life-threatening) | I5: Sweden | J5: Managed introduction / price negotiation | K5: Reimbursement / Subvention Assessment with Cost-Utility Analysis, later restricted subvention after side agreement | L5: 2021: Rejected. 2025: Reimbursed with restriction | M5: Restricted Positive | N5: Restricted | O5: Price/Cost-effectiveness | P5: 2021 | Q5: 21/10/2021; 01/02/2025; tablet added 26/08/2025 | R5: Active comparator drug(s) | S5: BSC / no addition to BSC; tablet compared with Evrysdi oral solution | T5: Not specified / unclear | U5: Clinical evidence uncertainty + Price / cost-effectiveness | V5: 2021: SEK 2.3–3.1M/QALY for SMA type 1; SEK 7.9M/QALY for SMA type 2/3. 2025: SEK 4.9M/QALY for SMA type 1; approx. SEK 800k/QALY for SMA type 2/3 after side agreement | W5: Long-term effect, survival, QoL, model uncertainty, transferability to Swedish population, personal assistance costs | X5: 5q SMA type 1, type 2 or type 3. Tablet: patients >2 years and ≥20 kg under same restriction | Y5: Initial rejection due to costs not being reasonable vs benefit, later approval enabled by side agreement between Roche and regions | Z5: Important reversal case: price agreement changed outcome. SMA type 1 included via need-solidarity principle, tablet decision was a formulation extension | AA5: Primary xlsx database | AB5: 5 | AC5: =IF(OR($M5="Positive",$M5="Restricted Positive"),1,0) -> 1 | AD5: =IF($M5="Not Evaluated",0,1) -> 1 | AE5: 800000 | AF5: 7900000 | AG5: range across 2021 and 2025 reassessments, by SMA subtype | AH5: Small molecule | AI5: =IF(COUNTIFS($A$2:$A$175,$A5,$C$2:$C$175,$C5,$AC$2:$AC$175,1)>0,1,0) -> 1 | AJ5: =IFERROR(_xludf.MINIFS($P$2:$P$175,$A$2:$A$175,$A5,$C$2:$C$175,$C5,$AC$2:$AC$175,1),"")
A6: Evrysdi | B6: Risdiplam | C6: 5q Spinal muscular atrophy (SMA) | D6: Roche AB | E6: Roche | F6: Small molecule | G6: Neuromuscular | H6: Ultra-severe (immediately life-threatening) | I6: Denmark | J6: Full / standard HTA | K6: Clinical Value Assessment + health economic assessment - later integrated into SMA treatment guidance and drug recommendation | L6: 2021: Recommended for selected SMA patients. 2024: Recommendation expanded after reassessment based on new price and new data. 2026: Evrysdi placed as first-choice option in current SMA drug recommendation | M6: Positive | N6: Broad | O6: N/A | P6: 2021 | Q6: Original recommendation: 27/10/2021. Reassessment/expanded recommendation: 28/08/2024. Current guidance: 29/04/2026 | R6: Active comparator drug(s) | S6: Nusinersen for SMA type 1 and selected SMA type 2/3 groups; BSC/placebo/no medical treatment for groups where nusinersen was not standard care | T6: Not specified / unclear | U6: Clinical evidence uncertainty + Price / cost-effectiveness | V6: No ICER reported. Medicinrådet used incremental cost and budget impact analyses. In 2021, risdiplam was less costly than nusinersen in recommended groups; list-price analyses showed high incremental costs vs BSC in older/non-recommended groups | W6: Sparse data for SMA type 1, short follow-up, uncertain effect in older children/adults in original assessment, uncertainty around long-term survival, treatment duration and accumulated medicine costs | X6: 2021: SMA type 1 patients not in permanent ventilation >16 h/day; SMA type 2/3 patients under 6 years at treatment start. Later expanded to patients meeting fixed start/stop criteria. Current guidance includes Evrysdi as first choice for SMA type 1/presymptomatic infants, SMA type 2/3 children, young people and adults, including adults >25 years meeting criteria | Y6: Risdiplam was initially recommended because it was considered as good as nusinersen for relevant younger patients and less costly. Older SMA type 2/3 patients were not included in 2021 due to insufficient evidence. Later evidence and pricing supported broader use | Z6: Important expansion case: access broadened over time through new data, new price and integration into SMA pathway guidance. Evrysdi is oral and taken at home, unlike nusinersen. Combination therapy with other SMA medicines is not recommended | AA6: Primary xlsx database | AB6: 5 | AC6: =IF(OR($M6="Positive",$M6="Restricted Positive"),1,0) -> 1 | AD6: =IF($M6="Not Evaluated",0,1) -> 1 | AH6: Small molecule | AI6: =IF(COUNTIFS($A$2:$A$175,$A6,$C$2:$C$175,$C6,$AC$2:$AC$175,1)>0,1,0) -> 1 | AJ6: =IFERROR(_xludf.MINIFS($P$2:$P$175,$A$2:$A$175,$A6,$C$2:$C$175,$C6,$AC$2:$AC$175,1),"")
A7: Evrysdi | B7: Risdiplam | C7: 5q Spinal muscular atrophy (SMA) | D7: Roche AB | E7: Roche | F7: Small molecule | G7: Neuromuscular | H7: Ultra-severe (immediately life-threatening) | I7: Norway | J7: Rapid / simplified HTA | K7: Multiple Evaluations: Simplified HTA (ID2021_088), Full HTA (ID2020_104), indication extensions and pricing reviews (ID2023_089, ID2025_010) | L7: Recommended (Introduced through stepwise indication expansions) | M7: Positive | N7: Broad | O7: N/A | P7: 2022 | Q7: Initial reimbursement: 17/01/2022. Expanded: 22/01/2024. Tablet formulation: 2025 | R7: Active comparator drug(s) | S7: Nusinersen (Spinraza) for children already eligible for treatment; supportive care/no disease-modifying treatment for adults and SMA type 3b populations | T7: Not specified / unclear | U7: Clinical evidence uncertainty + Comparator/positioning issue + Price / cost-effectiveness | V7: Full HTA (ID2020_104) estimated approximately NOK 12 million per QALY gained versus supportive care. No ICER reported in simplified assessments. | W7: Limited long-term evidence, small patient populations, uncertainty regarding long-term effectiveness and durability of treatment effect, particularly in adults | X7: Initially approved for children ≥2 months with SMA type 1, 2 or 3a. Later expanded to infants <2 months and subsequently to broader adult populations. National start/stop criteria apply. | Y7: Norway used different evaluation pathways depending on the patient population. Children already eligible for Spinraza underwent a simplified assessment, while adults and type 3b patients underwent a full HTA. | Z7: Market access was achieved through gradual indication expansion. Adult access required additional assessment and price negotiations. Tablet formulation was approved through a suitability assessment and pricing review rather than a new HTA. | AA7: Primary xlsx database | AB7: 5 | AC7: =IF(OR($M7="Positive",$M7="Restricted Positive"),1,0) -> 1 | AD7: =IF($M7="Not Evaluated",0,1) -> 1 | AH7: Small molecule | AI7: =IF(COUNTIFS($A$2:$A$175,$A7,$C$2:$C$175,$C7,$AC$2:$AC$175,1)>0,1,0) -> 1 | AJ7: =IFERROR(_xludf.MINIFS($P$2:$P$175,$A$2:$A$175,$A7,$C$2:$C$175,$C7,$AC$2:$AC$175,1),"")
A8: Spinraza | B8: Nusinersen | C8: 5q Spinal muscular atrophy (SMA) | D8: Biogen Sweden AB | E8: Biogen | F8: RNA-targeted (antisense oligonucleotide) | G8: Neuromuscular | H8: Ultra-severe (immediately life-threatening) | I8: Sweden | J8: Full / standard HTA | K8: Health Economic Assessment with Scenario Analysis | L8: Recomended (Reassessed 2023) | M8: Positive | N8: Broad | O8: N/A | P8: 2017 | Q8: 10/11/2017; 18/10/2023 | R8: Best supportive care / no active treatment | S8: BSC | T8: Real-world / registry / natural history | U8: Clinical evidence uncertainty | V8: 2017: SMA I SEK 5.7–7.7M/QALY; SMA II SEK 7.3–12.8M/QALY. 2023: Pediatric SMA I SEK 4.1–7.3M/QALY; Pediatric SMA II SEK 4.8–7.7M/QALY | W8: Long-term survival, durability of treatment effect, quality-of-life estimates, disease progression modelling and limited evidence for adult SMA populations | X8: Patients with 5q SMA type I, II and III. Reassessment included pediatric SMA type I/II and adult SMA type II/III populations | Y8: Initial TLV assessment followed by major reassessment using long-term evidence and real-world data | Z8: Spinraza became the reference therapy against which both Zolgensma and Evrysdi were later assessed in Sweden. Reassessment demonstrated improved evidence base but uncertainty remained for adult SMA populations. | AA8: Primary xlsx database | AB8: 6 | AC8: =IF(OR($M8="Positive",$M8="Restricted Positive"),1,0) -> 1 | AD8: =IF($M8="Not Evaluated",0,1) -> 1 | AE8: 4100000 | AF8: 12800000 | AG8: range across 2017 and 2023 reassessments, by SMA subtype | AH8: RNA-targeted | AI8: =IF(COUNTIFS($A$2:$A$175,$A8,$C$2:$C$175,$C8,$AC$2:$AC$175,1)>0,1,0) -> 1 | AJ8: =IFERROR(_xludf.MINIFS($P$2:$P$175,$A$2:$A$175,$A8,$C$2:$C$175,$C8,$AC$2:$AC$175,1),"")
A9: Spinraza | B9: Nusinersen | C9: 5q Spinal muscular atrophy (SMA) | D9: Biogen Sweden AB | E9: Biogen | F9: RNA-targeted (antisense oligonucleotide) | G9: Neuromuscular | H9: Ultra-severe (immediately life-threatening) | I9: Denmark | J9: Managed introduction / price negotiation | K9: Repeated HTA and reimbursement reassessments (2017, 2018, 2020) followed by national treatment guideline priorisation (2023) | L9: Restricted Recommendation / Recommended only for defined SMA subgroups; Not recommended for general SMA population | M9: Restricted Positive | N9: Restricted | O9: Clinical evidence uncertainty | P9: 2017 | Q9: 12/10/2017; 30/01/2018; 30/05/2018; 27/10/2020; 31/08/2023 | R9: Active comparator drug(s) | S9: BSC (initial assessments) + later compared directly with risdiplamn and onasemnogene in treatment guideline reviews | T9: Not specified / unclear | U9: Administrative/procedural + Clinical evidence uncertainty + Comparator/positioning issue + Price / cost-effectiveness | V9: No ICER publicly reported in Medicinrådet recommendations; decisions based on clinical value relative to negotiated price | W9: Limited long-term efficacy data, particularly for SMA type 2 and type 3; uncertainty regarding treatment effect in older children, adults and patients with longer disease duration; lack of evidence for SMA type 3 and adults | X9: Recommended for presymptomatic infants with 2–4 SMN2 copies, SMA type 1 and selected SMA type 2 patients meeting strict clinical criteria (including early treatment initiation and limited disease duration). Not recommended for SMA type 3 or general SMA populations. | Y9: Multiple reassessments due to new evidence and price negotiations. Medicinrådet repeatedly concluded that the price remained disproportionately high relative to documented benefit but accepted restricted use based on disease severity and demonstrated benefit in selected populations. | Z9: Illustrates Denmark’s highly restrictive access approach for rare disease therapies. Access expanded gradually as evidence accumulated, but recommendations remained limited to subgroups with strongest evidence. In 2023 Spinraza became a second-line option behind Evrysdi in most paediatric populations. | AA9: Primary xlsx database | AB9: 6 | AC9: =IF(OR($M9="Positive",$M9="Restricted Positive"),1,0) -> 1 | AD9: =IF($M9="Not Evaluated",0,1) -> 1 | AH9: RNA-targeted | AI9: =IF(COUNTIFS($A$2:$A$175,$A9,$C$2:$C$175,$C9,$AC$2:$AC$175,1)>0,1,0) -> 1 | AJ9: =IFERROR(_xludf.MINIFS($P$2:$P$175,$A$2:$A$175,$A9,$C$2:$C$175,$C9,$AC$2:$AC$175,1),"")
A10: Spinraza | B10: Nusinersen | C10: 5q Spinal muscular atrophy (SMA) | D10: Biogen Sweden AB | E10: Biogen | F10: RNA-targeted (antisense oligonucleotide) | G10: Neuromuscular | H10: Ultra-severe (immediately life-threatening) | I10: Norway | J10: Rapid / simplified HTA | K10: Rapid HTA (2017), multiple reassessments (2018, 2023) and price negotiations | L10: Recommended with restrictions (following initial non-recommendation) | M10: Restricted Positive | N10: Restricted | O10: N/A | P10: 2017 | Q10: 23/10/2017; 08/12/2017; 12/02/2018; 22/10/2018; 11/04/2023 | R10: Best supportive care / no active treatment | S10: BSC / no disease modifying treatment | T10: Real-world / registry / natural history | U10: Clinical evidence uncertainty + Price / cost-effectiveness | V10: Initial HTA estimated ICERs ranging from approximately NOK 16–40 million per QALY in the Norwegian Medicines Agency base-case scenarios, depending on SMA subtype. | W10: Long-term effectiveness, durability of treatment effect, limited trial data, uncertainty in health-economic model, effectiveness in older patients and later disease stages | X10: Restricted to defined paediatric SMA populations under strict start/stop criteria, national expert review, registry participation and regular reassessment. Expanded in 2023 to include SMA type 3b children. | Y10: Initially rejected because price was considered unacceptable and evidence uncertain. Following substantial price negotiations, Spinraza was introduced under one of the most restrictive managed-access schemes in Norway. | Z10: Illustrates Norway’s use of managed access, price negotiation, registry-based monitoring and start/stop criteria to manage uncertainty for an ultra-rare disease therapy. | AA10: Primary xlsx database | AB10: 6 | AC10: =IF(OR($M10="Positive",$M10="Restricted Positive"),1,0) -> 1 | AD10: =IF($M10="Not Evaluated",0,1) -> 1 | AH10: RNA-targeted | AI10: =IF(COUNTIFS($A$2:$A$175,$A10,$C$2:$C$175,$C10,$AC$2:$AC$175,1)>0,1,0) -> 1 | AJ10: =IFERROR(_xludf.MINIFS($P$2:$P$175,$A$2:$A$175,$A10,$C$2:$C$175,$C10,$AC$2:$AC$175,1),"")
A11: Libmeldy | B11: Atidarsagene autotemcel | C11: Metachromatic leukodystrophy | D11: Orchard Therapeutics (Kyowa Kirin) | E11: Kyowa Kirin | F11: Gene therapy (ex vivo lentiviral) | G11: Neurology (metabolic) | H11: Ultra-severe (immediately life-threatening) | I11: Sweden | J11: Joint Nordic HTA (FINOSE/JNHB) | K11: FINOSE Joint Health Economic Assessment + NT-rådet recommendation | L11: Recommended | M11: Positive | N11: Broad | O11: N/A | P11: 2022 | Q11: FINOSE HTA February 2022; NT-rådet recommendation November 2023 | R11: Best supportive care / no active treatment | S11: BSC | T11: Not specified / unclear | U11: Clinical evidence uncertainty + Comparator/positioning issue | V11: Approx. NOK 3.15–3.23 million/QALY in FINOSE scenarios; combined scenario approx. NOK 6.36 million/QALY | W11: Very small patient population, no randomized comparator, uncertainty regarding long-term durability and safety | X11: Late infantile or early juvenile MLD; presymptomatic patients or early symptomatic patients still able to walk independently and before cognitive decline | Y11: Joint FINOSE assessment with Norway and Finland | Z11: Sweden became the operational treatment hub for the Nordic region | AA11: Primary xlsx database | AB11: 7 | AC11: =IF(OR($M11="Positive",$M11="Restricted Positive"),1,0) -> 1 | AD11: =IF($M11="Not Evaluated",0,1) -> 1 | AG11: source quotes NOK 3.15-6.36M in the Sweden record - likely a currency labelling error in source data, excluded pending verification | AH11: Gene therapy | AI11: =IF(COUNTIFS($A$2:$A$175,$A11,$C$2:$C$175,$C11,$AC$2:$AC$175,1)>0,1,0) -> 1 | AJ11: =IFERROR(_xludf.MINIFS($P$2:$P$175,$A$2:$A$175,$A11,$C$2:$C$175,$C11,$AC$2:$AC$175,1),"")
A12: Libmeldy | B12: Atidarsagene autotemcel | C12: Metachromatic leukodystrophy | D12: Orchard Therapeutics (Kyowa Kirin) | E12: Kyowa Kirin | F12: Gene therapy (ex vivo lentiviral) | G12: Neurology (metabolic) | H12: Ultra-severe (immediately life-threatening) | I12: Denmark | J12: Other / unclassified process | K12: Assessment initiated but not completed by Medicinrådet | L12: Outside Medicinrådet jurisdiction | M12: Not Evaluated | N12: Not Applicable | O12: Administrative/Procedural | P12: 2022 | Q12: 2022-06-01 00:00:00 | R12: Not applicable / Not assessed | S12: N/A | T12: Not specified / unclear | U12: Not specified | V12: N/A | W12: Danish patients referred through cross-border arrangements | X12: Not evaluated because treatment delivered abroad | Y12: Medicinrådet concluded that treatment falls outside its mandate because Danish patients are treated abroad | Z12: Access ultimately achieved through Nordic collaboration rather than standard Medicinrådet recommendation | AA12: Primary xlsx database | AB12: 7 | AC12: =IF(OR($M12="Positive",$M12="Restricted Positive"),1,0) -> 0 | AD12: =IF($M12="Not Evaluated",0,1) -> 0 | AH12: Gene therapy | AI12: =IF(COUNTIFS($A$2:$A$175,$A12,$C$2:$C$175,$C12,$AC$2:$AC$175,1)>0,1,0) -> 1 | AJ12: =IFERROR(_xludf.MINIFS($P$2:$P$175,$A$2:$A$175,$A12,$C$2:$C$175,$C12,$AC$2:$AC$175,1),"")
A13: Libmeldy | B13: Atidarsagene autotemcel | C13: Metachromatic leukodystrophy | D13: Orchard Therapeutics (Kyowa Kirin) | E13: Kyowa Kirin | F13: Gene therapy (ex vivo lentiviral) | G13: Neurology (metabolic) | H13: Ultra-severe (immediately life-threatening) | I13: Norway | J13: Joint Nordic HTA (FINOSE/JNHB) | K13: Rapid HTA (Cost-Utility Assessment) + FINOSE Collaboration | L13: Recommended | M13: Positive | N13: Broad | O13: N/A | P13: 2023 | Q13: 2023-06-19 00:00:00 | R13: Best supportive care / no active treatment | S13: BSC | T13: Not specified / unclear | U13: Clinical evidence uncertainty + Price / cost-effectiveness | V13: Based on FINOSE cost-effectiveness assessment; exact negotiated price confidential | W13: Long-term durability, small evidence base, no control group | X13: Same population as EMA indication; treatment centralized to Nordic centre in Sweden | Y13: Norwegian adaptation of FINOSE assessment plus national price negotiations | Z13: Explicitly linked to Nordic collaboration and newborn screening discussion | AA13: Primary xlsx database | AB13: 7 | AC13: =IF(OR($M13="Positive",$M13="Restricted Positive"),1,0) -> 1 | AD13: =IF($M13="Not Evaluated",0,1) -> 1 | AH13: Gene therapy | AI13: =IF(COUNTIFS($A$2:$A$175,$A13,$C$2:$C$175,$C13,$AC$2:$AC$175,1)>0,1,0) -> 1 | AJ13: =IFERROR(_xludf.MINIFS($P$2:$P$175,$A$2:$A$175,$A13,$C$2:$C$175,$C13,$AC$2:$AC$175,1),"")
A14: Skysona | B14: Elivaldogene autotemcel | C14: Cerebral adrenoleukodystrophy | D14: Bluebird Bio | E14: bluebird bio | F14: Gene therapy (ex vivo lentiviral) | G14: Neurology (metabolic) | H14: Ultra-severe (immediately life-threatening) | I14: Sweden | J14: Early / horizon scanning only | K14: Early Assessment Report (Horizon Scanning) | L14: Withdrawn before HTA completion | M14: Withdrawn | N14: Not Applicable | O14: Administrative/Procedural | P14: 2021 | Q14: Early Assessment 04/05/2021; European withdrawal November 2021 | R14: Procedural / transplant-based comparator | S14: Allogeneic Hematopoietic Stem Cell Transplantation (HSCT) | T14: Not specified / unclear | U14: Administrative/procedural + Clinical evidence uncertainty | V14: N/A | W14: Limited clinical evidence, immature long-term data, uncertainty regarding durability, safety, implementation and expected pricing | X14: Intended for boys <18 years with early cerebral adrenoleukodystrophy (cALD) and ABCD1 mutation | Y14: Early assessment only. No TLV economic assessment, reimbursement review or NT-rådet recommendation completed. | Z14: Important failed market access case. Despite EMA approval in July 2021, Bluebird Bio withdrew Skysona from Europe in November 2021 following broader reimbursement and pricing challenges. No Nordic reimbursement process was completed and the therapy never entered routine clinical practice. | AA14: Primary xlsx database | AB14: 8 | AC14: =IF(OR($M14="Positive",$M14="Restricted Positive"),1,0) -> 0 | AD14: =IF($M14="Not Evaluated",0,1) -> 1 | AG14: none public - withdrawn before HTA completion | AH14: Gene therapy | AI14: =IF(COUNTIFS($A$2:$A$175,$A14,$C$2:$C$175,$C14,$AC$2:$AC$175,1)>0,1,0) -> 0 | AJ14: =IFERROR(_xludf.MINIFS($P$2:$P$175,$A$2:$A$175,$A14,$C$2:$C$175,$C14,$AC$2:$AC$175,1),"")
A15: Skysona | B15: Elivaldogene autotemcel | C15: Cerebral adrenoleukodystrophy | D15: Bluebird Bio | E15: bluebird bio | F15: Gene therapy (ex vivo lentiviral) | G15: Neurology (metabolic) | H15: Ultra-severe (immediately life-threatening) | I15: Denmark | J15: No formal assessment / not assessed | K15: Not assessed in Denmark | L15: Not assessed in Denmark | M15: Not Evaluated | N15: Not Applicable | O15: N/A | Q15: Not assessed in Denmark | R15: Not applicable / Not assessed | S15: Not assessed in Denmark | T15: Not specified / unclear | U15: Not specified | V15: Not assessed in Denmark | W15: Not assessed in Denmark | X15: Not assessed in Denmark | Y15: Not assessed in Denmark | Z15: Not assessed in Denmark | AA15: Primary xlsx database | AB15: 8 | AC15: =IF(OR($M15="Positive",$M15="Restricted Positive"),1,0) -> 0 | AD15: =IF($M15="Not Evaluated",0,1) -> 0 | AH15: Gene therapy | AI15: =IF(COUNTIFS($A$2:$A$175,$A15,$C$2:$C$175,$C15,$AC$2:$AC$175,1)>0,1,0) -> 0 | AJ15: =IFERROR(_xludf.MINIFS($P$2:$P$175,$A$2:$A$175,$A15,$C$2:$C$175,$C15,$AC$2:$AC$175,1),"")
A16: Skysona | B16: Elivaldogene autotemcel | C16: Cerebral adrenoleukodystrophy | D16: Bluebird Bio | E16: bluebird bio | F16: Gene therapy (ex vivo lentiviral) | G16: Neurology (metabolic) | H16: Ultra-severe (immediately life-threatening) | I16: Norway | J16: No formal assessment / not assessed | K16: Not assessed in Norway | L16: Not assessed in Norway | M16: Not Evaluated | N16: Not Applicable | O16: N/A | Q16: Not assessed in Norway | R16: Not applicable / Not assessed | S16: Not assessed in Norway | T16: Not specified / unclear | U16: Not specified | V16: Not assessed in Norway | W16: Not assessed in Norway | X16: Not assessed in Norway | Y16: Not assessed in Norway | Z16: Not assessed in Norway | AA16: Primary xlsx database | AB16: 8 | AC16: =IF(OR($M16="Positive",$M16="Restricted Positive"),1,0) -> 0 | AD16: =IF($M16="Not Evaluated",0,1) -> 0 | AH16: Gene therapy | AI16: =IF(COUNTIFS($A$2:$A$175,$A16,$C$2:$C$175,$C16,$AC$2:$AC$175,1)>0,1,0) -> 0 | AJ16: =IFERROR(_xludf.MINIFS($P$2:$P$175,$A$2:$A$175,$A16,$C$2:$C$175,$C16,$AC$2:$AC$175,1),"")
A17: Hemgenix | B17: Etranacogene dezaparvovec | C17: Hemophilia B | D17: CSL Behring | E17: CSL Behring | F17: Gene therapy (in vivo AAV) | G17: Hematology | H17: Serious (chronic, manageable) | I17: Sweden | J17: Full / standard HTA | K17: Health Economic Assessment with Scenario Analysis + NT-rådet recommendation | L17: Not recommended | M17: Negative | N17: Not Applicable | O17: Price/Cost-effectiveness | P17: 2023 | Q17: TLV assessment 18/09/2023; NT-rådet final recommendation 25/04/2025 | R17: Other / mixed comparator | S17: Prophylactic FIX concentrates | T17: Not specified / unclear | U17: Clinical evidence uncertainty + Price / cost-effectiveness | V17: TLV scenario: Hemgenix can be dominant if effect is sustained over model horizon, but uncertainty remains high; NT-rådet concluded it was not cost-effective after failed price reduction negotiation | W17: High scientific uncertainty and very high health-economic uncertainty; durability of one-time gene therapy effect unknown; no direct comparative study versus FIX prophylaxis; effect advantage versus current well-functioning treatment unclear | X17: Adults with severe or moderately severe hemophilia B without history of FIX inhibitors | Y17: NT-rådet recommended regions not to use Hemgenix. Negotiation did not produce sufficient cost reduction, and even an outcome-based agreement was judged insufficient | Z17: Clear negative access case. Current Swedish FIX prophylaxis is considered well-functioning, reducing disease severity and making the acceptable price for gene therapy harder to justify. | AA17: Primary xlsx database | AB17: 9 | AC17: =IF(OR($M17="Positive",$M17="Restricted Positive"),1,0) -> 0 | AD17: =IF($M17="Not Evaluated",0,1) -> 1 | AG17: no ICER reported; TLV scenario-dependent (dominant-to-uncertain) | AH17: Gene therapy | AI17: =IF(COUNTIFS($A$2:$A$175,$A17,$C$2:$C$175,$C17,$AC$2:$AC$175,1)>0,1,0) -> 1 | AJ17: =IFERROR(_xludf.MINIFS($P$2:$P$175,$A$2:$A$175,$A17,$C$2:$C$175,$C17,$AC$2:$AC$175,1),"")
A18: Hemgenix | B18: Etranacogene dezaparvovec | C18: Hemophilia B | D18: CSL Behring | E18: CSL Behring | F18: Gene therapy (in vivo AAV) | G18: Hematology | H18: Serious (chronic, manageable) | I18: Denmark | J18: Managed introduction / price negotiation | K18: Medicinrådet recommendation + reassessment + Amgros alternative price agreement | L18: 2023: Not recommended. 2024: Recommended | M18: Positive | N18: Broad | O18: N/A | P18: 2023 | Q18: Not recommended 22/11/2023; recommended 19/06/2024 | R18: Active comparator drug(s) | S18: FIX prophylaxis, especially Refixia | T18: Not specified / unclear | U18: Clinical evidence uncertainty + Price / cost-effectiveness | V18: No public ICER. 2023 analysis found Hemgenix could be dominant at AIP/SAIP but this was highly uncertain and dependent on long response duration. 2024 recommendation accepted costs as reasonable after alternative price agreement | W18: Long-term durability, sparse long-term safety data, uncertainty about how many patients will need to restart FIX prophylaxis | X18: Adults with severe or moderately severe hemophilia B without history of FIX inhibitors | Y18: Initial rejection due to price and uncertainty; later recommendation after new agreement where payment is linked to continued effect | Z18: Denmark is the positive contrast to Sweden: same core uncertainty, but access achieved through risk-sharing/payment-linked agreement. | AA18: Primary xlsx database | AB18: 9 | AC18: =IF(OR($M18="Positive",$M18="Restricted Positive"),1,0) -> 1 | AD18: =IF($M18="Not Evaluated",0,1) -> 1 | AH18: Gene therapy | AI18: =IF(COUNTIFS($A$2:$A$175,$A18,$C$2:$C$175,$C18,$AC$2:$AC$175,1)>0,1,0) -> 1 | AJ18: =IFERROR(_xludf.MINIFS($P$2:$P$175,$A$2:$A$175,$A18,$C$2:$C$175,$C18,$AC$2:$AC$175,1),"")
A19: Hemgenix | B19: Etranacogene dezaparvovec | C19: Hemophilia B | D19: CSL Behring | E19: CSL Behring | F19: Gene therapy (in vivo AAV) | G19: Hematology | H19: Serious (chronic, manageable) | I19: Norway | J19: Managed introduction / price negotiation | K19: Full Method Assessment (Metodevurdering) + Price Note | L19: Recommended / Introduced | M19: Positive | N19: Broad | O19: N/A | P19: 2026 | Q19: 2026-03-16 00:00:00 | R19: Active comparator drug(s) | S19: Standard FIX prophylaxis (factor IX replacement therapy) | T19: Not specified / unclear | U19: Clinical evidence uncertainty + Price / cost-effectiveness | V19: Full cost-effectiveness analysis conducted; ICER not publicly available due to confidential pricing | W19: Long-term durability of FIX expression; uncertainty regarding duration of treatment effect; extrapolation beyond trial follow-up | X19: Price must be equal to or lower than negotiated price; treatment centralized at Oslo University Hospital | Y19: DMP performed full HTA assessing severity, benefit, resource use, uncertainty and budget impact. Final approval followed price negotiations by Sykehusinnkjøp. | Z19: Major contrast with Sweden. Norway ultimately approved gene therapy after centralized negotiations and national funding. | AA19: Primary xlsx database | AB19: 9 | AC19: =IF(OR($M19="Positive",$M19="Restricted Positive"),1,0) -> 1 | AD19: =IF($M19="Not Evaluated",0,1) -> 1 | AH19: Gene therapy | AI19: =IF(COUNTIFS($A$2:$A$175,$A19,$C$2:$C$175,$C19,$AC$2:$AC$175,1)>0,1,0) -> 1 | AJ19: =IFERROR(_xludf.MINIFS($P$2:$P$175,$A$2:$A$175,$A19,$C$2:$C$175,$C19,$AC$2:$AC$175,1),"")
A20: Roctavian | B20: Valoctocogene roxaparvovec | C20: Hemophilia A | D20: BioMarin International Limited | E20: BioMarin | F20: Gene therapy (in vivo AAV) | G20: Hematology | H20: Serious (chronic, manageable) | I20: Sweden | J20: Full / standard HTA | K20: Health Economic Assessment with Scenario Analysis + NT-rådet wait recommendation | L20: Not recommended / wait; not marketed in Sweden | M20: Negative | N20: Not Applicable | O20: Administrative/Procedural | P20: 2024 | Q20: TLV assessment 29/08/2024; NT-rådet wait recommendation 19/12/2024 | R20: Active comparator drug(s) | S20: Prophylactic FVIII concentrates; Hemlibra considered in model | T20: Not specified / unclear | U20: Clinical evidence uncertainty | V20: TLV base scenario: Roctavian dominant versus FVIII prophylaxis, meaning more effective and lower cost, but only under uncertain assumptions about duration of effect and long-term cost offsets | W20: Very high uncertainty around durability of gene therapy effect, declining FVIII activity over time, representativeness of GENEr8-1 patients for Swedish well-controlled patients, HRQoL assumptions and lack of long-term data | X20: Adults with severe hemophilia A without history of FVIII inhibitors and without detectable AAV5 antibodies | Y20: TLV completed the health economic assessment, but NT-rådet could not proceed to final recommendation/contracting because BioMarin stated Roctavian would not be marketed in Sweden | Z20: Important “non-launch after HTA” case. Unlike Skysona, Sweden completed the HTA, but market access stopped because the company did not commercialize the medicine in Sweden. | AA20: Primary xlsx database | AB20: 10 | AC20: =IF(OR($M20="Positive",$M20="Restricted Positive"),1,0) -> 0 | AD20: =IF($M20="Not Evaluated",0,1) -> 1 | AG20: no ICER reported; TLV scenario-dependent (dominant under uncertain assumptions) | AH20: Gene therapy | AI20: =IF(COUNTIFS($A$2:$A$175,$A20,$C$2:$C$175,$C20,$AC$2:$AC$175,1)>0,1,0) -> 0 | AJ20: =IFERROR(_xludf.MINIFS($P$2:$P$175,$A$2:$A$175,$A20,$C$2:$C$175,$C20,$AC$2:$AC$175,1),"")
A21: Roctavian | B21: Valoctocogene roxaparvovec | C21: Hemophilia A | D21: BioMarin International Limited | E21: BioMarin | F21: Gene therapy (in vivo AAV) | G21: Hematology | H21: Serious (chronic, manageable) | I21: Denmark | J21: No formal assessment / not assessed | K21: Not assessed in Denmark | L21: Not assessed in Denmark | M21: Not Evaluated | N21: Not Applicable | O21: N/A | Q21: Not assessed in Denmark | R21: Not applicable / Not assessed | S21: Not assessed in Denmark | T21: Not specified / unclear | U21: Not specified | V21: Not assessed in Denmark | W21: Not assessed in Denmark | X21: Not assessed in Denmark | Y21: Not assessed in Denmark | Z21: Not assessed in Denmark | AA21: Primary xlsx database | AB21: 10 | AC21: =IF(OR($M21="Positive",$M21="Restricted Positive"),1,0) -> 0 | AD21: =IF($M21="Not Evaluated",0,1) -> 0 | AH21: Gene therapy | AI21: =IF(COUNTIFS($A$2:$A$175,$A21,$C$2:$C$175,$C21,$AC$2:$AC$175,1)>0,1,0) -> 0 | AJ21: =IFERROR(_xludf.MINIFS($P$2:$P$175,$A$2:$A$175,$A21,$C$2:$C$175,$C21,$AC$2:$AC$175,1),"")
A22: Roctavian | B22: Valoctocogene roxaparvovec | C22: Hemophilia A | D22: BioMarin International Limited | E22: BioMarin | F22: Gene therapy (in vivo AAV) | G22: Hematology | H22: Serious (chronic, manageable) | I22: Norway | J22: Rapid / simplified HTA | K22: Rapid HTA (Hurtig metodevurdering) + Cost-Utility Assessment | L22: Not launched / Withdrawn | M22: Withdrawn | N22: Not Applicable | O22: Administrative/Procedural | P22: 2025 | Q22: 2025-01-20 00:00:00 | R22: Active comparator drug(s) | S22: Standard FVIII prophylaxis | T22: Not specified / unclear | U22: Administrative/procedural + Clinical evidence uncertainty | V22: Evaluated but no reimbursement decision reached | W22: Durability of gene expression; long-term effectiveness; uncertainty around duration of benefit | Y22: Full assessment completed by DMP but manufacturer decided not to launch in Norway and subsequently withdrew product from market. | Z22: Similar outcome to Sweden, but due to manufacturer withdrawal rather than formal reimbursement rejection. | AA22: Primary xlsx database | AB22: 10 | AC22: =IF(OR($M22="Positive",$M22="Restricted Positive"),1,0) -> 0 | AD22: =IF($M22="Not Evaluated",0,1) -> 1 | AH22: Gene therapy | AI22: =IF(COUNTIFS($A$2:$A$175,$A22,$C$2:$C$175,$C22,$AC$2:$AC$175,1)>0,1,0) -> 0 | AJ22: =IFERROR(_xludf.MINIFS($P$2:$P$175,$A$2:$A$175,$A22,$C$2:$C$175,$C22,$AC$2:$AC$175,1),"")
A23: Hemlibra | B23: emicizumab | C23: Hemophilia A | D23: Roche AB | E23: Roche | F23: Monoclonal antibody (bispecific) | G23: Hematology | H23: Serious (chronic, manageable) | I23: Sweden | J23: Managed introduction / price negotiation | K23: Reimbursement/Subvention Assessment with Cost-Minimisation Analysis + side agreement | L23: Reimbursed / general subvention | M23: Positive | N23: Broad | O23: N/A | P23: 2022 | Q23: 2022-06-01 00:00:00 | R23: Best supportive care / no active treatment | S23: TLV used no treatment as formal comparator due to confidential FVIII net prices; FVIII prophylaxis clinically relevant | T23: Not specified / unclear | U23: Clinical evidence uncertainty + Price / cost-effectiveness | V23: No ICER reported; TLV used cost-minimisation and judged Hemlibra costs reasonable after side agreement | W23: Uncertainty from indirect comparisons, differences between study populations, lack of public net prices for FVIII concentrates, long-term treatment assumptions | X23: Hemophilia A with FVIII inhibitors and severe hemophilia A without inhibitors; all age groups within approved indication | Y23: Hemlibra had restricted reimbursement since 2018 and received broader/general reimbursement in 2022 after three-party negotiations and a side agreement | Z23: Essential market context for hemophilia A. Subcutaneous prophylaxis changed the treatment landscape and is relevant when assessing Roctavian’s incremental value. | AA23: Primary xlsx database | AB23: 11 | AC23: =IF(OR($M23="Positive",$M23="Restricted Positive"),1,0) -> 1 | AD23: =IF($M23="Not Evaluated",0,1) -> 1 | AG23: none public - cost-minimisation approach, not cost-utility | AH23: Monoclonal antibody | AI23: =IF(COUNTIFS($A$2:$A$175,$A23,$C$2:$C$175,$C23,$AC$2:$AC$175,1)>0,1,0) -> 1 | AJ23: =IFERROR(_xludf.MINIFS($P$2:$P$175,$A$2:$A$175,$A23,$C$2:$C$175,$C23,$AC$2:$AC$175,1),"")
A24: Hemlibra | B24: emicizumab | C24: Hemophilia A | D24: Roche AB | E24: Roche | F24: Monoclonal antibody (bispecific) | G24: Hematology | H24: Serious (chronic, manageable) | I24: Denmark | J24: Other / unclassified process | K24: Included in Medicinrådet hemophilia A treatment guideline and drug recommendation | L24: Recommended / established standard-of-care option | M24: Positive | N24: Broad | O24: N/A | P24: 2026 | Q24: Current hemophilia A recommendation effective 01/05/2026 | R24: Active comparator drug(s) | S24: FVIII prophylaxis and newer alternatives such as Altuvoct and marstacimab | T24: Not specified / unclear | U24: Comparator/positioning issue + Price / cost-effectiveness | V24: No ICER in current recommendation; ranked through treatment guideline and cost-based recommendation logic | W24: Treatment positioning, cost ranking, patient selection versus FVIII products | X24: Hemophilia A, especially patients where FVIII prophylaxis is unsuitable, insufficient or difficult to administer | Y24: Used as key comparator/context in later Danish hemophilia A evaluations | Z24: Essential context row. Hemlibra explains why hemophilia A gene therapies must prove value against a strong, convenient subcutaneous standard. | AA24: Primary xlsx database | AB24: 11 | AC24: =IF(OR($M24="Positive",$M24="Restricted Positive"),1,0) -> 1 | AD24: =IF($M24="Not Evaluated",0,1) -> 1 | AH24: Monoclonal antibody | AI24: =IF(COUNTIFS($A$2:$A$175,$A24,$C$2:$C$175,$C24,$AC$2:$AC$175,1)>0,1,0) -> 1 | AJ24: =IFERROR(_xludf.MINIFS($P$2:$P$175,$A$2:$A$175,$A24,$C$2:$C$175,$C24,$AC$2:$AC$175,1),"")
A25: Hemlibra | B25: emicizumab | C25: Hemophilia A | D25: Roche AB | E25: Roche | F25: Monoclonal antibody (bispecific) | G25: Hematology | H25: Serious (chronic, manageable) | I25: Norway | J25: Rapid / simplified HTA | K25: Rapid HTA (Hurtig metodevurdering) | L25: Recommended | M25: Positive | N25: Broad | O25: N/A | P25: 2018 | Q25: 2018-12-17 00:00:00 | R25: Active comparator drug(s) | S25: Bypassing agents and existing prophylaxis for inhibitor patients | T25: Not specified / unclear | U25: Not specified | V25: Cost-effectiveness assessment conducted; exact ICER confidential | W25: Limited long-term evidence and indirect comparisons | X25: Price equal to or below negotiated level | Y25: Approved for Hemophilia A patients with inhibitors after HTA review. | Z25: Became standard prophylaxis option for inhibitor population. | AA25: Primary xlsx database | AB25: 11 | AC25: =IF(OR($M25="Positive",$M25="Restricted Positive"),1,0) -> 1 | AD25: =IF($M25="Not Evaluated",0,1) -> 1 | AH25: Monoclonal antibody | AI25: =IF(COUNTIFS($A$2:$A$175,$A25,$C$2:$C$175,$C25,$AC$2:$AC$175,1)>0,1,0) -> 1 | AJ25: =IFERROR(_xludf.MINIFS($P$2:$P$175,$A$2:$A$175,$A25,$C$2:$C$175,$C25,$AC$2:$AC$175,1),"")
A26: Beqvez | B26: Fidanacogene elaparvovec | C26: Hemophilia B | D26: Pfizer | E26: Pfizer | F26: Gene therapy (in vivo AAV) | G26: Hematology | H26: Serious (chronic, manageable) | I26: Sweden | J26: No formal assessment / not assessed | K26: Not assessed in sweden - withdrawn drom European Commercialization | L26: Not assessed in sweden - withdrawn drom European Commercialization | M26: Withdrawn | N26: Not Applicable | O26: Administrative/Procedural | Q26: Not assessed in sweden - withdrawn drom European Commercialization | R26: Not applicable / Not assessed | S26: Not assessed in sweden - withdrawn drom European Commercialization | T26: Not specified / unclear | U26: Administrative/procedural | V26: Not assessed in sweden - withdrawn drom European Commercialization | W26: Not assessed in sweden - withdrawn drom European Commercialization | X26: Not assessed in sweden - withdrawn drom European Commercialization | Y26: Not assessed in sweden - withdrawn drom European Commercialization | Z26: Not assessed in sweden - withdrawn drom European Commercialization | AA26: Primary xlsx database | AB26: 12 | AC26: =IF(OR($M26="Positive",$M26="Restricted Positive"),1,0) -> 0 | AD26: =IF($M26="Not Evaluated",0,1) -> 1 | AG26: not assessed in Sweden | AH26: Gene therapy | AI26: =IF(COUNTIFS($A$2:$A$175,$A26,$C$2:$C$175,$C26,$AC$2:$AC$175,1)>0,1,0) -> 0 | AJ26: =IFERROR(_xludf.MINIFS($P$2:$P$175,$A$2:$A$175,$A26,$C$2:$C$175,$C26,$AC$2:$AC$175,1),"")
A27: Beqvez | B27: Fidanacogene elaparvovec | C27: Hemophilia B | D27: Pfizer | E27: Pfizer | F27: Gene therapy (in vivo AAV) | G27: Hematology | H27: Serious (chronic, manageable) | I27: Denmark | J27: Full / standard HTA | K27: Medicinrådet assessment initiated but discontinued | L27: Withdrawn | M27: Withdrawn | N27: Not Applicable | O27: Administrative/Procedural | P27: 2023 | Q27: Request received 12/11/2023; withdrawn 28/05/2024 | R27: Active comparator drug(s) | S27: Expected comparator: FIX prophylaxis | T27: Not specified / unclear | U27: Administrative/procedural + Clinical evidence uncertainty + Price / cost-effectiveness | V27: N/A | W27: Not assessed; expected uncertainty around durability, safety, comparative benefit and price | X27: Hemophilia B gene therapy population | Y27: Application withdrawn before recommendation | Z27: Important watchlist/failure-to-complete case. Denmark has access to Hemgenix, while Beqvez did not complete the Danish process. | AA27: Primary xlsx database | AB27: 12 | AC27: =IF(OR($M27="Positive",$M27="Restricted Positive"),1,0) -> 0 | AD27: =IF($M27="Not Evaluated",0,1) -> 1 | AH27: Gene therapy | AI27: =IF(COUNTIFS($A$2:$A$175,$A27,$C$2:$C$175,$C27,$AC$2:$AC$175,1)>0,1,0) -> 0 | AJ27: =IFERROR(_xludf.MINIFS($P$2:$P$175,$A$2:$A$175,$A27,$C$2:$C$175,$C27,$AC$2:$AC$175,1),"")
A28: Beqvez | B28: Fidanacogene elaparvovec | C28: Hemophilia B | D28: Pfizer | E28: Pfizer | F28: Gene therapy (in vivo AAV) | G28: Hematology | H28: Serious (chronic, manageable) | I28: Norway | J28: Other / unclassified process | K28: Withrawn from EMA | L28: Withrawn from EMA | M28: Withdrawn | N28: Not Applicable | O28: Administrative/Procedural | Q28: Withrawn from EMA | R28: Other / mixed comparator | S28: Withrawn from EMA | T28: Not specified / unclear | U28: Not specified | V28: Withrawn from EMA | W28: Withrawn from EMA | X28: Withrawn from EMA | Y28: Withrawn from EMA | Z28: Withrawn from EMA | AA28: Primary xlsx database | AB28: 12 | AC28: =IF(OR($M28="Positive",$M28="Restricted Positive"),1,0) -> 0 | AD28: =IF($M28="Not Evaluated",0,1) -> 1 | AH28: Gene therapy | AI28: =IF(COUNTIFS($A$2:$A$175,$A28,$C$2:$C$175,$C28,$AC$2:$AC$175,1)>0,1,0) -> 0 | AJ28: =IFERROR(_xludf.MINIFS($P$2:$P$175,$A$2:$A$175,$A28,$C$2:$C$175,$C28,$AC$2:$AC$175,1),"")
A29: Hympavzi | B29: marstacimab | C29: Hemophilia A and B | D29: Pfizer | E29: Pfizer | F29: Monoclonal antibody | G29: Hematology | H29: Serious (chronic, manageable) | I29: Sweden | J29: Early / horizon scanning only | K29: Early assessment / monitoring (no completed TLV reimbursement decision identified) | L29: No Swedish reimbursement decision identified / under market access monitoring | M29: Ongoing/Pending | N29: Not Applicable | O29: N/A | Q29: N/A | R29: Active comparator drug(s) | S29: Hemlibra, Alhemo, FVIII/FIX prophylaxis (expected comparators) | T29: Not specified / unclear | U29: Comparator/positioning issue | V29: N/A | W29: Pricing and positioning versus established non-factor prophylaxis therapies; limited Swedish HTA information currently available | X29: N/A | Y29: No completed Swedish HTA or reimbursement assessment identified at present. Appears mainly in pipeline and early assessment discussions. | Z29: Important emerging competitor. In Denmark it was directly incorporated into national treatment guidelines, highlighting different Nordic access approaches. | AA29: Primary xlsx database | AB29: 13 | AC29: =IF(OR($M29="Positive",$M29="Restricted Positive"),1,0) -> 0 | AD29: =IF($M29="Not Evaluated",0,1) -> 1 | AG29: ongoing/pending | AH29: Monoclonal antibody | AI29: =IF(COUNTIFS($A$2:$A$175,$A29,$C$2:$C$175,$C29,$AC$2:$AC$175,1)>0,1,0) -> 1 | AJ29: =IFERROR(_xludf.MINIFS($P$2:$P$175,$A$2:$A$175,$A29,$C$2:$C$175,$C29,$AC$2:$AC$175,1),"")
A30: Hympavzi | B30: marstacimab | C30: Hemophilia A and B | D30: Pfizer | E30: Pfizer | F30: Monoclonal antibody | G30: Hematology | H30: Serious (chronic, manageable) | I30: Denmark | J30: Other / unclassified process | K30: Direct placement into Medicinrådet hemophilia A and B treatment guidelines | L30: Recommended / placed in guideline | M30: Positive | N30: Broad | O30: N/A | P30: 2025 | Q30: Direct placement approved 03/09/2025; recommendation effective 01/05/2026 | R30: Active comparator drug(s) | S30: Hemlibra for hemophilia A; relevant hemophilia B prophylaxis alternatives | T30: Not specified / unclear | U30: Comparator/positioning issue | V30: No ICER; direct placement based on evidence review and Amgros negotiation | W30: Comparative evidence and positioning versus existing prophylaxis options | X30: Patients ≥12 years and ≥35 kg with severe hemophilia A or B without inhibitors | Y30: Added to both hemophilia A and B pathways | Z30: Not gene therapy, but important because it shows Denmark is actively expanding non-factor prophylaxis options. | AA30: Primary xlsx database | AB30: 13 | AC30: =IF(OR($M30="Positive",$M30="Restricted Positive"),1,0) -> 1 | AD30: =IF($M30="Not Evaluated",0,1) -> 1 | AH30: Monoclonal antibody | AI30: =IF(COUNTIFS($A$2:$A$175,$A30,$C$2:$C$175,$C30,$AC$2:$AC$175,1)>0,1,0) -> 1 | AJ30: =IFERROR(_xludf.MINIFS($P$2:$P$175,$A$2:$A$175,$A30,$C$2:$C$175,$C30,$AC$2:$AC$175,1),"")
A31: Hympavzi | B31: marstacimab | C31: Hemophilia A and B | D31: Pfizer | E31: Pfizer | F31: Monoclonal antibody | G31: Hematology | H31: Serious (chronic, manageable) | I31: Norway | J31: Full / standard HTA | K31: Single-drug Method Assessment (without full economic model) | L31: Under assessment / No final introduction decision identified | M31: Ongoing/Pending | N31: Not Applicable | O31: N/A | P31: 2026 | Q31: 03/02/2026 (assessment publication) | R31: Active comparator drug(s) | S31: Personalized FVIII/FIX prophylaxis; existing standard prophylaxis | T31: Not specified / unclear | U31: Not specified | V31: No ICER reported | W31: Clinical benefit versus optimized prophylaxis; higher annualized joint bleeding rates than existing individualized treatment strategies | X31: None yet | Y31: DMP completed clinical assessment for severe Hemophilia A and B without inhibitors. | Z31: Norway appears more cautious than Sweden regarding newer non-factor prophylaxis agents when effective standard factor treatment already exists. | AA31: Primary xlsx database | AB31: 13 | AC31: =IF(OR($M31="Positive",$M31="Restricted Positive"),1,0) -> 0 | AD31: =IF($M31="Not Evaluated",0,1) -> 1 | AH31: Monoclonal antibody | AI31: =IF(COUNTIFS($A$2:$A$175,$A31,$C$2:$C$175,$C31,$AC$2:$AC$175,1)>0,1,0) -> 1 | AJ31: =IFERROR(_xludf.MINIFS($P$2:$P$175,$A$2:$A$175,$A31,$C$2:$C$175,$C31,$AC$2:$AC$175,1),"")
A32: Alhemo | B32: concizumab | C32: Hemophilia B | D32: Novo Nordisk AB | E32: Novo Nordisk | F32: Monoclonal antibody | G32: Hematology | H32: Serious (chronic, manageable) | I32: Sweden | J32: Full / standard HTA | K32: Reimbursement/Subvention Assessment + Cost Comparison | L32: Reimbursed with restriction | M32: Restricted Positive | N32: Restricted | O32: N/A | P32: 2025 | Q32: 21/11/2025 (effective 25/11/2025) | R32: Active comparator drug(s) | S32: NovoSeven (eptacog alfa activated) | T32: Not specified / unclear | U32: Price / cost-effectiveness | V32: No ICER reported; cost-comparison approach. Lower treatment cost than NovoSeven | W32: No direct comparative trials; reliance on indirect comparison; differences between study populations and study designs | X32: Only reimbursed for Hemophilia B patients with inhibitors where immune tolerance induction (ITI) failed | Y32: TLV concluded Alhemo provides at least comparable efficacy with lower drug costs than NovoSeven, resulting in reimbursement for a narrow inhibitor population. | Z32: Good example of successful market access by targeting a small, high-cost niche population where economic value is easier to demonstrate. | AA32: Primary xlsx database | AB32: 14 | AC32: =IF(OR($M32="Positive",$M32="Restricted Positive"),1,0) -> 1 | AD32: =IF($M32="Not Evaluated",0,1) -> 1 | AG32: none public - cost-comparison approach, not cost-utility | AH32: Monoclonal antibody | AI32: =IF(COUNTIFS($A$2:$A$175,$A32,$C$2:$C$175,$C32,$AC$2:$AC$175,1)>0,1,0) -> 1 | AJ32: =IFERROR(_xludf.MINIFS($P$2:$P$175,$A$2:$A$175,$A32,$C$2:$C$175,$C32,$AC$2:$AC$175,1),"")
A33: Alhemo | B33: concizumab | C33: Hemophilia B | D33: Novo Nordisk AB | E33: Novo Nordisk | F33: Monoclonal antibody | G33: Hematology | H33: Serious (chronic, manageable) | I33: Denmark | J33: Other / unclassified process | K33: Direct placement into Medicinrådet hemophilia B treatment guideline | L33: Recommended / placed in guideline | M33: Positive | N33: Broad | O33: N/A | P33: 2026 | Q33: 2026-01-21 00:00:00 | R33: Active comparator drug(s) | S33: Marstacimab and other hemophilia B prophylaxis options | T33: Not specified / unclear | U33: Comparator/positioning issue | V33: No ICER; direct guideline placement | W33: Comparative evidence, patient positioning, safety and practical use | X33: Patients ≥12 years with hemophilia B without inhibitors | Y33: Concizumab was placed into the hemophilia B treatment pathway | Z33: Important non-factor competitor in hemophilia B. Helps explain why future gene therapies face more complex comparator landscapes. | AA33: Primary xlsx database | AB33: 14 | AC33: =IF(OR($M33="Positive",$M33="Restricted Positive"),1,0) -> 1 | AD33: =IF($M33="Not Evaluated",0,1) -> 1 | AH33: Monoclonal antibody | AI33: =IF(COUNTIFS($A$2:$A$175,$A33,$C$2:$C$175,$C33,$AC$2:$AC$175,1)>0,1,0) -> 1 | AJ33: =IFERROR(_xludf.MINIFS($P$2:$P$175,$A$2:$A$175,$A33,$C$2:$C$175,$C33,$AC$2:$AC$175,1),"")
A34: Alhemo | B34: concizumab | C34: Hemophilia B | D34: Novo Nordisk AB | E34: Novo Nordisk | F34: Monoclonal antibody | G34: Hematology | H34: Serious (chronic, manageable) | I34: Norway | J34: Full / standard HTA | K34: Requested assessment (method assessment without health-economic analysis planned) | L34: Cancelled / Withdrawn | M34: Withdrawn | N34: Not Applicable | O34: Administrative/Procedural | P34: 2025 | Q34: 2025-03-17 00:00:00 | R34: Active comparator drug(s) | S34: NovoSeven (expected comparator) | T34: Not specified / unclear | U34: Administrative/procedural | V34: Not assessed | W34: No assessment completed because manufacturer did not submit documentation within required timeframe | Y34: Bestillerforum cancelled the assessment after documentation was not submitted within 12 months. | Z34: Unlike Sweden, no reimbursement assessment was completed. Good example of pipeline attrition before decision stage. | AA34: Primary xlsx database | AB34: 14 | AC34: =IF(OR($M34="Positive",$M34="Restricted Positive"),1,0) -> 0 | AD34: =IF($M34="Not Evaluated",0,1) -> 1 | AH34: Monoclonal antibody | AI34: =IF(COUNTIFS($A$2:$A$175,$A34,$C$2:$C$175,$C34,$AC$2:$AC$175,1)>0,1,0) -> 1 | AJ34: =IFERROR(_xludf.MINIFS($P$2:$P$175,$A$2:$A$175,$A34,$C$2:$C$175,$C34,$AC$2:$AC$175,1),"")
A35: Altuvoct | B35: efanesoctocog alfa | C35: Hemophilia A | D35: Swedish Orphan Biovitrum AB (SOBI) | E35: Sobi (Swedish Orphan Biovitrum) | F35: Recombinant protein (extended half-life factor) | G35: Hematology | H35: Serious (chronic, manageable) | I35: Sweden | J35: Managed introduction / price negotiation | K35: Reimbursement/Subvention Assessment + Cost Comparison + side agreement | L35: Reimbursed with restriction | M35: Restricted Positive | N35: Restricted | O35: N/A | P35: 2025 | Q35: 25/09/2025 (effective 01/10/2025) | R35: Active comparator drug(s) | S35: Jivi (≥7 years), Elocta (<7 years), Hemlibra considered clinically relevant | T35: Not specified / unclear | U35: Clinical evidence uncertainty + Price / cost-effectiveness | V35: No ICER reported; cost-comparison approach. Cost judged acceptable only in pediatric subgroup after confidential side agreement | W35: Uncertainty regarding dose assumptions required to achieve comparable efficacy; comparison based largely on pharmacokinetic modelling and indirect evidence; uncertainty around true comparative benefit versus intensified FVIII prophylaxis | X35: Severe Hemophilia A children only; repeated breakthrough bleeds despite prophylactic treatment with another FVIII concentrate | Y35: TLV concluded Altuvoct provides comparable bleeding protection to intensified FVIII prophylaxis but is more expensive for the overall population. Side agreement reduced net cost sufficiently for pediatric reimbursement only. | Z35: Illustrates Sweden’s willingness to reimburse incremental innovation when accompanied by price concessions and narrow patient restrictions. NT-rådet later coordinated a regional agreement (2026–2028). | AA35: Primary xlsx database | AB35: 15 | AC35: =IF(OR($M35="Positive",$M35="Restricted Positive"),1,0) -> 1 | AD35: =IF($M35="Not Evaluated",0,1) -> 1 | AG35: none public - cost-comparison approach, not cost-utility | AH35: Recombinant protein | AI35: =IF(COUNTIFS($A$2:$A$175,$A35,$C$2:$C$175,$C35,$AC$2:$AC$175,1)>0,1,0) -> 1 | AJ35: =IFERROR(_xludf.MINIFS($P$2:$P$175,$A$2:$A$175,$A35,$C$2:$C$175,$C35,$AC$2:$AC$175,1),"")
A36: Altuvoct | B36: efanesoctocog alfa | C36: Hemophilia A | D36: Swedish Orphan Biovitrum AB (SOBI) | E36: Sobi (Swedish Orphan Biovitrum) | F36: Recombinant protein (extended half-life factor) | G36: Hematology | H36: Serious (chronic, manageable) | I36: Denmark | J36: Other / unclassified process | K36: Medicinrådet recommendation with cost-minimisation analysis | L36: Recommended for a limited subgroup | M36: Restricted Positive | N36: Restricted | O36: Clinical evidence uncertainty | P36: 2024 | Q36: 2024-10-23 00:00:00 | R36: Active comparator drug(s) | S36: Emicizumab/Hemlibra; FVIII EHL products as pathway context | T36: Not specified / unclear | U36: Price / cost-effectiveness | V36: No ICER; cost-minimisation versus emicizumab | W36: Comparative evidence versus emicizumab, patient weight assumptions, price relative to existing FVIII products | X36: Smaller group of severe hemophilia A patients not sufficiently protected by current FVIII prophylaxis | Y36: Recommended only for patients not well treated with other FVIII products | Z36: Important pathway context. Denmark limits use because it is cheaper than emicizumab but more expensive than most FVIII products. | AA36: Primary xlsx database | AB36: 15 | AC36: =IF(OR($M36="Positive",$M36="Restricted Positive"),1,0) -> 1 | AD36: =IF($M36="Not Evaluated",0,1) -> 1 | AH36: Recombinant protein | AI36: =IF(COUNTIFS($A$2:$A$175,$A36,$C$2:$C$175,$C36,$AC$2:$AC$175,1)>0,1,0) -> 1 | AJ36: =IFERROR(_xludf.MINIFS($P$2:$P$175,$A$2:$A$175,$A36,$C$2:$C$175,$C36,$AC$2:$AC$175,1),"")
A37: Altuvoct | B37: efanesoctocog alfa | C37: Hemophilia A | D37: Swedish Orphan Biovitrum AB (SOBI) | E37: Sobi (Swedish Orphan Biovitrum) | F37: Recombinant protein (extended half-life factor) | G37: Hematology | H37: Serious (chronic, manageable) | I37: Norway | J37: Managed introduction / price negotiation | K37: Subgroup reassessment request after prior decision | L37: Not recommended / Under renegotiation | M37: Negative | N37: Not Applicable | O37: Price/Cost-effectiveness | P37: 2026 | Q37: 02/02/2026 (new submission) | R37: Active comparator drug(s) | S37: Existing long-acting FVIII prophylaxis | T37: Not specified / unclear | U37: Price / cost-effectiveness | V37: Not publicly available | W37: Clinical value relative to existing FVIII products at proposed price | X37: Restricted subgroup proposed in renegotiation | Y37: Company submitted a restricted-population request following earlier Beslutningsforum decision and ongoing negotiations with Sykehusinnkjøp. | Z37: Strong example of Norway’s stricter stance toward expensive maintenance therapies compared with Sweden. | AA37: Primary xlsx database | AB37: 15 | AC37: =IF(OR($M37="Positive",$M37="Restricted Positive"),1,0) -> 0 | AD37: =IF($M37="Not Evaluated",0,1) -> 1 | AH37: Recombinant protein | AI37: =IF(COUNTIFS($A$2:$A$175,$A37,$C$2:$C$175,$C37,$AC$2:$AC$175,1)>0,1,0) -> 1 | AJ37: =IFERROR(_xludf.MINIFS($P$2:$P$175,$A$2:$A$175,$A37,$C$2:$C$175,$C37,$AC$2:$AC$175,1),"")
A38: Vyjuvek | B38: Beremagene geperpavec | C38: Dystrophic epidermolysis bullosa (DEB) | D38: Krystal Biotech | E38: Krystal Biotech | F38: Gene therapy (topical HSV vector) | G38: Dermatology | H38: Severe (progressive, life-shortening) | I38: Sweden | J38: Full / standard HTA | K38: Planned TLV health economic assessment + NT-rådet wait recommendation | L38: Pending / wait recommendation | M38: Ongoing/Pending | N38: Not Applicable | O38: N/A | P38: 2025 | Q38: NT-rådet wait recommendation: 28/08/2025 | R38: Best supportive care / no active treatment | S38: Expected: best supportive wound care / standard wound care | T38: Not specified / unclear | U38: Clinical evidence uncertainty + Price / cost-effectiveness | V38: Not available yet | W38: Full value assessment not yet completed; uncertainty around clinical value, cost-effectiveness and equal national introduction | X38: Treatment of wounds in patients with dystrophic EB with COL7A1 mutation(s), from birth | Y38: NT-rådet recommends regions wait until TLV completes the health economic assessment and NT-rådet can make a full recommendation. | Z38: Important upcoming gene therapy case for DEB. Sweden is preventing unequal early uptake while assessment is ongoing. | AA38: Primary xlsx database | AB38: 16 | AC38: =IF(OR($M38="Positive",$M38="Restricted Positive"),1,0) -> 0 | AD38: =IF($M38="Not Evaluated",0,1) -> 1 | AG38: not available yet | AH38: Gene therapy | AI38: =IF(COUNTIFS($A$2:$A$175,$A38,$C$2:$C$175,$C38,$AC$2:$AC$175,1)>0,1,0) -> 0 | AJ38: =IFERROR(_xludf.MINIFS($P$2:$P$175,$A$2:$A$175,$A38,$C$2:$C$175,$C38,$AC$2:$AC$175,1),"")
A39: Vyjuvek | B39: Beremagene geperpavec | C39: Dystrophic epidermolysis bullosa (DEB) | D39: Krystal Biotech | E39: Krystal Biotech | F39: Gene therapy (topical HSV vector) | G39: Dermatology | H39: Severe (progressive, life-shortening) | I39: Denmark | J39: No formal assessment / not assessed | K39: No assessment in Denmark | L39: No assessment in Denmark | M39: Not Evaluated | N39: Not Applicable | O39: N/A | Q39: No assessment in Denmark | R39: Not applicable / Not assessed | S39: No assessment in Denmark | T39: Not specified / unclear | U39: Not specified | V39: No assessment in Denmark | W39: No assessment in Denmark | X39: No assessment in Denmark | Y39: No assessment in Denmark | Z39: No assessment in Denmark | AA39: Primary xlsx database | AB39: 16 | AC39: =IF(OR($M39="Positive",$M39="Restricted Positive"),1,0) -> 0 | AD39: =IF($M39="Not Evaluated",0,1) -> 0 | AH39: Gene therapy | AI39: =IF(COUNTIFS($A$2:$A$175,$A39,$C$2:$C$175,$C39,$AC$2:$AC$175,1)>0,1,0) -> 0 | AJ39: =IFERROR(_xludf.MINIFS($P$2:$P$175,$A$2:$A$175,$A39,$C$2:$C$175,$C39,$AC$2:$AC$175,1),"")
A40: Vyjuvek | B40: Beremagene geperpavec | C40: Dystrophic epidermolysis bullosa (DEB) | D40: Krystal Biotech | E40: Krystal Biotech | F40: Gene therapy (topical HSV vector) | G40: Dermatology | H40: Severe (progressive, life-shortening) | I40: Norway | J40: Other / unclassified process | K40: Nye Metoder assessment initiated | L40: Pending | M40: Ongoing/Pending | N40: Not Applicable | O40: N/A | P40: 2025 | Q40: Assessment request / process initiated in 2025 | R40: Best supportive care / no active treatment | S40: Expected: standard wound care / best supportive care | T40: Not specified / unclear | U40: Clinical evidence uncertainty + Price / cost-effectiveness | V40: Not available yet | W40: Long-term effect, durability of wound closure, cost-effectiveness and treatment use in practice | X40: DEB wounds with COL7A1 mutation(s) | Y40: Vyjuvek is in the Norwegian pipeline under Nye Metoder; final decision not yet available | Z40: Keep as ongoing/pending. | AA40: Primary xlsx database | AB40: 16 | AC40: =IF(OR($M40="Positive",$M40="Restricted Positive"),1,0) -> 0 | AD40: =IF($M40="Not Evaluated",0,1) -> 1 | AH40: Gene therapy | AI40: =IF(COUNTIFS($A$2:$A$175,$A40,$C$2:$C$175,$C40,$AC$2:$AC$175,1)>0,1,0) -> 0 | AJ40: =IFERROR(_xludf.MINIFS($P$2:$P$175,$A$2:$A$175,$A40,$C$2:$C$175,$C40,$AC$2:$AC$175,1),"")
A41: Filsuvez | B41: birch triterpenes / bjørkeneverekstrakt | C41: Dystrophic epidermolysis bullosa (DEB) | D41: Chiesi Pharma AB | E41: Chiesi Group | F41: Other biologic/plant-derived | G41: Dermatology | H41: Severe (progressive, life-shortening) | I41: Sweden | J41: Full / standard HTA | K41: TLV reimbursement/subvention assessment with cost-utility analysis | L41: Not recommended / rejected | M41: Negative | N41: Not Applicable | O41: Price/Cost-effectiveness | P41: 2025 | Q41: 2025-04-24 00:00:00 | R41: Best supportive care / no active treatment | S41: No addition to best supportive care | T41: Not specified / unclear | U41: Clinical evidence uncertainty + Price / cost-effectiveness | V41: TLV scenario: approx. SEK 2.1M/QALY; sensitivity analyses approx. SEK 1.2–2.8M/QALY | W41: Very high uncertainty around long-term effect, quality-of-life benefit, model structure, wound heterogeneity and sustained effect after 90 days | X41: Patients ≥6 months with partial-thickness wounds associated with DEB or JEB | Y41: TLV found better wound-healing effect but judged costs not reasonable in relation to benefit. Application rejected. | Z41: Strong negative access case: clinical benefit acknowledged, but not enough to justify price. | AA41: Primary xlsx database | AB41: 17 | AC41: =IF(OR($M41="Positive",$M41="Restricted Positive"),1,0) -> 0 | AD41: =IF($M41="Not Evaluated",0,1) -> 1 | AE41: 1200000 | AF41: 2800000 | AG41: range (TLV scenario ~2.1M, sensitivity 1.2-2.8M) | AH41: Other biologic | AI41: =IF(COUNTIFS($A$2:$A$175,$A41,$C$2:$C$175,$C41,$AC$2:$AC$175,1)>0,1,0) -> 0 | AJ41: =IFERROR(_xludf.MINIFS($P$2:$P$175,$A$2:$A$175,$A41,$C$2:$C$175,$C41,$AC$2:$AC$175,1),"")
A42: Filsuvez | B42: birch triterpenes / bjørkeneverekstrakt | C42: Dystrophic epidermolysis bullosa (DEB) | D42: Chiesi Pharma AB | E42: Chiesi Group | F42: Other biologic/plant-derived | G42: Dermatology | H42: Severe (progressive, life-shortening) | I42: Denmark | J42: Full / standard HTA | K42: Medicinrådet clinical and health economic assessment | L42: Not recommended | M42: Negative | N42: Not Applicable | O42: Price/Cost-effectiveness | P42: 2025 | Q42: 2025-06-18 00:00:00 | R42: Best supportive care / no active treatment | S42: Standard of care / existing wound care | T42: Not specified / unclear | U42: Clinical evidence uncertainty + Price / cost-effectiveness | V42: AIP ICER approx. DKK 6.27M/QALY; QALY gain approx. 0.7 | W42: Uncertain quality-of-life effect, uncertain long-term clinical benefit, uncertain patient-level medicine use and wound burden | X42: Patients >6 months with partial-thickness wounds associated with DEB or JEB | Y42: Medicinrådet found faster wound healing, around 38 vs 45 days, but considered added costs unreasonable versus health gain. | Z42: Similar to Sweden: small clinical benefit, high cost, high uncertainty. | AA42: Primary xlsx database | AB42: 17 | AC42: =IF(OR($M42="Positive",$M42="Restricted Positive"),1,0) -> 0 | AD42: =IF($M42="Not Evaluated",0,1) -> 1 | AH42: Other biologic | AI42: =IF(COUNTIFS($A$2:$A$175,$A42,$C$2:$C$175,$C42,$AC$2:$AC$175,1)>0,1,0) -> 0 | AJ42: =IFERROR(_xludf.MINIFS($P$2:$P$175,$A$2:$A$175,$A42,$C$2:$C$175,$C42,$AC$2:$AC$175,1),"")
A43: Filsuvez | B43: birch triterpenes / bjørkeneverekstrakt | C43: Dystrophic epidermolysis bullosa (DEB) | D43: Chiesi Pharma AB | E43: Chiesi Group | F43: Other biologic/plant-derived | G43: Dermatology | H43: Severe (progressive, life-shortening) | I43: Norway | J43: Managed introduction / price negotiation | K43: Nye Metoder method assessment with health economic analysis + price note process | L43: Pending final decision | M43: Ongoing/Pending | N43: Not Applicable | O43: N/A | P43: 2025 | Q43: Bestillerforum decision: 26/05/2025; HTA published 04/12/2025 | R43: Best supportive care / no active treatment | S43: Current standard EB treatment / standard wound care | T43: Not specified / unclear | U43: Price / cost-effectiveness | V43: Not final/public decision yet | W43: Long-term effect, resource use, quality-of-life benefit and cost-effectiveness | X43: Patients ≥6 months with partial-thickness wounds associated with DEB or JEB | Y43: DMP delivered the method assessment; Sykehusinnkjøp is responsible for price negotiations and price note before Beslutningsforum decision. | Z43: Norway is further along than Finland but not yet at final reimbursement decision. | AA43: Primary xlsx database | AB43: 17 | AC43: =IF(OR($M43="Positive",$M43="Restricted Positive"),1,0) -> 0 | AD43: =IF($M43="Not Evaluated",0,1) -> 1 | AH43: Other biologic | AI43: =IF(COUNTIFS($A$2:$A$175,$A43,$C$2:$C$175,$C43,$AC$2:$AC$175,1)>0,1,0) -> 0 | AJ43: =IFERROR(_xludf.MINIFS($P$2:$P$175,$A$2:$A$175,$A43,$C$2:$C$175,$C43,$AC$2:$AC$175,1),"")
A44: Elfabrio | B44: Pegunigalsidase alfa | C44: Fabry disease | D44: Chiesi Pharma AB | E44: Chiesi Group | F44: Enzyme replacement therapy | G44: Metabolic/Lysosomal storage | H44: Severe (progressive, life-shortening) | I44: Sweden | J44: Managed introduction / price negotiation | K44: TLV reimbursement assessment, followed by TLV class reassessment of all Fabry medicines | L44: 2023: Reimbursed. 2025: Excluded from high-cost protection from 01/02/2026 after reassessment | M44: Negative | N44: Not Applicable | O44: Price/Cost-effectiveness | P44: 2023 | Q44: Elfabrio included from 18/11/2023; Fabry class reassessment decision 30/01/2025; exclusion effective 01/02/2026 | R44: Active comparator drug(s) | S44: Initial Elfabrio assessment: Fabrazyme/agalsidase beta. Class reassessment: no treatment as hypothetical comparator | T44: Not specified / unclear | U44: Clinical evidence uncertainty + Price / cost-effectiveness | V44: ICER not clearly available in current notes. TLV concluded costs were substantially higher than what is usually considered reasonable regardless of disease severity | W44: Main issue was not lack of clinical benefit, but unacceptable cost at current prices. No side agreements were reached. Uncertainty around whether current prices were reasonable given long-term treatment costs | X44: Adult patients with Fabry disease. In the class reassessment, Elfabrio, Fabrazyme, Replagal and Galafold were all reassessed together | Y44: TLV accepted that all Fabry medicines provide better effect than no treatment, but decided the costs were not reasonable. Long transition period was granted to avoid sudden disruption of care | Z44: Important negative pricing-pressure case. Sweden did not reject Fabry treatment clinically; it removed the whole class from reimbursement to force new regional solutions/pricing outside the high-cost protection system | AA44: Primary xlsx database | AB44: 18 | AC44: =IF(OR($M44="Positive",$M44="Restricted Positive"),1,0) -> 0 | AD44: =IF($M44="Not Evaluated",0,1) -> 1 | AG44: not clearly available; TLV stated cost was 'substantially higher than usually considered reasonable' | AH44: Enzyme replacement therapy | AI44: =IF(COUNTIFS($A$2:$A$175,$A44,$C$2:$C$175,$C44,$AC$2:$AC$175,1)>0,1,0) -> 1 | AJ44: =IFERROR(_xludf.MINIFS($P$2:$P$175,$A$2:$A$175,$A44,$C$2:$C$175,$C44,$AC$2:$AC$175,1),"")
A45: Elfabrio | B45: Pegunigalsidase alfa | C45: Fabry disease | D45: Chiesi Pharma AB | E45: Chiesi Group | F45: Enzyme replacement therapy | G45: Metabolic/Lysosomal storage | H45: Severe (progressive, life-shortening) | I45: Denmark | J45: Managed introduction / price negotiation | K45: Medicinrådet assessment, followed by Fabry treatment guideline, drug recommendation and Amgros tender | L45: Initially not recommended as standard treatment in 2024 due to price; later recommended after treatment guideline and tender | M45: Positive | N45: Broad | O45: N/A | P45: 2024 | Q45: Original decision 24/01/2024; treatment recommendation approved 26/03/2025; effective from 01/08/2025 | R45: Active comparator drug(s) | S45: Other Fabry treatments, especially agalsidase beta/Fabrazyme and other ERTs considered clinically comparable | T45: Not specified / unclear | U45: Price / cost-effectiveness | V45: ICER not publicly central in current notes. Decision driven by tender outcome: Elfabrio became clearly cheaper than the other clinically equivalent Fabry medicines | W45: Main issue was price relative to clinically comparable alternatives. After equivalence assessment, economic competition became decisive | X45: Recommended for Fabry disease. New patients should start on pegunigalsidase alfa, and as many existing patients as possible should switch where clinically appropriate | Y45: Medicinrådet created a treatment guideline to enable price competition in a high-cost rare disease area. Amgros tender made Elfabrio the cheapest option | Z45: Strong positive market access case. Denmark moved from rejection to recommendation once Elfabrio became the lowest-cost clinically equivalent option. This is a clear procurement-driven access model | AA45: Primary xlsx database | AB45: 18 | AC45: =IF(OR($M45="Positive",$M45="Restricted Positive"),1,0) -> 1 | AD45: =IF($M45="Not Evaluated",0,1) -> 1 | AH45: Enzyme replacement therapy | AI45: =IF(COUNTIFS($A$2:$A$175,$A45,$C$2:$C$175,$C45,$AC$2:$AC$175,1)>0,1,0) -> 1 | AJ45: =IFERROR(_xludf.MINIFS($P$2:$P$175,$A$2:$A$175,$A45,$C$2:$C$175,$C45,$AC$2:$AC$175,1),"")
A46: Elfabrio | B46: Pegunigalsidase alfa | C46: Fabry disease | D46: Chiesi Pharma AB | E46: Chiesi Group | F46: Enzyme replacement therapy | G46: Metabolic/Lysosomal storage | H46: Severe (progressive, life-shortening) | I46: Norway | J46: Rapid / simplified HTA | K46: Nye Metoder simplified method assessment with Sykehusinnkjøp price note | L46: Initially not introduced; later introduced after renewed price negotiations | M46: Positive | N46: Broad | O46: N/A | P46: 2023 | Q46: Not introduced 28/08/2023; introduced 23/10/2023; use from 01/12/2023 | R46: Active comparator drug(s) | S46: Existing Fabry treatments in procurement: Replagal/agalsidase alfa, Fabrazyme/agalsidase beta and Galafold/migalastat | T46: Not specified / unclear | U46: Price / cost-effectiveness | V46: No public ICER. Cost-effectiveness was not calculated; price comparison/procurement logic was central | W46: Benefit was not initially considered reasonable relative to price. Clinical evidence did not show clear superiority over agalsidase beta; cost-effectiveness was not calculated | X46: Long-term enzyme replacement therapy in adults with confirmed Fabry disease | Y46: DMP/NoMA used a simplified assessment because the mechanism was known, other ERTs were already in use, and Elfabrio was not expected to increase patient numbers | Z46: Classic Norwegian negotiation case: first no, then yes after improved price. Access depends on price being equal to or lower than the negotiated basis for the decision | AA46: Primary xlsx database | AB46: 18 | AC46: =IF(OR($M46="Positive",$M46="Restricted Positive"),1,0) -> 1 | AD46: =IF($M46="Not Evaluated",0,1) -> 1 | AH46: Enzyme replacement therapy | AI46: =IF(COUNTIFS($A$2:$A$175,$A46,$C$2:$C$175,$C46,$AC$2:$AC$175,1)>0,1,0) -> 1 | AJ46: =IFERROR(_xludf.MINIFS($P$2:$P$175,$A$2:$A$175,$A46,$C$2:$C$175,$C46,$AC$2:$AC$175,1),"")
A47: Fabrazyme | B47: Agalsidase beta | C47: Fabry disease | D47: Sanofi | E47: Sanofi | F47: Enzyme replacement therapy | G47: Metabolic/Lysosomal storage | H47: Severe (progressive, life-shortening) | I47: Sweden | J47: Managed introduction / price negotiation | K47: TLV class reassessment of Fabry medicines | L47: Excluded from high-cost protection from 01/02/2026 | M47: Negative | N47: Not Applicable | O47: Price/Cost-effectiveness | P47: 2025 | Q47: Decision 30/01/2025; effective 01/02/2026 | R47: Best supportive care / no active treatment | S47: No treatment, as hypothetical comparator | T47: Not specified / unclear | U47: Comparator/positioning issue + Price / cost-effectiveness | V47: ICER not available | W47: Cost+J19:N19 considered too high at current price; no side agreement reached | X47: Fabry disease treatment; previously reimbursed within high-cost protection | Y47: Reassessed together with Replagal, Galafold and Elfabrio | Z47: Established ERT and key comparator. Sweden accepted benefit but rejected current price level | AA47: Primary xlsx database | AB47: 19 | AC47: =IF(OR($M47="Positive",$M47="Restricted Positive"),1,0) -> 0 | AD47: =IF($M47="Not Evaluated",0,1) -> 1 | AG47: none public | AH47: Enzyme replacement therapy | AI47: =IF(COUNTIFS($A$2:$A$175,$A47,$C$2:$C$175,$C47,$AC$2:$AC$175,1)>0,1,0) -> 1 | AJ47: =IFERROR(_xludf.MINIFS($P$2:$P$175,$A$2:$A$175,$A47,$C$2:$C$175,$C47,$AC$2:$AC$175,1),"")
A48: Fabrazyme | B48: Agalsidase beta | C48: Fabry disease | D48: Sanofi | E48: Sanofi | F48: Enzyme replacement therapy | G48: Metabolic/Lysosomal storage | H48: Severe (progressive, life-shortening) | I48: Denmark | J48: Other / unclassified process | K48: Medicinrådet treatment guideline and drug recommendation for Fabry disease | L48: Not first-choice after 2025 recommendation | M48: Restricted Positive | N48: Restricted | O48: Comparator/positioning | P48: 2025 | Q48: Recommendation approved 26/03/2025; effective 01/08/2025 | R48: Active comparator drug(s) | S48: Other Fabry treatments, especially Elfabrio and Replagal | T48: Not specified / unclear | U48: Comparator/positioning issue + Price / cost-effectiveness | V48: ICER not central/not available | W48: Considered clinically comparable to Elfabrio, but more expensive after tender | X48: Fabry disease; may remain relevant if patient-specific reasons prevent switching | Y48: Included in guideline but not selected in drug recommendation because Elfabrio won on price | Z48: Important comparator, but Denmark now prioritises Elfabrio as cheaper equivalent ERT | AA48: Primary xlsx database | AB48: 19 | AC48: =IF(OR($M48="Positive",$M48="Restricted Positive"),1,0) -> 1 | AD48: =IF($M48="Not Evaluated",0,1) -> 1 | AH48: Enzyme replacement therapy | AI48: =IF(COUNTIFS($A$2:$A$175,$A48,$C$2:$C$175,$C48,$AC$2:$AC$175,1)>0,1,0) -> 1 | AJ48: =IFERROR(_xludf.MINIFS($P$2:$P$175,$A$2:$A$175,$A48,$C$2:$C$175,$C48,$AC$2:$AC$175,1),"")
A49: Fabrazyme | B49: Agalsidase beta | C49: Fabry disease | D49: Sanofi | E49: Sanofi | F49: Enzyme replacement therapy | G49: Metabolic/Lysosomal storage | H49: Severe (progressive, life-shortening) | I49: Norway | J49: Managed introduction / price negotiation | K49: Included in Sykehusinnkjøp Fabry procurement/tender | L49: Available / established treatment | M49: Positive | N49: Broad | O49: N/A | Q49: Existing before Elfabrio; tender dates vary | R49: Active comparator drug(s) | S49: Replagal, Galafold, Elfabrio | T49: Not specified / unclear | U49: Comparator/positioning issue + Price / cost-effectiveness | V49: ICER not available | W49: Price ranking and procurement position | X49: Fabry disease according to specialist use | Y49: ICER not available Established ERT in Norwegian Fabry tender system | Z49: Main comparator for Elfabrio. No new individual Nye Metoder assessment identified | AA49: Primary xlsx database | AB49: 19 | AC49: =IF(OR($M49="Positive",$M49="Restricted Positive"),1,0) -> 1 | AD49: =IF($M49="Not Evaluated",0,1) -> 1 | AH49: Enzyme replacement therapy | AI49: =IF(COUNTIFS($A$2:$A$175,$A49,$C$2:$C$175,$C49,$AC$2:$AC$175,1)>0,1,0) -> 1 | AJ49: =IFERROR(_xludf.MINIFS($P$2:$P$175,$A$2:$A$175,$A49,$C$2:$C$175,$C49,$AC$2:$AC$175,1),"")
A50: Replagal | B50: Agalsidase alfa | C50: Fabry disease | D50: Takeda/Shire | E50: Takeda | F50: Enzyme replacement therapy | G50: Metabolic/Lysosomal storage | H50: Severe (progressive, life-shortening) | I50: Sweden | J50: Managed introduction / price negotiation | K50: TLV class reassessment of Fabry medicines | L50: Excluded from high-cost protection from 01/02/2026 | M50: Negative | N50: Not Applicable | O50: Price/Cost-effectiveness | P50: 2025 | Q50: Decision 30/01/2025; effective 01/02/2026 | R50: Best supportive care / no active treatment | S50: No treatment, as hypothetical comparator | T50: Not specified / unclear | U50: Price / cost-effectiveness | V50: ICER not available | W50: Cost considered too high at current price; no side agreement reached | X50: Fabry disease treatment; previously reimbursed within high-cost protection | Y50: Reassessed together with Fabrazyme, Galafold and Elfabrio | Z50: Historical ERT standard. Sweden accepted benefit but rejected current price level | AA50: Primary xlsx database | AB50: 20 | AC50: =IF(OR($M50="Positive",$M50="Restricted Positive"),1,0) -> 0 | AD50: =IF($M50="Not Evaluated",0,1) -> 1 | AG50: none public | AH50: Enzyme replacement therapy | AI50: =IF(COUNTIFS($A$2:$A$175,$A50,$C$2:$C$175,$C50,$AC$2:$AC$175,1)>0,1,0) -> 1 | AJ50: =IFERROR(_xludf.MINIFS($P$2:$P$175,$A$2:$A$175,$A50,$C$2:$C$175,$C50,$AC$2:$AC$175,1),"")
A51: Replagal | B51: Agalsidase alfa | C51: Fabry disease | D51: Takeda/Shire | E51: Takeda | F51: Enzyme replacement therapy | G51: Metabolic/Lysosomal storage | H51: Severe (progressive, life-shortening) | I51: Denmark | J51: Other / unclassified process | K51: Medicinrådet treatment guideline and drug recommendation for Fabry disease | L51: Not first-choice after 2025 recommendation | M51: Restricted Positive | N51: Restricted | O51: Comparator/positioning | P51: 2025 | Q51: Recommendation approved 26/03/2025; effective 01/08/2025 | R51: Active comparator drug(s) | S51: Other Fabry treatments, especially Elfabrio and Fabrazyme | T51: Not specified / unclear | U51: Price / cost-effectiveness | V51: ICER not central/not available | W51: Considered part of clinically comparable ERT landscape, but not cheapest after tende | X51: Fabry disease; may remain relevant for patients who cannot switch | Y51: Included in treatment guideline but not selected as recommended first-choice | Z51: Historical standard of care but displaced by Elfabrio in Denmark due to price competition | AA51: Primary xlsx database | AB51: 20 | AC51: =IF(OR($M51="Positive",$M51="Restricted Positive"),1,0) -> 1 | AD51: =IF($M51="Not Evaluated",0,1) -> 1 | AH51: Enzyme replacement therapy | AI51: =IF(COUNTIFS($A$2:$A$175,$A51,$C$2:$C$175,$C51,$AC$2:$AC$175,1)>0,1,0) -> 1 | AJ51: =IFERROR(_xludf.MINIFS($P$2:$P$175,$A$2:$A$175,$A51,$C$2:$C$175,$C51,$AC$2:$AC$175,1),"")
A52: Replagal | B52: Agalsidase alfa | C52: Fabry disease | D52: Takeda/Shire | E52: Takeda | F52: Enzyme replacement therapy | G52: Metabolic/Lysosomal storage | H52: Severe (progressive, life-shortening) | I52: Norway | J52: Managed introduction / price negotiation | K52: Included in Sykehusinnkjøp Fabry procurement/tender | L52: Available / established treatment | M52: Positive | N52: Broad | O52: N/A | Q52: Existing before Elfabrio; tender dates var | R52: Active comparator drug(s) | S52: Fabrazyme, Galafold, Elfabrio | T52: Not specified / unclear | U52: Comparator/positioning issue + Price / cost-effectiveness | V52: ICER not available | W52: Price ranking and procurement position | X52: Fabry disease according to specialist use | Y52: Established ERT in Norwegian Fabry tender system | Z52: Important switch comparator for Elfabrio. No separate new Nye Metoder decision identified | AA52: Primary xlsx database | AB52: 20 | AC52: =IF(OR($M52="Positive",$M52="Restricted Positive"),1,0) -> 1 | AD52: =IF($M52="Not Evaluated",0,1) -> 1 | AH52: Enzyme replacement therapy | AI52: =IF(COUNTIFS($A$2:$A$175,$A52,$C$2:$C$175,$C52,$AC$2:$AC$175,1)>0,1,0) -> 1 | AJ52: =IFERROR(_xludf.MINIFS($P$2:$P$175,$A$2:$A$175,$A52,$C$2:$C$175,$C52,$AC$2:$AC$175,1),"")
A53: Galafold | B53: Migalastat | C53: Fabry disease | D53: Amicus Therapeutics | E53: Amicus Therapeutics | F53: Small molecule (pharmacological chaperone) | G53: Metabolic/Lysosomal storage | H53: Severe (progressive, life-shortening) | I53: Sweden | J53: Managed introduction / price negotiation | K53: TLV class reassessment of Fabry medicines | L53: Excluded from high-cost protection from 01/02/2026 | M53: Negative | N53: Not Applicable | O53: Price/Cost-effectiveness | P53: 2025 | Q53: Decision 30/01/2025; effective 01/02/2026 | R53: Best supportive care / no active treatment | S53: No treatment, as hypothetical comparator | T53: Not specified / unclear | U53: Price / cost-effectiveness | V53: ICER not available in current notes | W53: Cost considered too high at current price; no side agreement reached | X53: Fabry disease patients with amenable mutations | Y53: Reassessed together with Elfabrio, Fabrazyme and Replagal | Z53: Oral chaperone therapy. Benefit accepted, but current price rejected | AA53: Primary xlsx database | AB53: 21 | AC53: =IF(OR($M53="Positive",$M53="Restricted Positive"),1,0) -> 0 | AD53: =IF($M53="Not Evaluated",0,1) -> 1 | AG53: none public | AH53: Small molecule | AI53: =IF(COUNTIFS($A$2:$A$175,$A53,$C$2:$C$175,$C53,$AC$2:$AC$175,1)>0,1,0) -> 1 | AJ53: =IFERROR(_xludf.MINIFS($P$2:$P$175,$A$2:$A$175,$A53,$C$2:$C$175,$C53,$AC$2:$AC$175,1),"")
A54: Galafold | B54: Migalastat | C54: Fabry disease | D54: Amicus Therapeutics | E54: Amicus Therapeutics | F54: Small molecule (pharmacological chaperone) | G54: Metabolic/Lysosomal storage | H54: Severe (progressive, life-shortening) | I54: Denmark | J54: Other / unclassified process | K54: Medicinrådet treatment guideline and drug recommendation for Fabry disease | L54: Not first-choice after 2025 recommendation | M54: Restricted Positive | N54: Restricted | O54: Comparator/positioning | P54: 2025 | Q54: Recommendation approved 26/03/2025; effective 01/08/2025 | R54: Other / mixed comparator | S54: ERTs and other Fabry medicines | T54: Not specified / unclear | U54: Not specified | V54: ICER not central/not available | W54: Different eligible population because only patients with amenable mutations can receive migalastat | X54: Fabry disease with amenable mutation | Y54: Included in Fabry treatment framework, but Elfabrio became recommended first-choice after tender | Z54: Important alternative mechanism, but not interchangeable for all patients | AA54: Primary xlsx database | AB54: 21 | AC54: =IF(OR($M54="Positive",$M54="Restricted Positive"),1,0) -> 1 | AD54: =IF($M54="Not Evaluated",0,1) -> 1 | AH54: Small molecule | AI54: =IF(COUNTIFS($A$2:$A$175,$A54,$C$2:$C$175,$C54,$AC$2:$AC$175,1)>0,1,0) -> 1 | AJ54: =IFERROR(_xludf.MINIFS($P$2:$P$175,$A$2:$A$175,$A54,$C$2:$C$175,$C54,$AC$2:$AC$175,1),"")
A55: Galafold | B55: Migalastat | C55: Fabry disease | D55: Amicus Therapeutics | E55: Amicus Therapeutics | F55: Small molecule (pharmacological chaperone) | G55: Metabolic/Lysosomal storage | H55: Severe (progressive, life-shortening) | I55: Norway | J55: Managed introduction / price negotiation | K55: Included in Sykehusinnkjøp Fabry procurement/tender | L55: Available / established treatment | M55: Positive | N55: Broad | O55: N/A | Q55: Existing before Elfabrio; tender dates vary | R55: Active comparator drug(s) | S55: Fabrazyme, Replagal, Elfabrio | T55: Not specified / unclear | U55: Price / cost-effectiveness | V55: ICER not available | W55: Price ranking and eligible mutation population | X55: Fabry disease with amenable mutations | Y55: Included in Norwegian Fabry procurement as chaperone treatment | Z55: Important oral alternative; not directly suitable for all Fabry patients | AA55: Primary xlsx database | AB55: 21 | AC55: =IF(OR($M55="Positive",$M55="Restricted Positive"),1,0) -> 1 | AD55: =IF($M55="Not Evaluated",0,1) -> 1 | AH55: Small molecule | AI55: =IF(COUNTIFS($A$2:$A$175,$A55,$C$2:$C$175,$C55,$AC$2:$AC$175,1)>0,1,0) -> 1 | AJ55: =IFERROR(_xludf.MINIFS($P$2:$P$175,$A$2:$A$175,$A55,$C$2:$C$175,$C55,$AC$2:$AC$175,1),"")
A56: Amvuttra | B56: Vutrisiran | C56: Hereditary transthyretin amyloidosis with polyneuropathy, stage 1 or 2; ATTR-CM emerging/under assessment in some countries | D56: Alnylam | E56: Alnylam | F56: RNA-targeted (siRNA) | G56: Cardiology/Amyloidosis | H56: Severe (progressive, life-shortening) | I56: Sweden | J56: Managed introduction / price negotiation | K56: TLV reimbursement/subvention assessment with side agreement. | L56: Reimbursed with restriction. | M56: Restricted Positive | N56: Restricted | O56: N/A | P56: 2023 | Q56: 01/11/2023. | R56: Active comparator drug(s) | S56: Onpattro. | T56: Not specified / unclear | U56: Not specified | V56: Not public; TLV found Amvuttra cost lower than Onpattro after side agreement. | W56: Comparative evidence versus Onpattro, long-term outcomes. | X56: Adults with ATTRv-PN stage 1/2 who worsened despite TTR stabiliser. | Y56: SC injection every 3 months; prescription route. | Z56: Main newer gene-silencing therapy in Sweden; easier administration than Onpattro. | AA56: Primary xlsx database | AB56: 22 | AC56: =IF(OR($M56="Positive",$M56="Restricted Positive"),1,0) -> 1 | AD56: =IF($M56="Not Evaluated",0,1) -> 1 | AG56: not public - judged lower cost than Onpattro after side agreement | AH56: RNA-targeted | AI56: =IF(COUNTIFS($A$2:$A$175,$A56,$C$2:$C$175,$C56,$AC$2:$AC$175,1)>0,1,0) -> 1 | AJ56: =IFERROR(_xludf.MINIFS($P$2:$P$175,$A$2:$A$175,$A56,$C$2:$C$175,$C56,$AC$2:$AC$175,1),"")
A57: Amvuttra | B57: Vutrisiran | C57: Hereditary transthyretin amyloidosis with polyneuropathy, stage 1 or 2; ATTR-CM emerging/under assessment in some countries | D57: Alnylam | E57: Alnylam | F57: RNA-targeted (siRNA) | G57: Cardiology/Amyloidosis | H57: Severe (progressive, life-shortening) | I57: Denmark | J57: Other / unclassified process | K57: Medicinrådet status unclear; ATTR-CM request identified. | L57: Missing information / ongoing. | M57: Ongoing/Pending | N57: Not Applicable | O57: N/A | Q57: Missing information. | R57: Active comparator drug(s) | S57: Expected Onpattro for PN; tafamidis/BSC for CM depending indication. | T57: Not specified / unclear | U57: Price / cost-effectiveness | V57: No confirmed public hATTR-PN recommendation found. | W57: Comparative value and cost. | X57: Missing information. | Y57: Missing information. | Z57: mportant gap because Amvuttra would logically compete with Onpattro. | AA57: Primary xlsx database | AB57: 22 | AC57: =IF(OR($M57="Positive",$M57="Restricted Positive"),1,0) -> 0 | AD57: =IF($M57="Not Evaluated",0,1) -> 1 | AH57: RNA-targeted | AI57: =IF(COUNTIFS($A$2:$A$175,$A57,$C$2:$C$175,$C57,$AC$2:$AC$175,1)>0,1,0) -> 1 | AJ57: =IFERROR(_xludf.MINIFS($P$2:$P$175,$A$2:$A$175,$A57,$C$2:$C$175,$C57,$AC$2:$AC$175,1),"")
A58: Amvuttra | B58: Vutrisiran | C58: Hereditary transthyretin amyloidosis with polyneuropathy, stage 1 or 2; ATTR-CM emerging/under assessment in some countries | D58: Alnylam | E58: Alnylam | F58: RNA-targeted (siRNA) | G58: Cardiology/Amyloidosis | H58: Severe (progressive, life-shortening) | I58: Norway | J58: Other / unclassified process | K58: Nye Metoder assessment ongoing. | L58: : Ongoing / not introduced yet. | M58: Ongoing/Pending | N58: Not Applicable | O58: N/A | P58: 2025 | Q58: PN ongoing; ATTR-CM request identified in 2025. | R58: Active comparator drug(s) | S58: Expected Onpattro/Tegsedi for PN; tafamidis/BSC for CM | T58: Not specified / unclear | U58: Price / cost-effectiveness | V58: missing info | W58: Long-term comparative benefit, cost, patient numbers. | X58: pending | Y58: Main near-term opportunity to close Norway’s hATTR-PN access gap. | Z58: Should be followed closely. | AA58: Primary xlsx database | AB58: 22 | AC58: =IF(OR($M58="Positive",$M58="Restricted Positive"),1,0) -> 0 | AD58: =IF($M58="Not Evaluated",0,1) -> 1 | AH58: RNA-targeted | AI58: =IF(COUNTIFS($A$2:$A$175,$A58,$C$2:$C$175,$C58,$AC$2:$AC$175,1)>0,1,0) -> 1 | AJ58: =IFERROR(_xludf.MINIFS($P$2:$P$175,$A$2:$A$175,$A58,$C$2:$C$175,$C58,$AC$2:$AC$175,1),"")
A59: Onpattro | B59: Patisiran | C59: Hereditary transthyretin amyloidosis with polyneuropathy, stage 1 or 2 | D59: Alnylam | E59: Alnylam | F59: RNA-targeted (siRNA) | G59: Cardiology/Amyloidosis | H59: Severe (progressive, life-shortening) | I59: Sweden | J59: Full / standard HTA | K59: TLV health economic assessment for NT-rådet + NT-rådet recommendation. | L59: Recommended as clinic drug with regional agreement. | M59: Restricted Positive | N59: Restricted | O59: N/A | P59: 2018 | Q59: nitial recommendation after 2018 approval; updated 2025. | R59: Best supportive care / no active treatment | S59: No treatment/placebo initially; later gene-silencing alternatives. | T59: Not specified / unclear | U59: Comparator/positioning issue | V59: Not public/currently unavailable | W59: Long-term effect, comparative value versus newer gene silencers, indirect comparisons. | X59: Adults with ATTRv-PN stage 1/2 who worsened despite TTR stabiliser. | Y59: IV infusion every 3 weeks; still nationally coordinated by NT-rådet. | Z59: Important first-in-class gene silencer and key comparator for Amvuttra. | AA59: Primary xlsx database | AB59: 23 | AC59: =IF(OR($M59="Positive",$M59="Restricted Positive"),1,0) -> 1 | AD59: =IF($M59="Not Evaluated",0,1) -> 1 | AG59: not public | AH59: RNA-targeted | AI59: =IF(COUNTIFS($A$2:$A$175,$A59,$C$2:$C$175,$C59,$AC$2:$AC$175,1)>0,1,0) -> 1 | AJ59: =IFERROR(_xludf.MINIFS($P$2:$P$175,$A$2:$A$175,$A59,$C$2:$C$175,$C59,$AC$2:$AC$175,1),"")
A60: Onpattro | B60: Patisiran | C60: Hereditary transthyretin amyloidosis with polyneuropathy, stage 1 or 2 | D60: Alnylam | E60: Alnylam | F60: RNA-targeted (siRNA) | G60: Cardiology/Amyloidosis | H60: Severe (progressive, life-shortening) | I60: Denmark | J60: Other / unclassified process | K60: Medicinrådet clinical and economic assessment. | L60: Recommended. | M60: Positive | N60: Broad | O60: N/A | P60: 2020 | Q60: 2020-11-18 00:00:00 | R60: Best supportive care / no active treatment | S60: No treatment/placebo. | T60: Not specified / unclear | U60: Price / cost-effectiveness | V60: Incremental cost approx. DKK 20M per patient at AIP; confidential discount lowers actual cost. | W60: High cost, long-term benefit, budget impact. | X60: hATTR-PN stage 1/2. | Y60: Considered to provide large added value. | Z60: Strong positive Danish access case. | AA60: Primary xlsx database | AB60: 23 | AC60: =IF(OR($M60="Positive",$M60="Restricted Positive"),1,0) -> 1 | AD60: =IF($M60="Not Evaluated",0,1) -> 1 | AH60: RNA-targeted | AI60: =IF(COUNTIFS($A$2:$A$175,$A60,$C$2:$C$175,$C60,$AC$2:$AC$175,1)>0,1,0) -> 1 | AJ60: =IFERROR(_xludf.MINIFS($P$2:$P$175,$A$2:$A$175,$A60,$C$2:$C$175,$C60,$AC$2:$AC$175,1),"")
A61: Onpattro | B61: Patisiran | C61: Hereditary transthyretin amyloidosis with polyneuropathy, stage 1 or 2 | D61: Alnylam | E61: Alnylam | F61: RNA-targeted (siRNA) | G61: Cardiology/Amyloidosis | H61: Severe (progressive, life-shortening) | I61: Norway | J61: Other / unclassified process | K61: Nye Metoder assessment process | L61: Not introduced / shall not be used. | M61: Negative | N61: Not Applicable | O61: Price/Cost-effectiveness | P61: 2024 | Q61: Decision noted 18/03/2024. | R61: Other / mixed comparator | S61: Not fully assessed because required documentation was not submitted. | T61: Not specified / unclear | U61: Administrative/procedural | V61: No ICER; HTA not completed. | W61: Missing company documentation. | X61: N/A | Y61: Bestillerforum cancelled the assignment | Z61: Major Norwegian access gap caused by documentation non-submission. | AA61: Primary xlsx database | AB61: 23 | AC61: =IF(OR($M61="Positive",$M61="Restricted Positive"),1,0) -> 0 | AD61: =IF($M61="Not Evaluated",0,1) -> 1 | AH61: RNA-targeted | AI61: =IF(COUNTIFS($A$2:$A$175,$A61,$C$2:$C$175,$C61,$AC$2:$AC$175,1)>0,1,0) -> 1 | AJ61: =IFERROR(_xludf.MINIFS($P$2:$P$175,$A$2:$A$175,$A61,$C$2:$C$175,$C61,$AC$2:$AC$175,1),"")
A62: Tegsedi | B62: inotersen | C62: Hereditary transthyretin amyloidosis with polyneuropathy, stage 1 or 2 | D62: Ionis / Akcea | E62: Ionis/Akcea | F62: RNA-targeted (antisense oligonucleotide) | G62: Cardiology/Amyloidosis | H62: Severe (progressive, life-shortening) | I62: Sweden | J62: Full / standard HTA | K62: TLV health economic assessment for NT-rådet + NT-rådet recommendation. | L62: Recommended as clinic drug with regional agreement. | M62: Restricted Positive | N62: Restricted | O62: N/A | P62: 2019 | Q62: Initial recommendation after 2019 assessment; updated 2025. | R62: Active comparator drug(s) | S62: No treatment/placebo initially; later Onpattro/other gene silencers. | T62: Not specified / unclear | U62: Not specified | V62: Not public/currently unavailable. | W62: Safety profile, thrombocytopenia, renal monitoring, comparative value | X62: Adults with ATTRv-PN stage 1/2 who worsened despite TTR stabiliser. | Y62: Weekly SC injection; still nationally coordinated as clinic drug. | Z62: Available in Sweden, but with greater monitoring burden than Amvuttra/Wainzua. | AA62: Primary xlsx database | AB62: 24 | AC62: =IF(OR($M62="Positive",$M62="Restricted Positive"),1,0) -> 1 | AD62: =IF($M62="Not Evaluated",0,1) -> 1 | AG62: not public | AH62: RNA-targeted | AI62: =IF(COUNTIFS($A$2:$A$175,$A62,$C$2:$C$175,$C62,$AC$2:$AC$175,1)>0,1,0) -> 1 | AJ62: =IFERROR(_xludf.MINIFS($P$2:$P$175,$A$2:$A$175,$A62,$C$2:$C$175,$C62,$AC$2:$AC$175,1),"")
A63: Tegsedi | B63: inotersen | C63: Hereditary transthyretin amyloidosis with polyneuropathy, stage 1 or 2 | D63: Ionis / Akcea | E63: Ionis/Akcea | F63: RNA-targeted (antisense oligonucleotide) | G63: Cardiology/Amyloidosis | H63: Severe (progressive, life-shortening) | I63: Denmark | J63: Full / standard HTA | K63: Medicinrådet assessment. | L63: Not recommended. | M63: Negative | N63: Not Applicable | O63: Price/Cost-effectiveness | P63: 2020 | Q63: 2020/2021. | R63: Best supportive care / no active treatment | S63: No treatment/placebo; indirect comparison with patisiran. | T63: Not specified / unclear | U63: Price / cost-effectiveness | V63: Costs judged too high relative to effect and safety | W63: Serious adverse effects and cost relative to benefit. | X63: Not recommended | Y63: Medicinrådet considered benefit insufficient considering safety concerns. | Z63: Denmark is the clearest Nordic negative Tegsedi case. | AA63: Primary xlsx database | AB63: 24 | AC63: =IF(OR($M63="Positive",$M63="Restricted Positive"),1,0) -> 0 | AD63: =IF($M63="Not Evaluated",0,1) -> 1 | AH63: RNA-targeted | AI63: =IF(COUNTIFS($A$2:$A$175,$A63,$C$2:$C$175,$C63,$AC$2:$AC$175,1)>0,1,0) -> 1 | AJ63: =IFERROR(_xludf.MINIFS($P$2:$P$175,$A$2:$A$175,$A63,$C$2:$C$175,$C63,$AC$2:$AC$175,1),"")
A64: Tegsedi | B64: inotersen | C64: Hereditary transthyretin amyloidosis with polyneuropathy, stage 1 or 2 | D64: Ionis / Akcea | E64: Ionis/Akcea | F64: RNA-targeted (antisense oligonucleotide) | G64: Cardiology/Amyloidosis | H64: Severe (progressive, life-shortening) | I64: Norway | J64: Other / unclassified process | K64: Nye Metoder assessment ordered. | L64: Missing information / no final decision identified. | M64: Not Evaluated | N64: Not Applicable | O64: N/A | Q64: Missing information. | R64: Active comparator drug(s) | S64: Expected no treatment/Onpattro. | T64: Not specified / unclear | U64: Administrative/procedural | V64: Missing information. | W64: Possible non-submission; safety; comparative value. | X64: Missing information. | Y64: Assessment initiated but no final public decision confirmed. | AA64: Primary xlsx database | AB64: 24 | AC64: =IF(OR($M64="Positive",$M64="Restricted Positive"),1,0) -> 0 | AD64: =IF($M64="Not Evaluated",0,1) -> 0 | AH64: RNA-targeted | AI64: =IF(COUNTIFS($A$2:$A$175,$A64,$C$2:$C$175,$C64,$AC$2:$AC$175,1)>0,1,0) -> 1 | AJ64: =IFERROR(_xludf.MINIFS($P$2:$P$175,$A$2:$A$175,$A64,$C$2:$C$175,$C64,$AC$2:$AC$175,1),"")
A65: Vyndaqel | B65: tafamidis | C65: ATTR amyloidosis; historically hATTR-PN stage 1, currently especially ATTR-CM | D65: Pfizer | E65: Pfizer | F65: Small molecule (stabilizer) | G65: Cardiology/Amyloidosis | H65: Severe (progressive, life-shortening) | I65: Sweden | J65: Full / standard HTA | K65: TLV reimbursement assessment + NAG LOK clinical guidance. | L65: Vyndaqel 20 mg for PN no longer marketed; Vyndaqel 61 mg for ATTR-CM reimbursed with restriction and side agreement. | M65: Restricted Positive | N65: Restricted | O65: N/A | P65: 2021 | Q65: 61 mg reimbursed from 01/09/2021; current guidance 2025. | R65: Best supportive care / no active treatment | S65: BSC/no treatment for CM; TTR stabiliser context for PN. | T65: Not specified / unclear | U65: Comparator/positioning issue + Price / cost-effectiveness | V65: Not public/currently unavailable. | W65: Cost-effectiveness and appropriate patient selection. | X65: 61 mg restricted to ATTR-CM; 20 mg PN formulation no longer marketed. | Y65: TTR stabiliser; for PN, diflunisal is practical first-line stabiliser in Sweden. | Z65: Essential comparator/context drug rather than current main PN access product. | AA65: Primary xlsx database | AB65: 25 | AC65: =IF(OR($M65="Positive",$M65="Restricted Positive"),1,0) -> 1 | AD65: =IF($M65="Not Evaluated",0,1) -> 1 | AG65: not public | AH65: Small molecule | AI65: =IF(COUNTIFS($A$2:$A$175,$A65,$C$2:$C$175,$C65,$AC$2:$AC$175,1)>0,1,0) -> 1 | AJ65: =IFERROR(_xludf.MINIFS($P$2:$P$175,$A$2:$A$175,$A65,$C$2:$C$175,$C65,$AC$2:$AC$175,1),"")
A66: Vyndaqel | B66: tafamidis | C66: ATTR amyloidosis; historically hATTR-PN stage 1, currently especially ATTR-CM | D66: Pfizer | E66: Pfizer | F66: Small molecule (stabilizer) | G66: Cardiology/Amyloidosis | H66: Severe (progressive, life-shortening) | I66: Denmark | J66: Other / unclassified process | K66: Medicinrådet own-initiative comparative assessment. | L66: Recommended for hATTR-PN stage 1. | M66: Restricted Positive | N66: Restricted | O66: Clinical evidence uncertainty | P66: 2021 | Q66: 19/03/2021. | R66: Best supportive care / no active treatment | S66: Patisiran, inotersen, no treatment. | T66: Not specified / unclear | U66: Comparator/positioning issue | V66: Not central/currently unavailable. | W66: Limited to stage 1 and stabiliser role. | X66: hATTR-PN stage 1. | Y66: Positioned as stabiliser before gene-silencing therapy. | Z66: : Important first-line comparator in Danish sequence. | AA66: Primary xlsx database | AB66: 25 | AC66: =IF(OR($M66="Positive",$M66="Restricted Positive"),1,0) -> 1 | AD66: =IF($M66="Not Evaluated",0,1) -> 1 | AH66: Small molecule | AI66: =IF(COUNTIFS($A$2:$A$175,$A66,$C$2:$C$175,$C66,$AC$2:$AC$175,1)>0,1,0) -> 1 | AJ66: =IFERROR(_xludf.MINIFS($P$2:$P$175,$A$2:$A$175,$A66,$C$2:$C$175,$C66,$AC$2:$AC$175,1),"")
A67: Vyndaqel | B67: tafamidis | C67: ATTR amyloidosis; historically hATTR-PN stage 1, currently especially ATTR-CM | D67: Pfizer | E67: Pfizer | F67: Small molecule (stabilizer) | G67: Cardiology/Amyloidosis | H67: Severe (progressive, life-shortening) | I67: Norway | J67: Managed introduction / price negotiation | K67: Nye Metoder HTA + Sykehusinnkjøp price note + Beslutningsforum. | L67: Introduced for ATTR-CM. | M67: Positive | N67: Broad | O67: N/A | P67: 2022 | Q67: 20/06/2022; use from 15/07/2022. | R67: Best supportive care / no active treatment | S67: BSC/standard care | T67: Not specified / unclear | U67: Price / cost-effectiveness | V67: High at list price; confidential price enabled access. | W67: Budget impact, patient numbers, long-term benefit. | X67: ATTR-CM according to specialist criteria | Y67: Positive Norwegian ATTR case, but for cardiomyopathy not PN. | Z67: Norway has tafamidis access for CM but not clear gene-silencer access for PN. | AA67: Primary xlsx database | AB67: 25 | AC67: =IF(OR($M67="Positive",$M67="Restricted Positive"),1,0) -> 1 | AD67: =IF($M67="Not Evaluated",0,1) -> 1 | AH67: Small molecule | AI67: =IF(COUNTIFS($A$2:$A$175,$A67,$C$2:$C$175,$C67,$AC$2:$AC$175,1)>0,1,0) -> 1 | AJ67: =IFERROR(_xludf.MINIFS($P$2:$P$175,$A$2:$A$175,$A67,$C$2:$C$175,$C67,$AC$2:$AC$175,1),"")
A68: Oxlumo | B68: Lumasiran | C68: Primary hyperoxaluria type 1 (PH1) | D68: Alnylam Netherlands B.V. | E68: Alnylam | F68: RNA-targeted (siRNA) | G68: Renal/Metabolic | H68: Ultra-severe (immediately life-threatening) | I68: Sweden | J68: Other / unclassified process | K68: NT-rådet national recommendation; TLV health-economic assessment requested but not completed because company did not submit economic evidence | L68: General use not recommended; may be used only as indispensable care | M68: Restricted Positive | N68: Restricted | O68: Clinical evidence uncertainty | P68: 2025 | Q68: NT-rådet statement 24/11/2025; reviewed 14/04/2026 | R68: Procedural / transplant-based comparator | S68: Best supportive care: hyperhydration, crystallisation inhibitors, pyridoxine where relevant, dialysis/transplant pathway | T68: Not specified / unclear | U68: Clinical evidence uncertainty + Price / cost-effectiveness | V68: No public ICER; NT-rådet could not assess cost-effectiveness because health-economic evidence was not submitted | W68: No health-economic assessment available; high cost; uncertainty linking oxalate reduction to long-term renal survival and transplant avoidance | X68: Only after consultation with national PH1 treatment council: children with genetically verified infantile PH1 awaiting liver or liver+kidney transplant; children/adults with genetically verified PH1 where treatment enables transplant; stop after successful transplant | Y68: ILLUMINATE-A/B/C showed strong reductions in urinary/plasma oxalate, but evidence is mainly biomarker-based | Z68: Clear restricted-access case. Sweden accepts use only as bridge/indispensable care, not routine commercial uptake | AA68: Primary xlsx database | AB68: 26 | AC68: =IF(OR($M68="Positive",$M68="Restricted Positive"),1,0) -> 1 | AD68: =IF($M68="Not Evaluated",0,1) -> 1 | AG68: no public ICER - economic evidence not submitted | AH68: RNA-targeted | AI68: =IF(COUNTIFS($A$2:$A$175,$A68,$C$2:$C$175,$C68,$AC$2:$AC$175,1)>0,1,0) -> 1 | AJ68: =IFERROR(_xludf.MINIFS($P$2:$P$175,$A$2:$A$175,$A68,$C$2:$C$175,$C68,$AC$2:$AC$175,1),"")
A69: Oxlumo | B69: Lumasiran | C69: Primary hyperoxaluria type 1 (PH1) | D69: Alnylam Netherlands B.V. | E69: Alnylam | F69: RNA-targeted (siRNA) | G69: Renal/Metabolic | H69: Ultra-severe (immediately life-threatening) | I69: Denmark | J69: No formal assessment / not assessed | K69: Missing information | L69: Missing information | M69: Not Evaluated | N69: Not Applicable | O69: N/A | Q69: Missing information | R69: Not applicable / Not assessed | S69: Missing information | T69: Not specified / unclear | U69: Not specified | V69: Missing information | W69: Missing information | X69: Missing information | Y69: Missing information | Z69: Missing information | AA69: Primary xlsx database | AB69: 26 | AC69: =IF(OR($M69="Positive",$M69="Restricted Positive"),1,0) -> 0 | AD69: =IF($M69="Not Evaluated",0,1) -> 0 | AH69: RNA-targeted | AI69: =IF(COUNTIFS($A$2:$A$175,$A69,$C$2:$C$175,$C69,$AC$2:$AC$175,1)>0,1,0) -> 1 | AJ69: =IFERROR(_xludf.MINIFS($P$2:$P$175,$A$2:$A$175,$A69,$C$2:$C$175,$C69,$AC$2:$AC$175,1),"")
A70: Oxlumo | B70: Lumasiran | C70: Primary hyperoxaluria type 1 (PH1) | D70: Alnylam Netherlands B.V. | E70: Alnylam | F70: RNA-targeted (siRNA) | G70: Renal/Metabolic | H70: Ultra-severe (immediately life-threatening) | I70: Norway | J70: Rapid / simplified HTA | K70: Nye Metoder / Bestillerforum assignment for short method assessment of effect and safety | L70: Assessment cancelled / not completed due to missing company documentation | M70: Not Evaluated | N70: Not Applicable | O70: Administrative/Procedural | P70: 2023 | Q70: Bestillerforum case 25/09/2023; original assignment 18/01/2021 | R70: Best supportive care / no active treatment | S70: BSC | T70: Not specified / unclear | U70: Administrative/procedural + Price / cost-effectiveness | V70: Missing information — no public ICER because no completed method assessment | W70: No method assessment completed because required documentation was not submitted; therefore clinical effect, safety, costs and cost-effectiveness were not assessed nationally | X70: No national routine-use conditions established | Y70: Lumasiran was identified as Oxlumo for PH1, ATC A16AX18, orphan medicine, subcutaneous injection, specialist-healthcare responsibility; not marketed in Norway at the time of the Bestillerforum note | Z70: Important procedural failure case: market access did not fail after negative cost-effectiveness modelling; it stalled/collapsed because the company did not provide documentation | AA70: Primary xlsx database | AB70: 26 | AC70: =IF(OR($M70="Positive",$M70="Restricted Positive"),1,0) -> 0 | AD70: =IF($M70="Not Evaluated",0,1) -> 0 | AH70: RNA-targeted | AI70: =IF(COUNTIFS($A$2:$A$175,$A70,$C$2:$C$175,$C70,$AC$2:$AC$175,1)>0,1,0) -> 1 | AJ70: =IFERROR(_xludf.MINIFS($P$2:$P$175,$A$2:$A$175,$A70,$C$2:$C$175,$C70,$AC$2:$AC$175,1),"")
A71: Crysvita | B71: Burosumab | C71: X-linked hypophosphatemia (XLH) | D71: Kyowa Kirin AB | E71: Kyowa Kirin | F71: Monoclonal antibody | G71: Musculoskeletal/Metabolic | H71: Serious (chronic, manageable) | I71: Sweden | J71: Other / unclassified process | K71: TLV health-economic assessment + NT-rådet national recommendation | L71: Restricted | M71: Restricted Positive | N71: Restricted | O71: N/A | P71: 2019 | Q71: TLV 2019; NT-rådet updated 2023/2024; agreement active 01/12/2023–30/11/2026, extension option to 30/11/2027 | R71: Other / mixed comparator | S71: Conventional therapy: oral phosphate + active vitamin D analogues | T71: Not specified / unclear | U71: Clinical evidence uncertainty + Price / cost-effectiveness | V71: Approx. SEK 12M/QALY vs conventional therapy | W71: Long-term effect, high ICER, durability of skeletal benefit, translation of rickets/phosphate outcomes into lifetime QoL and cost-effectiveness | X71: Children ≥1 year and adolescents with growing skeleton, genetically verified XLH, insufficient response to optimized conventional treatment; treatment initiated/evaluated with National XLH Treatment Board | Y71: Clinically superior to conventional therapy for rickets healing and phosphate regulation, but cost-effectiveness very uncertain at list price | Z71: Strong restricted paediatric access case; access depends on expert-board gatekeeping and regional agreement | AA71: Primary xlsx database | AB71: 27 | AC71: =IF(OR($M71="Positive",$M71="Restricted Positive"),1,0) -> 1 | AD71: =IF($M71="Not Evaluated",0,1) -> 1 | AE71: 12000000 | AF71: 12000000 | AG71: exact (approx., vs conventional therapy) | AH71: Monoclonal antibody | AI71: =IF(COUNTIFS($A$2:$A$175,$A71,$C$2:$C$175,$C71,$AC$2:$AC$175,1)>0,1,0) -> 1 | AJ71: =IFERROR(_xludf.MINIFS($P$2:$P$175,$A$2:$A$175,$A71,$C$2:$C$175,$C71,$AC$2:$AC$175,1),"")
A72: Crysvita | B72: Burosumab | C72: X-linked hypophosphatemia (XLH) | D72: Kyowa Kirin AB | E72: Kyowa Kirin | F72: Monoclonal antibody | G72: Musculoskeletal/Metabolic | H72: Serious (chronic, manageable) | I72: Denmark | J72: Full / standard HTA | K72: Medicinrådet assessment + Amgros negotiation | L72: Restricted | M72: Restricted Positive | N72: Restricted | O72: N/A | P72: 2019 | Q72: 2019-11-20 00:00:00 | R72: Other / mixed comparator | S72: Conventional therapy: oral phosphate + alfacalcidol / active vitamin D | T72: Not specified / unclear | U72: Clinical evidence uncertainty + Price / cost-effectiveness | V72: No public ICER; Medicinrådet considered costs very high and cost-benefit not reasonable, but recommendation justified due to severity | W72: Low evidence quality, long-term durability, high cost, uncertainty around sustained benefit | X72: Children/adolescents with skeletal growth and severe XLH defined by RSS ≥2 | Y72: Moderate-to-large added clinical value assumed for severe paediatric patients, despite low evidence certainty | Z72: Denmark uses a clear radiographic severity threshold; positive but narrow access | AA72: Primary xlsx database | AB72: 27 | AC72: =IF(OR($M72="Positive",$M72="Restricted Positive"),1,0) -> 1 | AD72: =IF($M72="Not Evaluated",0,1) -> 1 | AH72: Monoclonal antibody | AI72: =IF(COUNTIFS($A$2:$A$175,$A72,$C$2:$C$175,$C72,$AC$2:$AC$175,1)>0,1,0) -> 1 | AJ72: =IFERROR(_xludf.MINIFS($P$2:$P$175,$A$2:$A$175,$A72,$C$2:$C$175,$C72,$AC$2:$AC$175,1),"")
A73: Crysvita | B73: Burosumab | C73: X-linked hypophosphatemia (XLH) | D73: Kyowa Kirin AB | E73: Kyowa Kirin | F73: Monoclonal antibody | G73: Musculoskeletal/Metabolic | H73: Serious (chronic, manageable) | I73: Norway | J73: Rapid / simplified HTA | K73: Nye Metoder rapid HTA + Beslutningsforum decision | L73: Restricted for paediatric patients; Negative for adults | M73: Restricted Positive | N73: Restricted | O73: Clinical evidence uncertainty | P73: 2019 | Q73: Initial paediatric introduction 23/09/2019; updated assessment 2021; criteria confirmed/updated 09/01/2025 | R73: Other / mixed comparator | S73: Conventional therapy expected; exact comparator not fully detailed in public summary | T73: Not specified / unclear | U73: Administrative/procedural + Price / cost-effectiveness | V73: No public ICER identified | W73: Budget impact, high cost, restricted reimbursement criteria | X73: Restricted special reimbursement in upper 100% reimbursement class; conditional reimbursement with financial agreement | Y73: Finland used HILA/Kela reimbursement route rather than Fimea/PALKO hospital HTA route | Z73: mportant correction: Finland is not missing anymore; access is documented through outpatient reimbursement, but public details remain limited | AA73: Primary xlsx database | AB73: 27 | AC73: =IF(OR($M73="Positive",$M73="Restricted Positive"),1,0) -> 1 | AD73: =IF($M73="Not Evaluated",0,1) -> 1 | AH73: Monoclonal antibody | AI73: =IF(COUNTIFS($A$2:$A$175,$A73,$C$2:$C$175,$C73,$AC$2:$AC$175,1)>0,1,0) -> 1 | AJ73: =IFERROR(_xludf.MINIFS($P$2:$P$175,$A$2:$A$175,$A73,$C$2:$C$175,$C73,$AC$2:$AC$175,1),"")
A74: Enspryng | B74: Satralizumab | C74: Neuromyelitis optica spectrum disorder | D74: Roche AB | E74: Roche | F74: Monoclonal antibody | G74: Neurology (autoimmune) | H74: Severe (progressive, life-shortening) | I74: Sweden | J74: Managed introduction / price negotiation | K74: NT-rådet managed introduction / TLV pathway | L74: Wait / defer introduction | M74: Ongoing/Pending | N74: Not Applicable | O74: N/A | P74: 2022 | Q74: 2022-05-30 00:00:00 | R74: Not applicable / Not assessed | S74: Missing information | T74: Not specified / unclear | U74: Price / cost-effectiveness | V74: Not public | W74: Cost-effectiveness vs current practice | X74: AQP4-IgG+ NMOSD; regions should wait for TLV decision | Y74: NT-rådet told regions to await TLV benefit decision | Z74: Use as “deferred / no routine access” | AA74: Primary xlsx database | AB74: 28 | AC74: =IF(OR($M74="Positive",$M74="Restricted Positive"),1,0) -> 0 | AD74: =IF($M74="Not Evaluated",0,1) -> 1 | AG74: not public; ongoing | AH74: Monoclonal antibody | AI74: =IF(COUNTIFS($A$2:$A$175,$A74,$C$2:$C$175,$C74,$AC$2:$AC$175,1)>0,1,0) -> 0 | AJ74: =IFERROR(_xludf.MINIFS($P$2:$P$175,$A$2:$A$175,$A74,$C$2:$C$175,$C74,$AC$2:$AC$175,1),"")
A75: Enspryng | B75: Satralizumab | C75: Neuromyelitis optica spectrum disorder | D75: Roche AB | E75: Roche | F75: Monoclonal antibody | G75: Neurology (autoimmune) | H75: Severe (progressive, life-shortening) | I75: Denmark | J75: Full / standard HTA | K75: Medicinrådet assessment + Amgros negotiation | L75: Not recommended | M75: Negative | N75: Not Applicable | O75: Price/Cost-effectiveness | P75: 2022 | Q75: 2022-03-24 00:00:00 | R75: Best supportive care / no active treatment | S75: Current Danish off-label practice / no treatment in evidence base | T75: Not specified / unclear | U75: Price / cost-effectiveness | V75: Not public | W75: Effect vs existing off-label therapies; infections; high cost | X75: AQP4-IgG+ adults/adolescents | Y75: Satralizumab reduced attacks vs no treatment, but was much more expensive than current medicines | Z75: Negative access case | AA75: Primary xlsx database | AB75: 28 | AC75: =IF(OR($M75="Positive",$M75="Restricted Positive"),1,0) -> 0 | AD75: =IF($M75="Not Evaluated",0,1) -> 1 | AH75: Monoclonal antibody | AI75: =IF(COUNTIFS($A$2:$A$175,$A75,$C$2:$C$175,$C75,$AC$2:$AC$175,1)>0,1,0) -> 0 | AJ75: =IFERROR(_xludf.MINIFS($P$2:$P$175,$A$2:$A$175,$A75,$C$2:$C$175,$C75,$AC$2:$AC$175,1),"")
A76: Enspryng | B76: Satralizumab | C76: Neuromyelitis optica spectrum disorder | D76: Roche AB | E76: Roche | F76: Monoclonal antibody | G76: Neurology (autoimmune) | H76: Severe (progressive, life-shortening) | I76: Norway | J76: Other / unclassified process | K76: DMP / Nye Metoder assessment | L76: Not introduced | M76: Negative | N76: Not Applicable | O76: Price/Cost-effectiveness | Q76: 2021 | R76: Active comparator drug(s) | S76: Off-label rituximab/contextual SoC | T76: Not specified / unclear | U76: Clinical evidence uncertainty + Price / cost-effectiveness | V76: Not public | W76: Price vs uncertain incremental value | X76: AQP4-IgG+ NMOSD | Y76: Norway notes satralizumab has MT but is not introduced; rituximab/tocilizumab used off-label | Z76: Rituximab trap | AA76: Primary xlsx database | AB76: 28 | AC76: =IF(OR($M76="Positive",$M76="Restricted Positive"),1,0) -> 0 | AD76: =IF($M76="Not Evaluated",0,1) -> 1 | AH76: Monoclonal antibody | AI76: =IF(COUNTIFS($A$2:$A$175,$A76,$C$2:$C$175,$C76,$AC$2:$AC$175,1)>0,1,0) -> 0 | AJ76: =IFERROR(_xludf.MINIFS($P$2:$P$175,$A$2:$A$175,$A76,$C$2:$C$175,$C76,$AC$2:$AC$175,1),"")
A77: Uplizna | B77: Inebilizumab | C77: NMOSD | D77: Amgen | E77: Amgen | F77: Monoclonal antibody | G77: Neurology (autoimmune) | H77: Severe (progressive, life-shortening) | I77: Sweden | J77: No formal assessment / not assessed | K77: No public Swedish NMOSD HTA/reimbursement assessment identified. Swedish source only says Uplizna is not launched in Sweden for NMOSD; later horizon scanning is for IgG4-RD, not NMOSD. | M77: Not Evaluated | N77: Not Applicable | O77: N/A | R77: Not applicable / Not assessed | T77: Not specified / unclear | U77: Not specified | AA77: Primary xlsx database | AB77: 29 | AC77: =IF(OR($M77="Positive",$M77="Restricted Positive"),1,0) -> 0 | AD77: =IF($M77="Not Evaluated",0,1) -> 0 | AG77: not evaluated | AH77: Monoclonal antibody | AI77: =IF(COUNTIFS($A$2:$A$175,$A77,$C$2:$C$175,$C77,$AC$2:$AC$175,1)>0,1,0) -> 0 | AJ77: =IFERROR(_xludf.MINIFS($P$2:$P$175,$A$2:$A$175,$A77,$C$2:$C$175,$C77,$AC$2:$AC$175,1),"")
A78: Uplizna | B78: Inebilizumab | C78: NMOSD | D78: Amgen | E78: Amgen | F78: Monoclonal antibody | G78: Neurology (autoimmune) | H78: Severe (progressive, life-shortening) | I78: Denmark | J78: Full / standard HTA | K78: Medicinrådet assessment + Amgros negotiation | L78: Not recommended | M78: Negative | N78: Not Applicable | O78: Price/Cost-effectiveness | P78: 2024 | Q78: 2024-11-28 00:00:00 | R78: Active comparator drug(s) | S78: Rituximab | T78: Not specified / unclear | U78: Comparator/positioning issue + Price / cost-effectiveness | V78: Not public | W78: No reliable evidence of better efficacy/safety than rituximab; high cost | X78: AQP4-IgG+ adults | Y78: Amgros negotiated confidential price, but final value remained insufficient | Z78: Strong comparator rejection | AA78: Primary xlsx database | AB78: 29 | AC78: =IF(OR($M78="Positive",$M78="Restricted Positive"),1,0) -> 0 | AD78: =IF($M78="Not Evaluated",0,1) -> 1 | AH78: Monoclonal antibody | AI78: =IF(COUNTIFS($A$2:$A$175,$A78,$C$2:$C$175,$C78,$AC$2:$AC$175,1)>0,1,0) -> 0 | AJ78: =IFERROR(_xludf.MINIFS($P$2:$P$175,$A$2:$A$175,$A78,$C$2:$C$175,$C78,$AC$2:$AC$175,1),"")
A79: Uplizna | B79: Inebilizumab | C79: NMOSD | D79: Amgen | E79: Amgen | F79: Monoclonal antibody | G79: Neurology (autoimmune) | H79: Severe (progressive, life-shortening) | I79: Norway | J79: Managed introduction / price negotiation | K79: DMP method assessment + Sykehusinnkjøp price note + Beslutningsforum | L79: Not introduced | M79: Negative | N79: Not Applicable | O79: Price/Cost-effectiveness | P79: 2025 | Q79: 2025-09-22 00:00:00 | R79: Active comparator drug(s) | S79: Rituximab and placebo requested | T79: Not specified / unclear | U79: Price / cost-effectiveness | V79: No valid ICER; max price used | W79: Evidence not suitable for cost-utility analysis; no price offer | X79: AQP4-IgG+ adults | Y79: Amgen gave no price offer; max AUP used; year 1 cost listed as 2.22M NOK incl. VAT | Z79: Clear price/evidence failure | AA79: Primary xlsx database | AB79: 29 | AC79: =IF(OR($M79="Positive",$M79="Restricted Positive"),1,0) -> 0 | AD79: =IF($M79="Not Evaluated",0,1) -> 1 | AH79: Monoclonal antibody | AI79: =IF(COUNTIFS($A$2:$A$175,$A79,$C$2:$C$175,$C79,$AC$2:$AC$175,1)>0,1,0) -> 0 | AJ79: =IFERROR(_xludf.MINIFS($P$2:$P$175,$A$2:$A$175,$A79,$C$2:$C$175,$C79,$AC$2:$AC$175,1),"")
A80: Soliris | B80: Eculizumab | C80: Paroxysmal nocturnal hemoglobinuria (PNH) | D80: Alexion (AstraZeneca Rare Disease) | E80: Alexion (AstraZeneca Rare Disease) | F80: Monoclonal antibody | G80: Neurology (autoimmune) | H80: Severe (progressive, life-shortening) | I80: Sweden | J80: Other / unclassified process | K80: NT-radet opinion (price-based, no new health-economic assessment) | L80: Not recommended for general use (Soliris specifically) | M80: Not Evaluated | N80: Not Applicable | O80: N/A | P80: 2024 | Q80: 2024-12-19 00:00:00 | R80: Other / mixed comparator | S80: Bekemv (eculizumab biosimilar), Epysqli, Ultomiris, Aspaveli | T80: Not specified / unclear | U80: Clinical evidence uncertainty + Price / cost-effectiveness | V80: Not reported (recommendation is price-comparison based, not a fresh cost-per-QALY assessment) | W80: N/A - decision is price-driven, not an evidence/uncertainty issue | X80: NT-radet recommends against general use of Soliris/Epysqli/Ultomiris/Aspaveli for PNH; Bekemv recommended where treatment is unavoidable; a national treatment council (PNH-gruppen) decides which patients can be offered Bekemv and manages switching from Soliris | Y80: Replaces NT-radet's earlier PNH opinion. Verified against source 'PNH Soliris 2024-12-19' (TLV/NT-radet). | Z80: Source: TLV/NT-radet opinion, 'PNH Soliris 2024-12-19'. | AA80: Primary xlsx database | AB80: 30 | AC80: =IF(OR($M80="Positive",$M80="Restricted Positive"),1,0) -> 0 | AD80: =IF($M80="Not Evaluated",0,1) -> 0 | AG80: not evaluated | AH80: Monoclonal antibody | AI80: =IF(COUNTIFS($A$2:$A$175,$A80,$C$2:$C$175,$C80,$AC$2:$AC$175,1)>0,1,0) -> 0 | AJ80: =IFERROR(_xludf.MINIFS($P$2:$P$175,$A$2:$A$175,$A80,$C$2:$C$175,$C80,$AC$2:$AC$175,1),"")
A81: Soliris | B81: Eculizumab | C81: Paroxysmal nocturnal hemoglobinuria (PNH) | D81: Alexion (AstraZeneca Rare Disease) | E81: Alexion (AstraZeneca Rare Disease) | F81: Monoclonal antibody | G81: Neurology (autoimmune) | H81: Severe (progressive, life-shortening) | I81: Denmark | J81: Other / unclassified process | K81: Not Evaluated | L81: No Medicinraadet PNH-specific assessment identified in available sources | M81: Not Evaluated | N81: Not Applicable | O81: N/A | R81: Not applicable / Not assessed | T81: Not specified / unclear | U81: Administrative/procedural + Comparator/positioning issue | Y81: No HTA assessment identified in available source documents for this indication/country combination | AA81: Primary xlsx database | AB81: 30 | AC81: =IF(OR($M81="Positive",$M81="Restricted Positive"),1,0) -> 0 | AD81: =IF($M81="Not Evaluated",0,1) -> 0 | AH81: Monoclonal antibody | AI81: =IF(COUNTIFS($A$2:$A$175,$A81,$C$2:$C$175,$C81,$AC$2:$AC$175,1)>0,1,0) -> 0 | AJ81: =IFERROR(_xludf.MINIFS($P$2:$P$175,$A$2:$A$175,$A81,$C$2:$C$175,$C81,$AC$2:$AC$175,1),"")
A82: Soliris | B82: Eculizumab | C82: Paroxysmal nocturnal hemoglobinuria (PNH) | D82: Alexion (AstraZeneca Rare Disease) | E82: Alexion (AstraZeneca Rare Disease) | F82: Monoclonal antibody | G82: Neurology (autoimmune) | H82: Severe (progressive, life-shortening) | I82: Norway | J82: Managed introduction / price negotiation | K82: Sykehusinnkjop price note (Legemiddelverket forenklet metodevurdering, 20.4.2022, underlying) | L82: Outcome not confirmed in available sources | M82: Not Evaluated | N82: Not Applicable | O82: N/A | P82: 2022 | Q82: 2022-08-30 00:00:00 | R82: Other / mixed comparator | S82: None submitted - Alexion did not provide documentation for a cost-effectiveness assessment for any of the 4 indications | T82: Not specified / unclear | U82: Administrative/procedural + Comparator/positioning issue + Price / cost-effectiveness | V82: Not assessed / no ICER (Legemiddelverket: 'med dagens pris... er det lite sannsynlig at prioriteringskriteriene er oppfylt') | W82: No ICER calculable: Alexion chose not to submit the required documentation for a health-economic assessment for any indication | X82: Price note ID2019_61 covers PNH together with aHUS (ID2020_003), NMOSD (ID2019_043) and gMG (ID2017_020/ID2019_021) in a single combined document | Y82: Sykehusinnkjop recommended that, if eculizumab is introduced, the agreed maximum price be used. A Beslutningsforum decision was scheduled for 26.09.2022. No Beslutningsforum decision letter for PNH (or any of the 4 indications) was found among the available source documents. | Z82: Source: id2019_061-med-flere price note, Sykehusinnkjop HF, 30.08.2022. NB: the unrelated date 18.10.2022 that appeared in the prior version of this database belongs to a real Yescarta (axicabtagene ciloleucel) Beslutningsforum decision, not to any Soliris indication -- that entry was fabricated/misattributed. | AA82: Primary xlsx database | AB82: 30 | AC82: =IF(OR($M82="Positive",$M82="Restricted Positive"),1,0) -> 0 | AD82: =IF($M82="Not Evaluated",0,1) -> 0 | AH82: Monoclonal antibody | AI82: =IF(COUNTIFS($A$2:$A$175,$A82,$C$2:$C$175,$C82,$AC$2:$AC$175,1)>0,1,0) -> 0 | AJ82: =IFERROR(_xludf.MINIFS($P$2:$P$175,$A$2:$A$175,$A82,$C$2:$C$175,$C82,$AC$2:$AC$175,1),"")
A83: Ultomiris | B83: Ravulizumab | C83: NMOSD | D83: Alexion Pharma Nordics | E83: Alexion (AstraZeneca Rare Disease) | F83: Monoclonal antibody | G83: Neurology (autoimmune) | H83: Severe (progressive, life-shortening) | I83: Sweden | J83: Other / unclassified process | K83: No Swedish NMOSD recommendation. Samverkan says Soliris has NMOSD indication, but NT-rådet has only taken a position for PNH and aHUS. | M83: Not Evaluated | N83: Not Applicable | O83: N/A | R83: Not applicable / Not assessed | T83: Not specified / unclear | U83: Not specified | AA83: Primary xlsx database | AB83: 31 | AC83: =IF(OR($M83="Positive",$M83="Restricted Positive"),1,0) -> 0 | AD83: =IF($M83="Not Evaluated",0,1) -> 0 | AG83: not evaluated | AH83: Monoclonal antibody | AI83: =IF(COUNTIFS($A$2:$A$175,$A83,$C$2:$C$175,$C83,$AC$2:$AC$175,1)>0,1,0) -> 0 | AJ83: =IFERROR(_xludf.MINIFS($P$2:$P$175,$A$2:$A$175,$A83,$C$2:$C$175,$C83,$AC$2:$AC$175,1),"")
A84: Ultomiris | B84: Ravulizumab | C84: NMOSD | D84: Alexion Pharma Nordics | E84: Alexion (AstraZeneca Rare Disease) | F84: Monoclonal antibody | G84: Neurology (autoimmune) | H84: Severe (progressive, life-shortening) | I84: Denmark | J84: Full / standard HTA | K84: Medicinrådet assessment + Amgros negotiation | L84: Not recommended | M84: Negative | N84: Not Applicable | O84: Price/Cost-effectiveness | P84: 2026 | Q84: 2026-04-29 00:00:00 | R84: Active comparator drug(s) | S84: Current standard treatment after rituximab failure | T84: Not specified / unclear | U84: Clinical evidence uncertainty + Comparator/positioning issue + Price / cost-effectiveness | V84: 3.0 QALYs and 3.0 life-years estimated; list-price extra cost ~19.0M DKK per patient | W84: Single-arm CHAMPION-NMOSD design; indirect PREVENT comparator; uncertain survival/QoL gain; meningococcal infection risk | X84: AQP4+ adults, EDSS ≤7, attack in last 12 months, insufficient rituximab effect | Y84: Rejected because costs not acceptable despite estimated benefit | Z84: Best row for “benefit accepted but price too high” | AA84: Primary xlsx database | AB84: 31 | AC84: =IF(OR($M84="Positive",$M84="Restricted Positive"),1,0) -> 0 | AD84: =IF($M84="Not Evaluated",0,1) -> 1 | AH84: Monoclonal antibody | AI84: =IF(COUNTIFS($A$2:$A$175,$A84,$C$2:$C$175,$C84,$AC$2:$AC$175,1)>0,1,0) -> 0 | AJ84: =IFERROR(_xludf.MINIFS($P$2:$P$175,$A$2:$A$175,$A84,$C$2:$C$175,$C84,$AC$2:$AC$175,1),"")
A85: Ultomiris | B85: Ravulizumab | C85: NMOSD | D85: Alexion Pharma Nordics | E85: Alexion (AstraZeneca Rare Disease) | F85: Monoclonal antibody | G85: Neurology (autoimmune) | H85: Severe (progressive, life-shortening) | I85: Norway | J85: Early / horizon scanning only | K85: Nye Metoder suitability assessment / ongoing mapping | L85: Under evaluation | M85: Ongoing/Pending | N85: Not Applicable | O85: N/A | P85: 2022 | Q85: ID2022_143 active; request 19/08/2025 | R85: Active comparator drug(s) | S85: Under review; rituximab/tocilizumab are Norwegian off-label practice | T85: Not specified / unclear | U85: Comparator/positioning issue | V85: Not available | W85: No introduced NMOSD branded comparators; long-term value and sequencing | X85: AQP4+ adults | Y85: DMP states satralizumab, eculizumab, inebilizumab and ravulizumab have MT but are not introduced | Z85: Pipeline/watch row | AA85: Primary xlsx database | AB85: 31 | AC85: =IF(OR($M85="Positive",$M85="Restricted Positive"),1,0) -> 0 | AD85: =IF($M85="Not Evaluated",0,1) -> 1 | AH85: Monoclonal antibody | AI85: =IF(COUNTIFS($A$2:$A$175,$A85,$C$2:$C$175,$C85,$AC$2:$AC$175,1)>0,1,0) -> 0 | AJ85: =IFERROR(_xludf.MINIFS($P$2:$P$175,$A$2:$A$175,$A85,$C$2:$C$175,$C85,$AC$2:$AC$175,1),"")
A86: Koselugo | B86: Selumetinib | C86: NF1 plexiform neurofibromas | D86: Alexion Pharma Nordics AB | E86: Alexion (AstraZeneca Rare Disease) | F86: Small molecule (kinase inhibitor) | G86: Oncology (genetic tumour syndrome) | H86: Severe (progressive, life-shortening) | I86: Sweden | J86: Full / standard HTA | K86: TLV reimbursement assessment | L86: Not reimbursed / rejected | M86: Negative | N86: Not Applicable | O86: Price/Cost-effectiveness | P86: 2024 | Q86: 2024-07-11 00:00:00 | R86: Best supportive care / no active treatment | S86: Best supportive care | T86: Not specified / unclear | U86: Clinical evidence uncertainty + Price / cost-effectiveness | V86: Company base case: 1,756,579 SEK/QALY | W86: Single-arm SPRINT evidence; indirect Natural History comparison; uncertain long-term benefit | X86: Applied subgroup: children 3–18 with very high severity NF1 PN | Y86: TLV rejected inclusion in pharmaceutical benefits; no tripartite agreement | Z86: Cost-effectiveness rejection despite high severity | AA86: Primary xlsx database | AB86: 32 | AC86: =IF(OR($M86="Positive",$M86="Restricted Positive"),1,0) -> 0 | AD86: =IF($M86="Not Evaluated",0,1) -> 1 | AE86: 1756579 | AF86: 1756579 | AG86: exact (company base case, TLV rejected 11 Jul 2024) | AH86: Small molecule | AI86: =IF(COUNTIFS($A$2:$A$175,$A86,$C$2:$C$175,$C86,$AC$2:$AC$175,1)>0,1,0) -> 1 | AJ86: =IFERROR(_xludf.MINIFS($P$2:$P$175,$A$2:$A$175,$A86,$C$2:$C$175,$C86,$AC$2:$AC$175,1),"")
A87: Koselugo | B87: Selumetinib | C87: NF1 plexiform neurofibromas | D87: Alexion Pharma Nordics AB | E87: Alexion (AstraZeneca Rare Disease) | F87: Small molecule (kinase inhibitor) | G87: Oncology (genetic tumour syndrome) | H87: Severe (progressive, life-shortening) | I87: Denmark | J87: No formal assessment / not assessed | K87: No Medicinrådet HTA identified; Amgros institutional framework | L87: No Medicinrådet HTA identified; Amgros institutional framework | M87: Not Evaluated | N87: Not Applicable | O87: Administrative/Procedural | Q87: No Medicinrådet HTA identified; Amgros institutional framework | R87: Not applicable / Not assessed | S87: No Medicinrådet HTA identified; Amgros institutional framework | T87: Not specified / unclear | U87: Not specified | V87: No Medicinrådet HTA identified; Amgros institutional framework | W87: No Medicinrådet HTA identified; Amgros institutional framework | X87: No Medicinrådet HTA identified; Amgros institutional framework | Y87: No Medicinrådet HTA identified; Amgros institutional framework | Z87: No Medicinrådet HTA identified; Amgros institutional framework | AA87: Primary xlsx database | AB87: 32 | AC87: =IF(OR($M87="Positive",$M87="Restricted Positive"),1,0) -> 0 | AD87: =IF($M87="Not Evaluated",0,1) -> 0 | AH87: Small molecule | AI87: =IF(COUNTIFS($A$2:$A$175,$A87,$C$2:$C$175,$C87,$AC$2:$AC$175,1)>0,1,0) -> 1 | AJ87: =IFERROR(_xludf.MINIFS($P$2:$P$175,$A$2:$A$175,$A87,$C$2:$C$175,$C87,$AC$2:$AC$175,1),"")
A88: Koselugo | B88: Selumetinib | C88: NF1 plexiform neurofibromas | D88: Alexion Pharma Nordics AB | E88: Alexion (AstraZeneca Rare Disease) | F88: Small molecule (kinase inhibitor) | G88: Oncology (genetic tumour syndrome) | H88: Severe (progressive, life-shortening) | I88: Norway | J88: Other / unclassified process | K88: Nye Metoder / DMP + Sykehusinnkjøp | L88: Introduced / recommended with restrictions | M88: Restricted Positive | N88: Restricted | O88: N/A | P88: 2026 | Q88: 2026-01-19 00:00:00 | R88: Best supportive care / no active treatment | S88: Best supportive care | T88: Not specified / unclear | U88: Clinical evidence uncertainty + Price / cost-effectiveness | V88: Not public / confidential | W88: Single-arm SPRINT; uncertain long-term outcomes | X88: Pediatric NF1 PN ≥3 years; severe symptoms; specialist initiation; strict criteria | Y88: Rejected in 2023 and 2024, approved after new price/alternative agreement | Z88: Managed-entry success | AA88: Primary xlsx database | AB88: 32 | AC88: =IF(OR($M88="Positive",$M88="Restricted Positive"),1,0) -> 1 | AD88: =IF($M88="Not Evaluated",0,1) -> 1 | AH88: Small molecule | AI88: =IF(COUNTIFS($A$2:$A$175,$A88,$C$2:$C$175,$C88,$AC$2:$AC$175,1)>0,1,0) -> 1 | AJ88: =IFERROR(_xludf.MINIFS($P$2:$P$175,$A$2:$A$175,$A88,$C$2:$C$175,$C88,$AC$2:$AC$175,1),"")
A89: Fintepla | B89: Fenfluramine | C89: Dravet syndrome | D89: Zogenix | E89: Zogenix (UCB) | F89: Small molecule | G89: Neurology (epilepsy) | H89: Ultra-severe (immediately life-threatening) | I89: Sweden | J89: Other / unclassified process | K89: Clinical guidance / regional specialist use; no Dravet reimbursement | L89: Restricted / not reimbursed for Dravet | M89: Negative | N89: Not Applicable | O89: Clinical evidence uncertainty | P89: 2025 | Q89: 04/07/2025 guideline | R89: Other / mixed comparator | S89: Valproate + stiripentol + clobazam background therapy | T89: Not specified / unclear | U89: Price / cost-effectiveness | V89: No public Dravet ICER | W89: Long-term cardiac safety; regional budget impact; lack of Dravet reimbursement | X89: Use only after insufficient effect of valproate + stiripentol + clobazam; university hospital paediatric neurology dialogue; seizure diary; labs; echocardiography | Y89: Fintepla reimbursed for LGS, not Dravet | Z89: Code as: restricted regional clinic funding / no national reimbursement | AA89: Primary xlsx database | AB89: 33 | AC89: =IF(OR($M89="Positive",$M89="Restricted Positive"),1,0) -> 0 | AD89: =IF($M89="Not Evaluated",0,1) -> 1 | AG89: no public Dravet ICER | AH89: Small molecule | AI89: =IF(COUNTIFS($A$2:$A$175,$A89,$C$2:$C$175,$C89,$AC$2:$AC$175,1)>0,1,0) -> 1 | AJ89: =IFERROR(_xludf.MINIFS($P$2:$P$175,$A$2:$A$175,$A89,$C$2:$C$175,$C89,$AC$2:$AC$175,1),"")
A90: Fintepla | B90: Fenfluramine | C90: Dravet syndrome | D90: Zogenix | E90: Zogenix (UCB) | F90: Small molecule | G90: Neurology (epilepsy) | H90: Ultra-severe (immediately life-threatening) | I90: Denmark | J90: Full / standard HTA | K90: Medicinrådet assessment + Amgros negotiation | L90: Recommended | M90: Positive | N90: Broad | O90: N/A | P90: 2022 | Q90: 2022-03-24 00:00:00 | R90: Best supportive care / no active treatment | S90: Stiripentol for stiripentol-naïve patients; placebo add-on where stiripentol already included | T90: Not specified / unclear | U90: Price / cost-effectiveness | V90: AIP analysis: ~2.2m DKK incremental cost/patient; 5-year budget impact ~6.8m DKK; confidential net values redacted | W90: Mortality assumptions, treatment duration, lifelong cost, dose assumptions | X90: Add-on therapy to standard treatment; specialist hospital use | Y90: Markov model, 28-day cycles; states: on treatment, stopped treatment, death | Z90: Strong Danish positive access case; good for “MEA/procurement success” pivot | AA90: Primary xlsx database | AB90: 33 | AC90: =IF(OR($M90="Positive",$M90="Restricted Positive"),1,0) -> 1 | AD90: =IF($M90="Not Evaluated",0,1) -> 1 | AH90: Small molecule | AI90: =IF(COUNTIFS($A$2:$A$175,$A90,$C$2:$C$175,$C90,$AC$2:$AC$175,1)>0,1,0) -> 1 | AJ90: =IFERROR(_xludf.MINIFS($P$2:$P$175,$A$2:$A$175,$A90,$C$2:$C$175,$C90,$AC$2:$AC$175,1),"")
A91: Fintepla | B91: Fenfluramine | C91: Dravet syndrome | D91: Zogenix | E91: Zogenix (UCB) | F91: Small molecule | G91: Neurology (epilepsy) | H91: Ultra-severe (immediately life-threatening) | I91: Norway | J91: Managed introduction / price negotiation | K91: Nye Metoder / DMP + Sykehusinnkjøp + Beslutningsforum | L91: Not introduced initially; later should be coded according to latest official decision you have | M91: Ongoing/Pending | N91: Not Applicable | O91: N/A | P91: 2024 | Q91: 12/02/2024 negative; check final positive date if confirmed | R91: Other / mixed comparator | S91: Cannabidiol / Epidyolex | T91: Not specified / unclear | U91: Administrative/procedural + Clinical evidence uncertainty + Price / cost-effectiveness | V91: ICER not public; price note confidential | W91: Price too high vs documented clinical benefit; uncertainty vs cannabidiol | X91: Add-on therapy ≥2 years; specialist initiation | Y91: Beslutningsforum wanted use but rejected due to price; asked Sykehusinnkjøp to renegotiat | Z91: Code as “price-driven rejection / renegotiation”; update to “recommended” only if final approval document is confirmed | AA91: Primary xlsx database | AB91: 33 | AC91: =IF(OR($M91="Positive",$M91="Restricted Positive"),1,0) -> 0 | AD91: =IF($M91="Not Evaluated",0,1) -> 1 | AH91: Small molecule | AI91: =IF(COUNTIFS($A$2:$A$175,$A91,$C$2:$C$175,$C91,$AC$2:$AC$175,1)>0,1,0) -> 1 | AJ91: =IFERROR(_xludf.MINIFS($P$2:$P$175,$A$2:$A$175,$A91,$C$2:$C$175,$C91,$AC$2:$AC$175,1),"")
A92: Diacomit | B92: Stiripentol | C92: Dravet syndrome | D92: Biocodex | E92: Biocodex | F92: Small molecule | G92: Neurology (epilepsy) | H92: Ultra-severe (immediately life-threatening) | I92: Sweden | J92: Other / unclassified process | K92: TLV outpatient reimbursement, older orphan drug | L92: Reimbursed | M92: Positive | N92: Broad | O92: N/A | P92: 2016 | Q92: Historical; follow-up condition removed 2016 | R92: Best supportive care / no active treatment | S92: Placebo add-on to clobazam + valproate | T92: Not specified / unclear | U92: Clinical evidence uncertainty | V92: No modern ICER | W92: Older evidence base; limited modern HTA uncertainty | X92: Adjunct to clobazam + valproate | Y92: Established standard therapy | Z92: Code as “grandfathered / established reimbursed SoC” | AA92: Primary xlsx database | AB92: 34 | AC92: =IF(OR($M92="Positive",$M92="Restricted Positive"),1,0) -> 1 | AD92: =IF($M92="Not Evaluated",0,1) -> 1 | AG92: no modern ICER | AH92: Small molecule | AI92: =IF(COUNTIFS($A$2:$A$175,$A92,$C$2:$C$175,$C92,$AC$2:$AC$175,1)>0,1,0) -> 1 | AJ92: =IFERROR(_xludf.MINIFS($P$2:$P$175,$A$2:$A$175,$A92,$C$2:$C$175,$C92,$AC$2:$AC$175,1),"")
A93: Diacomit | B93: Stiripentol | C93: Dravet syndrome | D93: Biocodex | E93: Biocodex | F93: Small molecule | G93: Neurology (epilepsy) | H93: Ultra-severe (immediately life-threatening) | I93: Denmark | J93: Other / unclassified process | K93: Historical access; used as standard comparator/background therapy | L93: Reimbursed / established SoC | M93: Positive | N93: Broad | O93: N/A | Q93: Historical / pre-modern Medicinrådet | R93: Best supportive care / no active treatment | S93: Placebo add-on to clobazam + valproate | T93: Not specified / unclear | U93: Comparator/positioning issue | V93: No modern ICER | W93: Not reassessed under modern HTA | X93: Used as part of standard therapy | Y93: Medicinrådet uses stiripentol as key comparator/background in Fintepla assessment | Z93: Code as “established comparator / pre-modern reimbursement” | AA93: Primary xlsx database | AB93: 34 | AC93: =IF(OR($M93="Positive",$M93="Restricted Positive"),1,0) -> 1 | AD93: =IF($M93="Not Evaluated",0,1) -> 1 | AH93: Small molecule | AI93: =IF(COUNTIFS($A$2:$A$175,$A93,$C$2:$C$175,$C93,$AC$2:$AC$175,1)>0,1,0) -> 1 | AJ93: =IFERROR(_xludf.MINIFS($P$2:$P$175,$A$2:$A$175,$A93,$C$2:$C$175,$C93,$AC$2:$AC$175,1),"")
A94: Diacomit | B94: Stiripentol | C94: Dravet syndrome | D94: Biocodex | E94: Biocodex | F94: Small molecule | G94: Neurology (epilepsy) | H94: Ultra-severe (immediately life-threatening) | I94: Norway | J94: Other / unclassified process | K94: Historical access; not ordered for separate Nye Metoder assessment | L94: Established / available, but not separately assessed | M94: Positive | N94: Broad | O94: N/A | Q94: Historical | R94: Other / mixed comparator | S94: Valproate + clobazam | T94: Not specified / unclear | U94: Not specified | V94: No ICER | W94: No modern HTA | X94: Add-on after valproate + clobazam insufficient | Y94: Norwegian method alert states stiripentol may be considered after valproate + clobazam failure | Z94: Code as “standard care / not separately HTA-assessed” | AA94: Primary xlsx database | AB94: 34 | AC94: =IF(OR($M94="Positive",$M94="Restricted Positive"),1,0) -> 1 | AD94: =IF($M94="Not Evaluated",0,1) -> 1 | AH94: Small molecule | AI94: =IF(COUNTIFS($A$2:$A$175,$A94,$C$2:$C$175,$C94,$AC$2:$AC$175,1)>0,1,0) -> 1 | AJ94: =IFERROR(_xludf.MINIFS($P$2:$P$175,$A$2:$A$175,$A94,$C$2:$C$175,$C94,$AC$2:$AC$175,1),"")
A95: Takhzyro | B95: Lanadelumab | C95: Hereditary angioedema | D95: Takeda Pharma AB | E95: Takeda | F95: Monoclonal antibody | G95: Immunology | H95: Serious (chronic, manageable) | I95: Sweden | J95: Full / standard HTA | K95: TLV outpatient reimbursement assessment | L95: Approved with restriction / limited subsidy | M95: Restricted Positive | N95: Restricted | O95: N/A | P95: 2022 | Q95: 01/01/2022; expanded 14/06/2024 | R95: Other / mixed comparator | S95: Acute on-demand treatment only | T95: Not specified / unclear | U95: Price / cost-effectiveness | V95: Exact ICER not public; TLV judged cost reasonable only in restricted high-attack subgroup | W95: Dose-spacing in practice; long-term budget impact; high cost | X95: Severe HAE; ≥4 HAE attacks/month; age restriction removed after pediatric expansion | Y95: TLV accepted Takhzyro for patients with severe disease and high acute-treatment use; 2024 decision expanded to patients from 2 years | Z95: Strong restricted-access case; good pivot code: positive with restriction + severity threshold | AA95: Primary xlsx database | AB95: 35 | AC95: =IF(OR($M95="Positive",$M95="Restricted Positive"),1,0) -> 1 | AD95: =IF($M95="Not Evaluated",0,1) -> 1 | AG95: not public - judged reasonable only in restricted subgroup | AH95: Monoclonal antibody | AI95: =IF(COUNTIFS($A$2:$A$175,$A95,$C$2:$C$175,$C95,$AC$2:$AC$175,1)>0,1,0) -> 1 | AJ95: =IFERROR(_xludf.MINIFS($P$2:$P$175,$A$2:$A$175,$A95,$C$2:$C$175,$C95,$AC$2:$AC$175,1),"")
A96: Takhzyro | B96: Lanadelumab | C96: Hereditary angioedema | D96: Takeda Pharma AB | E96: Takeda | F96: Monoclonal antibody | G96: Immunology | H96: Serious (chronic, manageable) | I96: Denmark | J96: Full / standard HTA | K96: Medicinrådet assessment + Amgros negotiation | L96: Recommended with restriction | M96: Restricted Positive | N96: Restricted | O96: N/A | P96: 2019 | Q96: Missing information / first recommendation reported around 2019 | R96: Active comparator drug(s) | S96: On-demand acute treatment / existing prophylaxis context | T96: Not specified / unclear | U96: Administrative/procedural + Price / cost-effectiveness | V96: ot public / confidential Amgros pricing | W96: Comparative value vs existing prophylaxis; confidential net price | X96: Specialist use for severe HAE; exact Danish criteria need official source confirmation | Y96: Public upload set does not include Danish primary document; use as provisional until official Medicinrådet/Amgros source is stored | Z96: Code as positive restricted, but mark “official source pending” | AA96: Primary xlsx database | AB96: 35 | AC96: =IF(OR($M96="Positive",$M96="Restricted Positive"),1,0) -> 1 | AD96: =IF($M96="Not Evaluated",0,1) -> 1 | AH96: Monoclonal antibody | AI96: =IF(COUNTIFS($A$2:$A$175,$A96,$C$2:$C$175,$C96,$AC$2:$AC$175,1)>0,1,0) -> 1 | AJ96: =IFERROR(_xludf.MINIFS($P$2:$P$175,$A$2:$A$175,$A96,$C$2:$C$175,$C96,$AC$2:$AC$175,1),"")
A97: Takhzyro | B97: Lanadelumab | C97: Hereditary angioedema | D97: Takeda Pharma AB | E97: Takeda | F97: Monoclonal antibody | G97: Immunology | H97: Serious (chronic, manageable) | I97: Norway | J97: Managed introduction / price negotiation | K97: Nye Metoder / DMP reassessment + Sykehusinnkjøp price negotiation | L97: Introduced with conditions | M97: Restricted Positive | N97: Restricted | O97: N/A | P97: 2024 | Q97: 23/09/2024; pediatric price note 2026 | R97: Active comparator drug(s) | S97: Orladeyo became the relevant current comparator in Norway | T97: Not specified / unclear | U97: Comparator/positioning issue + Price / cost-effectiveness | V97: ICER/cost-effectiveness not public; confidential prices used | W97: Indirect comparison vs Orladeyo; long-term efficacy; dose-spacing; utility mapping | X97: ≥12 years initially; ≥1 severe attack/week at start; evaluate after 3 months and stop if attacks not reduced by 50%; children 2–11 assessed separately | Y97: DMP states Orladeyo is current standard comparator; pediatric expansion handled through price note | Z97: Strong managed-entry success; important for pivot: positive after reassessment + active comparator + stop rule | AA97: Primary xlsx database | AB97: 35 | AC97: =IF(OR($M97="Positive",$M97="Restricted Positive"),1,0) -> 1 | AD97: =IF($M97="Not Evaluated",0,1) -> 1 | AH97: Monoclonal antibody | AI97: =IF(COUNTIFS($A$2:$A$175,$A97,$C$2:$C$175,$C97,$AC$2:$AC$175,1)>0,1,0) -> 1 | AJ97: =IFERROR(_xludf.MINIFS($P$2:$P$175,$A$2:$A$175,$A97,$C$2:$C$175,$C97,$AC$2:$AC$175,1),"")
A98: Orkambi | B98: Lumacaftor/Ivacaftor | C98: Cystic fibrosis | D98: Vertex Pharmaceuticals (Ireland) Limited | E98: Vertex Pharmaceuticals | F98: Small molecule (CFTR modulator) | G98: Pulmonology | H98: Severe (progressive, life-shortening) | I98: Sweden | J98: Full / standard HTA | K98: TLV outpatient benefit assessment | L98: Reimbursed / restricted | M98: Restricted Positive | N98: Restricted | O98: N/A | P98: 2018 | Q98: 2018-07-01 00:00:00 | R98: Best supportive care / no active treatment | S98: BSC | T98: Not specified / unclear | U98: Price / cost-effectiveness | V98: missing | W98: Modest clinical benefit, long-term survival extrapolation | X98: F508del homozygous; specialist CF care | Y98: Included in high-cost protection; later part of CFTR portfolio context | AA98: Primary xlsx database | AB98: 36 | AC98: =IF(OR($M98="Positive",$M98="Restricted Positive"),1,0) -> 1 | AD98: =IF($M98="Not Evaluated",0,1) -> 1 | AG98: missing | AH98: Small molecule | AI98: =IF(COUNTIFS($A$2:$A$175,$A98,$C$2:$C$175,$C98,$AC$2:$AC$175,1)>0,1,0) -> 1 | AJ98: =IFERROR(_xludf.MINIFS($P$2:$P$175,$A$2:$A$175,$A98,$C$2:$C$175,$C98,$AC$2:$AC$175,1),"")
A99: Orkambi | B99: Lumacaftor/Ivacaftor | C99: Cystic fibrosis | D99: Vertex Pharmaceuticals (Ireland) Limited | E99: Vertex Pharmaceuticals | F99: Small molecule (CFTR modulator) | G99: Pulmonology | H99: Severe (progressive, life-shortening) | I99: Denmark | J99: Other / unclassified process | K99: Amgros portfolio agreement; limited public HTA detail | L99: Reimbursed through portfolio access | M99: Positive | N99: Broad | O99: N/A | P99: 2018 | Q99: 2018-10-01 00:00:00 | R99: Best supportive care / no active treatment | S99: BSC / portfolio context | T99: Not specified / unclear | U99: Not specified | V99: not public | W99: Missing information on standalone HTA | X99: F508del homozygous | Z99: Fixed annual portfolio agreement across Vertex CFTR modulators | AA99: Primary xlsx database | AB99: 36 | AC99: =IF(OR($M99="Positive",$M99="Restricted Positive"),1,0) -> 1 | AD99: =IF($M99="Not Evaluated",0,1) -> 1 | AH99: Small molecule | AI99: =IF(COUNTIFS($A$2:$A$175,$A99,$C$2:$C$175,$C99,$AC$2:$AC$175,1)>0,1,0) -> 1 | AJ99: =IFERROR(_xludf.MINIFS($P$2:$P$175,$A$2:$A$175,$A99,$C$2:$C$175,$C99,$AC$2:$AC$175,1),"")
A100: Orkambi | B100: Lumacaftor/Ivacaftor | C100: Cystic fibrosis | D100: Vertex Pharmaceuticals (Ireland) Limited | E100: Vertex Pharmaceuticals | F100: Small molecule (CFTR modulator) | G100: Pulmonology | H100: Severe (progressive, life-shortening) | I100: Norway | J100: Managed introduction / price negotiation | K100: Nye Metoder + Sykehusinnkjøp price note | L100: Introduced after agreement | M100: Positive | N100: Broad | O100: N/A | P100: 2022 | Q100: 25/04/2022; extension >1 year assessed 27/05/2024 | R100: Best supportive care / no active treatment | S100: BSC | T100: Not specified / unclear | U100: Price / cost-effectiveness | V100: Not calculated for 2024 extension | W100: No new CE model for 1-year extension; low expected budget impact | X100: F508del homozygous; age ≥1 after extension | Z100: Alternative price agreement linked to original CFTR modulator introduction | AA100: Primary xlsx database | AB100: 36 | AC100: =IF(OR($M100="Positive",$M100="Restricted Positive"),1,0) -> 1 | AD100: =IF($M100="Not Evaluated",0,1) -> 1 | AH100: Small molecule | AI100: =IF(COUNTIFS($A$2:$A$175,$A100,$C$2:$C$175,$C100,$AC$2:$AC$175,1)>0,1,0) -> 1 | AJ100: =IFERROR(_xludf.MINIFS($P$2:$P$175,$A$2:$A$175,$A100,$C$2:$C$175,$C100,$AC$2:$AC$175,1),"")
...

Sheet 01 Country Attractiveness
B2: 1. Country Attractiveness Analysis
B3: Which Nordic country is more permissive, and how has that changed over time? Outcome counts and positive-access rate by country, with Wilson 95% confidence intervals (small-sample-appropriate) and a time trend.
B5: Table A - Access outcome distribution by country (counts, live formulas)
B6: Country | C6: Positive | D6: Restricted Positive | E6: Negative | F6: Withdrawn | G6: Ongoing/Pending | H6: Not Evaluated | I6: Total records | J6: Total assessed (excl. Not Evaluated) | K6: % Positive or Restricted Positive of assessed | L6: Wilson 95% CI lower | M6: Wilson 95% CI upper
B7: Sweden | C7: =COUNTIFS('Master Data'!$I$2:$I$175,"Sweden",'Master Data'!$M$2:$M$175,"Positive") -> 8 | D7: =COUNTIFS('Master Data'!$I$2:$I$175,"Sweden",'Master Data'!$M$2:$M$175,"Restricted Positive") -> 18 | E7: =COUNTIFS('Master Data'!$I$2:$I$175,"Sweden",'Master Data'!$M$2:$M$175,"Negative") -> 14 | F7: =COUNTIFS('Master Data'!$I$2:$I$175,"Sweden",'Master Data'!$M$2:$M$175,"Withdrawn") -> 3 | G7: =COUNTIFS('Master Data'!$I$2:$I$175,"Sweden",'Master Data'!$M$2:$M$175,"Ongoing/Pending") -> 6 | H7: =COUNTIFS('Master Data'!$I$2:$I$175,"Sweden",'Master Data'!$M$2:$M$175,"Not Evaluated") -> 9 | I7: =SUM(C7:H7) -> 58 | J7: =I7-H7 -> 49 | K7: =IF(J7=0,"",((C7+D7)/J7)) -> 0.53061224 | L7: =IF(J7=0,"",MAX(0,((((C7+D7)/J7)+1.959963985^2/(2*J7))/(1+1.959963985^2/J7))-((1.959963985*SQRT((((C7+D7)/J7)*(1-((C7+D7)/J7))/J7)+(1.959963985^2/(4*J7^2))))/(1+1.959963985^2/J7)))) -> 0.39380864 | M7: =IF(J7=0,"",MIN(1,((((C7+D7)/J7)+1.959963985^2/(2*J7))/(1+1.959963985^2/J7))+((1.959963985*SQRT((((C7+D7)/J7)*(1-((C7+D7)/J7))/J7)+(1.959963985^2/(4*J7^2))))/(1+1.959963985^2/J7)))) -> 0.66296496
B8: Denmark | C8: =COUNTIFS('Master Data'!$I$2:$I$175,"Denmark",'Master Data'!$M$2:$M$175,"Positive") -> 14 | D8: =COUNTIFS('Master Data'!$I$2:$I$175,"Denmark",'Master Data'!$M$2:$M$175,"Restricted Positive") -> 11 | E8: =COUNTIFS('Master Data'!$I$2:$I$175,"Denmark",'Master Data'!$M$2:$M$175,"Negative") -> 12 | F8: =COUNTIFS('Master Data'!$I$2:$I$175,"Denmark",'Master Data'!$M$2:$M$175,"Withdrawn") -> 2 | G8: =COUNTIFS('Master Data'!$I$2:$I$175,"Denmark",'Master Data'!$M$2:$M$175,"Ongoing/Pending") -> 1 | H8: =COUNTIFS('Master Data'!$I$2:$I$175,"Denmark",'Master Data'!$M$2:$M$175,"Not Evaluated") -> 18 | I8: =SUM(C8:H8) -> 58 | J8: =I8-H8 -> 40 | K8: =IF(J8=0,"",((C8+D8)/J8)) -> 0.625 | L8: =IF(J8=0,"",MAX(0,((((C8+D8)/J8)+1.959963985^2/(2*J8))/(1+1.959963985^2/J8))-((1.959963985*SQRT((((C8+D8)/J8)*(1-((C8+D8)/J8))/J8)+(1.959963985^2/(4*J8^2))))/(1+1.959963985^2/J8)))) -> 0.47032439 | M8: =IF(J8=0,"",MIN(1,((((C8+D8)/J8)+1.959963985^2/(2*J8))/(1+1.959963985^2/J8))+((1.959963985*SQRT((((C8+D8)/J8)*(1-((C8+D8)/J8))/J8)+(1.959963985^2/(4*J8^2))))/(1+1.959963985^2/J8)))) -> 0.75777021
B9: Norway | C9: =COUNTIFS('Master Data'!$I$2:$I$175,"Norway",'Master Data'!$M$2:$M$175,"Positive") -> 13 | D9: =COUNTIFS('Master Data'!$I$2:$I$175,"Norway",'Master Data'!$M$2:$M$175,"Restricted Positive") -> 7 | E9: =COUNTIFS('Master Data'!$I$2:$I$175,"Norway",'Master Data'!$M$2:$M$175,"Negative") -> 12 | F9: =COUNTIFS('Master Data'!$I$2:$I$175,"Norway",'Master Data'!$M$2:$M$175,"Withdrawn") -> 3 | G9: =COUNTIFS('Master Data'!$I$2:$I$175,"Norway",'Master Data'!$M$2:$M$175,"Ongoing/Pending") -> 8 | H9: =COUNTIFS('Master Data'!$I$2:$I$175,"Norway",'Master Data'!$M$2:$M$175,"Not Evaluated") -> 15 | I9: =SUM(C9:H9) -> 58 | J9: =I9-H9 -> 43 | K9: =IF(J9=0,"",((C9+D9)/J9)) -> 0.46511628 | L9: =IF(J9=0,"",MAX(0,((((C9+D9)/J9)+1.959963985^2/(2*J9))/(1+1.959963985^2/J9))-((1.959963985*SQRT((((C9+D9)/J9)*(1-((C9+D9)/J9))/J9)+(1.959963985^2/(4*J9^2))))/(1+1.959963985^2/J9)))) -> 0.32511058 | M9: =IF(J9=0,"",MIN(1,((((C9+D9)/J9)+1.959963985^2/(2*J9))/(1+1.959963985^2/J9))+((1.959963985*SQRT((((C9+D9)/J9)*(1-((C9+D9)/J9))/J9)+(1.959963985^2/(4*J9^2))))/(1+1.959963985^2/J9)))) -> 0.6108436
B11: Wilson score interval used (not normal approximation) because country subgroup sample sizes are small (n=40 to n=49 assessed records) and proportions can sit near 0/1. "Restricted Positive" = reimbursed/recommended only with conditions (subgroup, MEA, price agreement, etc.) - counted as access for the headline rate, but see Table B in sheet 02 for the access-vs-restriction distinction.
B13: Table B - Positive-access rate trend over time, by country
B14: Country | C14: Pre-2022 | D14: 2022-2023 | E14: 2024-2026
B15: Sweden | C15: =IF(COUNTIFS('Master Data'!$I$2:$I$175,"Sweden",'Master Data'!$P$2:$P$175,">="&0,'Master Data'!$P$2:$P$175,"<="&2021,'Master Data'!$AD$2:$AD$175,1)=0,"n/a",COUNTIFS('Master Data'!$I$2:$I$175,"Sweden",'Master Data'!$P$2:$P$175,">="&0,'Master Data'!$P$2:$P$175,"<="&2021,'Master Data'!$AC$2:$AC$175,1)/COUNTIFS('Master Data'!$I$2:$I$175,"Sweden",'Master Data'!$P$2:$P$175,">="&0,'Master Data'!$P$2:$P$175,"<="&2021,'Master Data'!$AD$2:$AD$175,1)) -> 0.78571429 | D15: =IF(COUNTIFS('Master Data'!$I$2:$I$175,"Sweden",'Master Data'!$P$2:$P$175,">="&2022,'Master Data'!$P$2:$P$175,"<="&2023,'Master Data'!$AD$2:$AD$175,1)=0,"n/a",COUNTIFS('Master Data'!$I$2:$I$175,"Sweden",'Master Data'!$P$2:$P$175,">="&2022,'Master Data'!$P$2:$P$175,"<="&2023,'Master Data'!$AC$2:$AC$175,1)/COUNTIFS('Master Data'!$I$2:$I$175,"Sweden",'Master Data'!$P$2:$P$175,">="&2022,'Master Data'!$P$2:$P$175,"<="&2023,'Master Data'!$AD$2:$AD$175,1)) -> 0.44444444 | E15: =IF(COUNTIFS('Master Data'!$I$2:$I$175,"Sweden",'Master Data'!$P$2:$P$175,">="&2024,'Master Data'!$P$2:$P$175,"<="&2026,'Master Data'!$AD$2:$AD$175,1)=0,"n/a",COUNTIFS('Master Data'!$I$2:$I$175,"Sweden",'Master Data'!$P$2:$P$175,">="&2024,'Master Data'!$P$2:$P$175,"<="&2026,'Master Data'!$AC$2:$AC$175,1)/COUNTIFS('Master Data'!$I$2:$I$175,"Sweden",'Master Data'!$P$2:$P$175,">="&2024,'Master Data'!$P$2:$P$175,"<="&2026,'Master Data'!$AD$2:$AD$175,1)) -> 0.42857143
B16: Denmark | C16: =IF(COUNTIFS('Master Data'!$I$2:$I$175,"Denmark",'Master Data'!$P$2:$P$175,">="&0,'Master Data'!$P$2:$P$175,"<="&2021,'Master Data'!$AD$2:$AD$175,1)=0,"n/a",COUNTIFS('Master Data'!$I$2:$I$175,"Denmark",'Master Data'!$P$2:$P$175,">="&0,'Master Data'!$P$2:$P$175,"<="&2021,'Master Data'!$AC$2:$AC$175,1)/COUNTIFS('Master Data'!$I$2:$I$175,"Denmark",'Master Data'!$P$2:$P$175,">="&0,'Master Data'!$P$2:$P$175,"<="&2021,'Master Data'!$AD$2:$AD$175,1)) -> 0.73333333 | D16: =IF(COUNTIFS('Master Data'!$I$2:$I$175,"Denmark",'Master Data'!$P$2:$P$175,">="&2022,'Master Data'!$P$2:$P$175,"<="&2023,'Master Data'!$AD$2:$AD$175,1)=0,"n/a",COUNTIFS('Master Data'!$I$2:$I$175,"Denmark",'Master Data'!$P$2:$P$175,">="&2022,'Master Data'!$P$2:$P$175,"<="&2023,'Master Data'!$AC$2:$AC$175,1)/COUNTIFS('Master Data'!$I$2:$I$175,"Denmark",'Master Data'!$P$2:$P$175,">="&2022,'Master Data'!$P$2:$P$175,"<="&2023,'Master Data'!$AD$2:$AD$175,1)) -> 0.5 | E16: =IF(COUNTIFS('Master Data'!$I$2:$I$175,"Denmark",'Master Data'!$P$2:$P$175,">="&2024,'Master Data'!$P$2:$P$175,"<="&2026,'Master Data'!$AD$2:$AD$175,1)=0,"n/a",COUNTIFS('Master Data'!$I$2:$I$175,"Denmark",'Master Data'!$P$2:$P$175,">="&2024,'Master Data'!$P$2:$P$175,"<="&2026,'Master Data'!$AC$2:$AC$175,1)/COUNTIFS('Master Data'!$I$2:$I$175,"Denmark",'Master Data'!$P$2:$P$175,">="&2024,'Master Data'!$P$2:$P$175,"<="&2026,'Master Data'!$AD$2:$AD$175,1)) -> 0.64705882
B17: Norway | C17: =IF(COUNTIFS('Master Data'!$I$2:$I$175,"Norway",'Master Data'!$P$2:$P$175,">="&0,'Master Data'!$P$2:$P$175,"<="&2021,'Master Data'!$AD$2:$AD$175,1)=0,"n/a",COUNTIFS('Master Data'!$I$2:$I$175,"Norway",'Master Data'!$P$2:$P$175,">="&0,'Master Data'!$P$2:$P$175,"<="&2021,'Master Data'!$AC$2:$AC$175,1)/COUNTIFS('Master Data'!$I$2:$I$175,"Norway",'Master Data'!$P$2:$P$175,">="&0,'Master Data'!$P$2:$P$175,"<="&2021,'Master Data'!$AD$2:$AD$175,1)) -> 0.75 | D17: =IF(COUNTIFS('Master Data'!$I$2:$I$175,"Norway",'Master Data'!$P$2:$P$175,">="&2022,'Master Data'!$P$2:$P$175,"<="&2023,'Master Data'!$AD$2:$AD$175,1)=0,"n/a",COUNTIFS('Master Data'!$I$2:$I$175,"Norway",'Master Data'!$P$2:$P$175,">="&2022,'Master Data'!$P$2:$P$175,"<="&2023,'Master Data'!$AC$2:$AC$175,1)/COUNTIFS('Master Data'!$I$2:$I$175,"Norway",'Master Data'!$P$2:$P$175,">="&2022,'Master Data'!$P$2:$P$175,"<="&2023,'Master Data'!$AD$2:$AD$175,1)) -> 0.75 | E17: =IF(COUNTIFS('Master Data'!$I$2:$I$175,"Norway",'Master Data'!$P$2:$P$175,">="&2024,'Master Data'!$P$2:$P$175,"<="&2026,'Master Data'!$AD$2:$AD$175,1)=0,"n/a",COUNTIFS('Master Data'!$I$2:$I$175,"Norway",'Master Data'!$P$2:$P$175,">="&2024,'Master Data'!$P$2:$P$175,"<="&2026,'Master Data'!$AC$2:$AC$175,1)/COUNTIFS('Master Data'!$I$2:$I$175,"Norway",'Master Data'!$P$2:$P$175,">="&2024,'Master Data'!$P$2:$P$175,"<="&2026,'Master Data'!$AD$2:$AD$175,1)) -> 0.21052632
B19: Buckets group decisions by Decision_Year extracted from free-text decision dates (available for 136 of 174 records). "n/a" = no dated, assessed records in that country/period.
B21: Table C - Restriction level by country (broad vs tightly managed access)
B22: Country | C22: Broad (no restriction) | D22: Restricted / managed | E22: Not applicable | F22: % of positive access that is Restricted
B23: Sweden | C23: =COUNTIFS('Master Data'!$I$2:$I$175,"Sweden",'Master Data'!$N$2:$N$175,"Broad") -> 8 | D23: =COUNTIFS('Master Data'!$I$2:$I$175,"Sweden",'Master Data'!$N$2:$N$175,"Restricted") -> 18 | E23: =COUNTIFS('Master Data'!$I$2:$I$175,"Sweden",'Master Data'!$N$2:$N$175,"Not Applicable") -> 32 | F23: =IF((C23+D23)=0,"n/a",D23/(C23+D23)) -> 0.69230769
B24: Denmark | C24: =COUNTIFS('Master Data'!$I$2:$I$175,"Denmark",'Master Data'!$N$2:$N$175,"Broad") -> 14 | D24: =COUNTIFS('Master Data'!$I$2:$I$175,"Denmark",'Master Data'!$N$2:$N$175,"Restricted") -> 11 | E24: =COUNTIFS('Master Data'!$I$2:$I$175,"Denmark",'Master Data'!$N$2:$N$175,"Not Applicable") -> 33 | F24: =IF((C24+D24)=0,"n/a",D24/(C24+D24)) -> 0.44
B25: Norway | C25: =COUNTIFS('Master Data'!$I$2:$I$175,"Norway",'Master Data'!$N$2:$N$175,"Broad") -> 13 | D25: =COUNTIFS('Master Data'!$I$2:$I$175,"Norway",'Master Data'!$N$2:$N$175,"Restricted") -> 7 | E25: =COUNTIFS('Master Data'!$I$2:$I$175,"Norway",'Master Data'!$N$2:$N$175,"Not Applicable") -> 38 | F25: =IF((C25+D25)=0,"n/a",D25/(C25+D25)) -> 0.35

Sheet 02 Access Pathways
B2: 2. Access Pathways, Decision Type & Restrictions
B3: Which countries provide broad vs tightly managed access, and how does that interact with the assessment process used (not just country)?
B5: Table A - Decision process type, by country (counts and % share of that country's total)
B6: Decision Type | C6: Sweden | D6: Denmark | E6: Norway | F6: Total | G6: % of Sweden total | H6: % of Denmark total | I6: % of Norway total
B7: Full / standard HTA | C7: =COUNTIFS('Master Data'!$J$2:$J$175,"Full / standard HTA",'Master Data'!$I$2:$I$175,"Sweden") -> 18 | D7: =COUNTIFS('Master Data'!$J$2:$J$175,"Full / standard HTA",'Master Data'!$I$2:$I$175,"Denmark") -> 20 | E7: =COUNTIFS('Master Data'!$J$2:$J$175,"Full / standard HTA",'Master Data'!$I$2:$I$175,"Norway") -> 5 | F7: =SUM(C7:E7) -> 43 | G7: =IF(C14=0,"n/a",C7/C14) -> 0.31034483 | H7: =IF(D14=0,"n/a",D7/D14) -> 0.34482759 | I7: =IF(E14=0,"n/a",E7/E14) -> 0.086206897
B8: Rapid / simplified HTA | C8: =COUNTIFS('Master Data'!$J$2:$J$175,"Rapid / simplified HTA",'Master Data'!$I$2:$I$175,"Sweden") -> 0 | D8: =COUNTIFS('Master Data'!$J$2:$J$175,"Rapid / simplified HTA",'Master Data'!$I$2:$I$175,"Denmark") -> 0 | E8: =COUNTIFS('Master Data'!$J$2:$J$175,"Rapid / simplified HTA",'Master Data'!$I$2:$I$175,"Norway") -> 8 | F8: =SUM(C8:E8) -> 8 | G8: =IF(C14=0,"n/a",C8/C14) -> 0 | H8: =IF(D14=0,"n/a",D8/D14) -> 0 | I8: =IF(E14=0,"n/a",E8/E14) -> 0.13793103
B9: Joint Nordic HTA (FINOSE/JNHB) | C9: =COUNTIFS('Master Data'!$J$2:$J$175,"Joint Nordic HTA (FINOSE/JNHB)",'Master Data'!$I$2:$I$175,"Sweden") -> 2 | D9: =COUNTIFS('Master Data'!$J$2:$J$175,"Joint Nordic HTA (FINOSE/JNHB)",'Master Data'!$I$2:$I$175,"Denmark") -> 2 | E9: =COUNTIFS('Master Data'!$J$2:$J$175,"Joint Nordic HTA (FINOSE/JNHB)",'Master Data'!$I$2:$I$175,"Norway") -> 3 | F9: =SUM(C9:E9) -> 7 | G9: =IF(C14=0,"n/a",C9/C14) -> 0.034482759 | H9: =IF(D14=0,"n/a",D9/D14) -> 0.034482759 | I9: =IF(E14=0,"n/a",E9/E14) -> 0.051724138
B10: Managed introduction / price negotiation | C10: =COUNTIFS('Master Data'!$J$2:$J$175,"Managed introduction / price negotiation",'Master Data'!$I$2:$I$175,"Sweden") -> 12 | D10: =COUNTIFS('Master Data'!$J$2:$J$175,"Managed introduction / price negotiation",'Master Data'!$I$2:$I$175,"Denmark") -> 4 | E10: =COUNTIFS('Master Data'!$J$2:$J$175,"Managed introduction / price negotiation",'Master Data'!$I$2:$I$175,"Norway") -> 27 | F10: =SUM(C10:E10) -> 43 | G10: =IF(C14=0,"n/a",C10/C14) -> 0.20689655 | H10: =IF(D14=0,"n/a",D10/D14) -> 0.068965517 | I10: =IF(E14=0,"n/a",E10/E14) -> 0.46551724
B11: Early / horizon scanning only | C11: =COUNTIFS('Master Data'!$J$2:$J$175,"Early / horizon scanning only",'Master Data'!$I$2:$I$175,"Sweden") -> 2 | D11: =COUNTIFS('Master Data'!$J$2:$J$175,"Early / horizon scanning only",'Master Data'!$I$2:$I$175,"Denmark") -> 0 | E11: =COUNTIFS('Master Data'!$J$2:$J$175,"Early / horizon scanning only",'Master Data'!$I$2:$I$175,"Norway") -> 2 | F11: =SUM(C11:E11) -> 4 | G11: =IF(C14=0,"n/a",C11/C14) -> 0.034482759 | H11: =IF(D14=0,"n/a",D11/D14) -> 0 | I11: =IF(E14=0,"n/a",E11/E14) -> 0.034482759
B12: No formal assessment / not assessed | C12: =COUNTIFS('Master Data'!$J$2:$J$175,"No formal assessment / not assessed",'Master Data'!$I$2:$I$175,"Sweden") -> 2 | D12: =COUNTIFS('Master Data'!$J$2:$J$175,"No formal assessment / not assessed",'Master Data'!$I$2:$I$175,"Denmark") -> 6 | E12: =COUNTIFS('Master Data'!$J$2:$J$175,"No formal assessment / not assessed",'Master Data'!$I$2:$I$175,"Norway") -> 1 | F12: =SUM(C12:E12) -> 9 | G12: =IF(C14=0,"n/a",C12/C14) -> 0.034482759 | H12: =IF(D14=0,"n/a",D12/D14) -> 0.10344828 | I12: =IF(E14=0,"n/a",E12/E14) -> 0.017241379
B13: Other / unclassified process | C13: =COUNTIFS('Master Data'!$J$2:$J$175,"Other / unclassified process",'Master Data'!$I$2:$I$175,"Sweden") -> 22 | D13: =COUNTIFS('Master Data'!$J$2:$J$175,"Other / unclassified process",'Master Data'!$I$2:$I$175,"Denmark") -> 26 | E13: =COUNTIFS('Master Data'!$J$2:$J$175,"Other / unclassified process",'Master Data'!$I$2:$I$175,"Norway") -> 12 | F13: =SUM(C13:E13) -> 60 | G13: =IF(C14=0,"n/a",C13/C14) -> 0.37931034 | H13: =IF(D14=0,"n/a",D13/D14) -> 0.44827586 | I13: =IF(E14=0,"n/a",E13/E14) -> 0.20689655
B14: Total | C14: =SUM(C7:C13) -> 58 | D14: =SUM(D7:D13) -> 58 | E14: =SUM(E7:E13) -> 58 | F14: =SUM(F7:F13) -> 174 | G14: =100% -> 1 | H14: =100% -> 1 | I14: =100% -> 1
B33: Table B - Restriction level x Decision Type (multivariable: does the PROCESS used, not just the country, predict broad vs restricted access?)
B34: Decision Type | C34: Broad access | D34: Restricted access | E34: Not applicable | F34: % Restricted of (Broad+Restricted)
B35: Full / standard HTA | C35: =COUNTIFS('Master Data'!$J$2:$J$175,"Full / standard HTA",'Master Data'!$N$2:$N$175,"Broad") -> 5 | D35: =COUNTIFS('Master Data'!$J$2:$J$175,"Full / standard HTA",'Master Data'!$N$2:$N$175,"Restricted") -> 14 | E35: =COUNTIFS('Master Data'!$J$2:$J$175,"Full / standard HTA",'Master Data'!$N$2:$N$175,"Not Applicable") -> 24 | F35: =IF((C35+D35)=0,"n/a",D35/(C35+D35)) -> 0.73684211
B36: Rapid / simplified HTA | C36: =COUNTIFS('Master Data'!$J$2:$J$175,"Rapid / simplified HTA",'Master Data'!$N$2:$N$175,"Broad") -> 4 | D36: =COUNTIFS('Master Data'!$J$2:$J$175,"Rapid / simplified HTA",'Master Data'!$N$2:$N$175,"Restricted") -> 2 | E36: =COUNTIFS('Master Data'!$J$2:$J$175,"Rapid / simplified HTA",'Master Data'!$N$2:$N$175,"Not Applicable") -> 2 | F36: =IF((C36+D36)=0,"n/a",D36/(C36+D36)) -> 0.33333333
B37: Joint Nordic HTA (FINOSE/JNHB) | C37: =COUNTIFS('Master Data'!$J$2:$J$175,"Joint Nordic HTA (FINOSE/JNHB)",'Master Data'!$N$2:$N$175,"Broad") -> 2 | D37: =COUNTIFS('Master Data'!$J$2:$J$175,"Joint Nordic HTA (FINOSE/JNHB)",'Master Data'!$N$2:$N$175,"Restricted") -> 1 | E37: =COUNTIFS('Master Data'!$J$2:$J$175,"Joint Nordic HTA (FINOSE/JNHB)",'Master Data'!$N$2:$N$175,"Not Applicable") -> 4 | F37: =IF((C37+D37)=0,"n/a",D37/(C37+D37)) -> 0.33333333
B38: Managed introduction / price negotiation | C38: =COUNTIFS('Master Data'!$J$2:$J$175,"Managed introduction / price negotiation",'Master Data'!$N$2:$N$175,"Broad") -> 11 | D38: =COUNTIFS('Master Data'!$J$2:$J$175,"Managed introduction / price negotiation",'Master Data'!$N$2:$N$175,"Restricted") -> 9 | E38: =COUNTIFS('Master Data'!$J$2:$J$175,"Managed introduction / price negotiation",'Master Data'!$N$2:$N$175,"Not Applicable") -> 23 | F38: =IF((C38+D38)=0,"n/a",D38/(C38+D38)) -> 0.45
B39: Early / horizon scanning only | C39: =COUNTIFS('Master Data'!$J$2:$J$175,"Early / horizon scanning only",'Master Data'!$N$2:$N$175,"Broad") -> 0 | D39: =COUNTIFS('Master Data'!$J$2:$J$175,"Early / horizon scanning only",'Master Data'!$N$2:$N$175,"Restricted") -> 0 | E39: =COUNTIFS('Master Data'!$J$2:$J$175,"Early / horizon scanning only",'Master Data'!$N$2:$N$175,"Not Applicable") -> 4 | F39: =IF((C39+D39)=0,"n/a",D39/(C39+D39)) -> n/a
B40: No formal assessment / not assessed | C40: =COUNTIFS('Master Data'!$J$2:$J$175,"No formal assessment / not assessed",'Master Data'!$N$2:$N$175,"Broad") -> 0 | D40: =COUNTIFS('Master Data'!$J$2:$J$175,"No formal assessment / not assessed",'Master Data'!$N$2:$N$175,"Restricted") -> 0 | E40: =COUNTIFS('Master Data'!$J$2:$J$175,"No formal assessment / not assessed",'Master Data'!$N$2:$N$175,"Not Applicable") -> 9 | F40: =IF((C40+D40)=0,"n/a",D40/(C40+D40)) -> n/a
B41: Other / unclassified process | C41: =COUNTIFS('Master Data'!$J$2:$J$175,"Other / unclassified process",'Master Data'!$N$2:$N$175,"Broad") -> 13 | D41: =COUNTIFS('Master Data'!$J$2:$J$175,"Other / unclassified process",'Master Data'!$N$2:$N$175,"Restricted") -> 10 | E41: =COUNTIFS('Master Data'!$J$2:$J$175,"Other / unclassified process",'Master Data'!$N$2:$N$175,"Not Applicable") -> 37 | F41: =IF((C41+D41)=0,"n/a",D41/(C41+D41)) -> 0.43478261
B61: Table C - Restriction level x Severity tier (multivariable: does disease severity change how tightly access is managed?)
B62: Severity Tier | C62: Broad access | D62: Restricted access | E62: Not applicable | F62: % Restricted of (Broad+Restricted)
B63: Ultra-severe (immediately life-threatening) | C63: =COUNTIFS('Master Data'!$H$2:$H$175,"Ultra-severe (immediately life-threatening)",'Master Data'!$N$2:$N$175,"Broad") -> 14 | D63: =COUNTIFS('Master Data'!$H$2:$H$175,"Ultra-severe (immediately life-threatening)",'Master Data'!$N$2:$N$175,"Restricted") -> 11 | E63: =COUNTIFS('Master Data'!$H$2:$H$175,"Ultra-severe (immediately life-threatening)",'Master Data'!$N$2:$N$175,"Not Applicable") -> 32 | F63: =IF((C63+D63)=0,"n/a",D63/(C63+D63)) -> 0.44
B64: Severe (progressive, life-shortening) | C64: =COUNTIFS('Master Data'!$H$2:$H$175,"Severe (progressive, life-shortening)",'Master Data'!$N$2:$N$175,"Broad") -> 13 | D64: =COUNTIFS('Master Data'!$H$2:$H$175,"Severe (progressive, life-shortening)",'Master Data'!$N$2:$N$175,"Restricted") -> 15 | E64: =COUNTIFS('Master Data'!$H$2:$H$175,"Severe (progressive, life-shortening)",'Master Data'!$N$2:$N$175,"Not Applicable") -> 59 | F64: =IF((C64+D64)=0,"n/a",D64/(C64+D64)) -> 0.53571429
B65: Serious (chronic, manageable) | C65: =COUNTIFS('Master Data'!$H$2:$H$175,"Serious (chronic, manageable)",'Master Data'!$N$2:$N$175,"Broad") -> 8 | D65: =COUNTIFS('Master Data'!$H$2:$H$175,"Serious (chronic, manageable)",'Master Data'!$N$2:$N$175,"Restricted") -> 10 | E65: =COUNTIFS('Master Data'!$H$2:$H$175,"Serious (chronic, manageable)",'Master Data'!$N$2:$N$175,"Not Applicable") -> 12 | F65: =IF((C65+D65)=0,"n/a",D65/(C65+D65)) -> 0.55555556
B67: "Broad" = recommended/reimbursed without named conditions in Decision_Status_Raw. "Restricted" = access granted only for a subgroup, with a managed-entry agreement, price condition, or other named restriction. Both Tables B and C let you see whether restriction is driven more by the HTA process used or by disease severity, rather than treating restriction as purely a country effect (Table C in sheet 01). Denominator: 71/174 records have a Broad-or-Restricted classification at all (the rest are Not Applicable - not assessed, withdrawn, or pending - and are excluded from the % Restricted columns in Tables B and C, but included as their own column for transparency).

Sheet 03 Severity & WTP (Sweden)
B2: 3. Rare Disease Severity & Sweden Willingness-to-Pay (WTP) Analysis
B3: Drugs classified by severity tier, related to TLV's severity-graded cost-per-QALY norms, and flagged where the accepted ICER exceeded the relevant threshold.
B5: Assumptions (editable inputs - blue): TLV severity-graded WTP thresholds, SEK per QALY
B6: Severity Tier | C6: WTP threshold (SEK/QALY)
B7: Ultra-severe (immediately life-threatening) | C7: 2000000
B8: Severe (progressive, life-shortening) | C8: 1000000
B9: Serious (chronic, manageable) | C9: 500000
B11: Source: TLV established severity-graded subvention practice, cross-checked against the Fabhalta/iptacopan decision (May 2026, accepted at SEK 2,035,738/QALY for a very rare/very severe condition) - verified via live web search 2026-06-21. TLV does not publish a single official cutoff; these are reference benchmarks, not binding rules. Edit the blue cells to test alternative thresholds - all formulas below recalculate.
B13: Table A - Severity tier x Access outcome (Sweden only)
B14: Severity Tier | C14: Positive | D14: Restricted Positive | E14: Negative | F14: Withdrawn | G14: Ongoing/Pending | H14: Not Evaluated | I14: Total
B15: Ultra-severe (immediately life-threatening) | C15: =COUNTIFS('Master Data'!$I$2:$I$175,"Sweden",'Master Data'!$H$2:$H$175,"Ultra-severe (immediately life-threatening)",'Master Data'!$M$2:$M$175,"Positive") -> 6 | D15: =COUNTIFS('Master Data'!$I$2:$I$175,"Sweden",'Master Data'!$H$2:$H$175,"Ultra-severe (immediately life-threatening)",'Master Data'!$M$2:$M$175,"Restricted Positive") -> 6 | E15: =COUNTIFS('Master Data'!$I$2:$I$175,"Sweden",'Master Data'!$H$2:$H$175,"Ultra-severe (immediately life-threatening)",'Master Data'!$M$2:$M$175,"Negative") -> 4 | F15: =COUNTIFS('Master Data'!$I$2:$I$175,"Sweden",'Master Data'!$H$2:$H$175,"Ultra-severe (immediately life-threatening)",'Master Data'!$M$2:$M$175,"Withdrawn") -> 1 | G15: =COUNTIFS('Master Data'!$I$2:$I$175,"Sweden",'Master Data'!$H$2:$H$175,"Ultra-severe (immediately life-threatening)",'Master Data'!$M$2:$M$175,"Ongoing/Pending") -> 0 | H15: =COUNTIFS('Master Data'!$I$2:$I$175,"Sweden",'Master Data'!$H$2:$H$175,"Ultra-severe (immediately life-threatening)",'Master Data'!$M$2:$M$175,"Not Evaluated") -> 2 | I15: =SUM(C15:H15) -> 19
B16: Severe (progressive, life-shortening) | C16: =COUNTIFS('Master Data'!$I$2:$I$175,"Sweden",'Master Data'!$H$2:$H$175,"Severe (progressive, life-shortening)",'Master Data'!$M$2:$M$175,"Positive") -> 1 | D16: =COUNTIFS('Master Data'!$I$2:$I$175,"Sweden",'Master Data'!$H$2:$H$175,"Severe (progressive, life-shortening)",'Master Data'!$M$2:$M$175,"Restricted Positive") -> 8 | E16: =COUNTIFS('Master Data'!$I$2:$I$175,"Sweden",'Master Data'!$H$2:$H$175,"Severe (progressive, life-shortening)",'Master Data'!$M$2:$M$175,"Negative") -> 8 | F16: =COUNTIFS('Master Data'!$I$2:$I$175,"Sweden",'Master Data'!$H$2:$H$175,"Severe (progressive, life-shortening)",'Master Data'!$M$2:$M$175,"Withdrawn") -> 1 | G16: =COUNTIFS('Master Data'!$I$2:$I$175,"Sweden",'Master Data'!$H$2:$H$175,"Severe (progressive, life-shortening)",'Master Data'!$M$2:$M$175,"Ongoing/Pending") -> 4 | H16: =COUNTIFS('Master Data'!$I$2:$I$175,"Sweden",'Master Data'!$H$2:$H$175,"Severe (progressive, life-shortening)",'Master Data'!$M$2:$M$175,"Not Evaluated") -> 7 | I16: =SUM(C16:H16) -> 29
B17: Serious (chronic, manageable) | C17: =COUNTIFS('Master Data'!$I$2:$I$175,"Sweden",'Master Data'!$H$2:$H$175,"Serious (chronic, manageable)",'Master Data'!$M$2:$M$175,"Positive") -> 1 | D17: =COUNTIFS('Master Data'!$I$2:$I$175,"Sweden",'Master Data'!$H$2:$H$175,"Serious (chronic, manageable)",'Master Data'!$M$2:$M$175,"Restricted Positive") -> 4 | E17: =COUNTIFS('Master Data'!$I$2:$I$175,"Sweden",'Master Data'!$H$2:$H$175,"Serious (chronic, manageable)",'Master Data'!$M$2:$M$175,"Negative") -> 2 | F17: =COUNTIFS('Master Data'!$I$2:$I$175,"Sweden",'Master Data'!$H$2:$H$175,"Serious (chronic, manageable)",'Master Data'!$M$2:$M$175,"Withdrawn") -> 1 | G17: =COUNTIFS('Master Data'!$I$2:$I$175,"Sweden",'Master Data'!$H$2:$H$175,"Serious (chronic, manageable)",'Master Data'!$M$2:$M$175,"Ongoing/Pending") -> 2 | H17: =COUNTIFS('Master Data'!$I$2:$I$175,"Sweden",'Master Data'!$H$2:$H$175,"Serious (chronic, manageable)",'Master Data'!$M$2:$M$175,"Not Evaluated") -> 0 | I17: =SUM(C17:H17) -> 10
B20: Table B - Sweden drugs with an extractable ICER, vs severity-tier WTP threshold
B21: Drug | C21: Severity Tier | D21: Access Outcome | E21: ICER Min (SEK/QALY) | F21: ICER Max (SEK/QALY) | G21: WTP Threshold (SEK/QALY) | H21: Min ICER > Threshold? | I21: Accepted ABOVE threshold? | J21: Basis / source note
B22: ='Master Data'!A2 -> Zolgensma | C22: ='Master Data'!H2 -> Ultra-severe (immediately life-threatening) | D22: ='Master Data'!M2 -> Negative | E22: ='Master Data'!AE2 -> 850000 | F22: ='Master Data'!AF2 -> 5700000 | G22: =VLOOKUP(C22,$B$7:$C$9,2,FALSE) -> 2000000 | H22: =IF(E22>G22,"Yes","No") -> No | I22: =IF(AND(OR(D22="Positive",D22="Restricted Positive"),H22="Yes"),"YES - accepted above threshold","No") -> No | J22: ='Master Data'!AG2 -> range (vs Spinraza+BSC: 0.85-3.2M; vs BSC alone: 2.9-5.7M)
B23: ='Master Data'!A5 -> Evrysdi | C23: ='Master Data'!H5 -> Ultra-severe (immediately life-threatening) | D23: ='Master Data'!M5 -> Restricted Positive | E23: ='Master Data'!AE5 -> 800000 | F23: ='Master Data'!AF5 -> 7900000 | G23: =VLOOKUP(C23,$B$7:$C$9,2,FALSE) -> 2000000 | H23: =IF(E23>G23,"Yes","No") -> No | I23: =IF(AND(OR(D23="Positive",D23="Restricted Positive"),H23="Yes"),"YES - accepted above threshold","No") -> No | J23: ='Master Data'!AG5 -> range across 2021 and 2025 reassessments, by SMA subtype
B24: ='Master Data'!A8 -> Spinraza | C24: ='Master Data'!H8 -> Ultra-severe (immediately life-threatening) | D24: ='Master Data'!M8 -> Positive | E24: ='Master Data'!AE8 -> 4100000 | F24: ='Master Data'!AF8 -> 12800000 | G24: =VLOOKUP(C24,$B$7:$C$9,2,FALSE) -> 2000000 | H24: =IF(E24>G24,"Yes","No") -> Yes | I24: =IF(AND(OR(D24="Positive",D24="Restricted Positive"),H24="Yes"),"YES - accepted above threshold","No") -> YES - accepted above threshold | J24: ='Master Data'!AG8 -> range across 2017 and 2023 reassessments, by SMA subtype
B25: ='Master Data'!A41 -> Filsuvez | C25: ='Master Data'!H41 -> Severe (progressive, life-shortening) | D25: ='Master Data'!M41 -> Negative | E25: ='Master Data'!AE41 -> 1200000 | F25: ='Master Data'!AF41 -> 2800000 | G25: =VLOOKUP(C25,$B$7:$C$9,2,FALSE) -> 1000000 | H25: =IF(E25>G25,"Yes","No") -> Yes | I25: =IF(AND(OR(D25="Positive",D25="Restricted Positive"),H25="Yes"),"YES - accepted above threshold","No") -> No | J25: ='Master Data'!AG41 -> range (TLV scenario ~2.1M, sensitivity 1.2-2.8M)
B26: ='Master Data'!A71 -> Crysvita | C26: ='Master Data'!H71 -> Serious (chronic, manageable) | D26: ='Master Data'!M71 -> Restricted Positive | E26: ='Master Data'!AE71 -> 12000000 | F26: ='Master Data'!AF71 -> 12000000 | G26: =VLOOKUP(C26,$B$7:$C$9,2,FALSE) -> 500000 | H26: =IF(E26>G26,"Yes","No") -> Yes | I26: =IF(AND(OR(D26="Positive",D26="Restricted Positive"),H26="Yes"),"YES - accepted above threshold","No") -> YES - accepted above threshold | J26: ='Master Data'!AG71 -> exact (approx., vs conventional therapy)
B27: ='Master Data'!A86 -> Koselugo | C27: ='Master Data'!H86 -> Severe (progressive, life-shortening) | D27: ='Master Data'!M86 -> Negative | E27: ='Master Data'!AE86 -> 1756579 | F27: ='Master Data'!AF86 -> 1756579 | G27: =VLOOKUP(C27,$B$7:$C$9,2,FALSE) -> 1000000 | H27: =IF(E27>G27,"Yes","No") -> Yes | I27: =IF(AND(OR(D27="Positive",D27="Restricted Positive"),H27="Yes"),"YES - accepted above threshold","No") -> No | J27: ='Master Data'!AG86 -> exact (company base case, TLV rejected 11 Jul 2024)
B28: ='Master Data'!A101 -> Kaftrio | C28: ='Master Data'!H101 -> Severe (progressive, life-shortening) | D28: ='Master Data'!M101 -> Positive | E28: ='Master Data'!AE101 -> 7700000 | F28: ='Master Data'!AF101 -> 11700000 | G28: =VLOOKUP(C28,$B$7:$C$9,2,FALSE) -> 1000000 | H28: =IF(E28>G28,"Yes","No") -> Yes | I28: =IF(AND(OR(D28="Positive",D28="Restricted Positive"),H28="Yes"),"YES - accepted above threshold","No") -> YES - accepted above threshold | J28: ='Master Data'!AG101 -> range (earlier 2021 estimate for F/MF; final ICER confidential after agreement)
B29: ='Master Data'!A125 -> Qalsody | C29: ='Master Data'!H125 -> Ultra-severe (immediately life-threatening) | D29: ='Master Data'!M125 -> Restricted Positive | E29: ='Master Data'!AE125 -> 10600000 | F29: ='Master Data'!AF125 -> 28300000 | G29: =VLOOKUP(C29,$B$7:$C$9,2,FALSE) -> 2000000 | H29: =IF(E29>G29,"Yes","No") -> Yes | I29: =IF(AND(OR(D29="Positive",D29="Restricted Positive"),H29="Yes"),"YES - accepted above threshold","No") -> YES - accepted above threshold | J29: ='Master Data'!AG125 -> range (PDF-sourced research estimate)
B31: n=8 of 58 Sweden drug-indications had an extractable numeric ICER point/range in the source text (most public Swedish ICERs are confidential or reported only as cost-comparison/cost-minimisation, not cost-utility). This is the genuine usable sample for this comparison - treat conclusions as indicative, not exhaustive. See README for which figures were excluded as non-ICER (e.g. unit acquisition prices) and the Libmeldy currency-labelling flag.
B33: Reading the table: column I flags drugs that were ULTIMATELY accepted (Positive or Restricted Positive) despite the MINIMUM reported ICER exceeding the severity-tier WTP threshold - i.e. cases where TLV/NT-rådet granted access above the normal benchmark, typically via a managed-entry agreement, side agreement, or risk-sharing/price-cap model (see Comments column in Master Data for mechanism).
B35: Pattern in column I "YES" cases (Spinraza, Crysvita, Kaftrio, Qalsody): all are ultra-rare, high-severity indications (e.g. SMA, X-linked hypophosphatemia, cystic fibrosis, ALS) where TLV/NT-rådet's own published reasoning explicitly invokes the severity/rarity of the condition as grounds to accept an ICER above the nominal benchmark, almost always paired with a confidential managed-entry agreement or price-cap mechanism (see Comments/Conditions in Master Data per drug) rather than a published exception to the threshold itself. This is consistent with TLV's stated practice that severity-graded WTP is a sliding scale, not a hard cutoff - the cases above are evidence of that sliding scale in use, not evidence that the threshold is routinely ignored (only 4 of 8 drugs with an extractable ICER show this pattern).

Sheet 04 Technology & Modality
B2: 4. Technology Type / Treatment Modality Analysis
B3: Are some technologies favoured in the Nordics? Positive-access rate by technology group overall, by country, and Wilson 95% CIs.
B5: Table A - Access outcome by technology group (all countries)
B6: Technology Group | C6: Positive | D6: Restricted Positive | E6: Negative | F6: Withdrawn | G6: Ongoing/Pending | H6: Not Evaluated | I6: Total assessed | J6: x (Pos+RPos) | K6: % positive of assessed | L6: Wilson CI lower | M6: Wilson CI upper
B7: Gene therapy | C7: =COUNTIFS('Master Data'!$AH$2:$AH$175,"Gene therapy",'Master Data'!$M$2:$M$175,"Positive") -> 7 | D7: =COUNTIFS('Master Data'!$AH$2:$AH$175,"Gene therapy",'Master Data'!$M$2:$M$175,"Restricted Positive") -> 1 | E7: =COUNTIFS('Master Data'!$AH$2:$AH$175,"Gene therapy",'Master Data'!$M$2:$M$175,"Negative") -> 6 | F7: =COUNTIFS('Master Data'!$AH$2:$AH$175,"Gene therapy",'Master Data'!$M$2:$M$175,"Withdrawn") -> 6 | G7: =COUNTIFS('Master Data'!$AH$2:$AH$175,"Gene therapy",'Master Data'!$M$2:$M$175,"Ongoing/Pending") -> 5 | H7: =COUNTIFS('Master Data'!$AH$2:$AH$175,"Gene therapy",'Master Data'!$M$2:$M$175,"Not Evaluated") -> 5 | I7: =SUM(C7:H7)-H7 -> 25 | J7: =C7+D7 -> 8 | K7: =IF(I7=0,"",(J7/I7)) -> 0.32 | L7: =IF(I7=0,"",MAX(0,(((J7/I7)+1.959963985^2/(2*I7))/(1+1.959963985^2/I7))-((1.959963985*SQRT(((J7/I7)*(1-(J7/I7))/I7)+(1.959963985^2/(4*I7^2))))/(1+1.959963985^2/I7)))) -> 0.1720519 | M7: =IF(I7=0,"",MIN(1,(((J7/I7)+1.959963985^2/(2*I7))/(1+1.959963985^2/I7))+((1.959963985*SQRT(((J7/I7)*(1-(J7/I7))/I7)+(1.959963985^2/(4*I7^2))))/(1+1.959963985^2/I7)))) -> 0.51589731
B8: Cell therapy | C8: =COUNTIFS('Master Data'!$AH$2:$AH$175,"Cell therapy",'Master Data'!$M$2:$M$175,"Positive") -> 3 | D8: =COUNTIFS('Master Data'!$AH$2:$AH$175,"Cell therapy",'Master Data'!$M$2:$M$175,"Restricted Positive") -> 0 | E8: =COUNTIFS('Master Data'!$AH$2:$AH$175,"Cell therapy",'Master Data'!$M$2:$M$175,"Negative") -> 3 | F8: =COUNTIFS('Master Data'!$AH$2:$AH$175,"Cell therapy",'Master Data'!$M$2:$M$175,"Withdrawn") -> 0 | G8: =COUNTIFS('Master Data'!$AH$2:$AH$175,"Cell therapy",'Master Data'!$M$2:$M$175,"Ongoing/Pending") -> 0 | H8: =COUNTIFS('Master Data'!$AH$2:$AH$175,"Cell therapy",'Master Data'!$M$2:$M$175,"Not Evaluated") -> 15 | I8: =SUM(C8:H8)-H8 -> 6 | J8: =C8+D8 -> 3 | K8: =IF(I8=0,"",(J8/I8)) -> 0.5 | L8: =IF(I8=0,"",MAX(0,(((J8/I8)+1.959963985^2/(2*I8))/(1+1.959963985^2/I8))-((1.959963985*SQRT(((J8/I8)*(1-(J8/I8))/I8)+(1.959963985^2/(4*I8^2))))/(1+1.959963985^2/I8)))) -> 0.18761631 | M8: =IF(I8=0,"",MIN(1,(((J8/I8)+1.959963985^2/(2*I8))/(1+1.959963985^2/I8))+((1.959963985*SQRT(((J8/I8)*(1-(J8/I8))/I8)+(1.959963985^2/(4*I8^2))))/(1+1.959963985^2/I8)))) -> 0.81238369
B9: RNA-targeted | C9: =COUNTIFS('Master Data'!$AH$2:$AH$175,"RNA-targeted",'Master Data'!$M$2:$M$175,"Positive") -> 2 | D9: =COUNTIFS('Master Data'!$AH$2:$AH$175,"RNA-targeted",'Master Data'!$M$2:$M$175,"Restricted Positive") -> 8 | E9: =COUNTIFS('Master Data'!$AH$2:$AH$175,"RNA-targeted",'Master Data'!$M$2:$M$175,"Negative") -> 3 | F9: =COUNTIFS('Master Data'!$AH$2:$AH$175,"RNA-targeted",'Master Data'!$M$2:$M$175,"Withdrawn") -> 0 | G9: =COUNTIFS('Master Data'!$AH$2:$AH$175,"RNA-targeted",'Master Data'!$M$2:$M$175,"Ongoing/Pending") -> 2 | H9: =COUNTIFS('Master Data'!$AH$2:$AH$175,"RNA-targeted",'Master Data'!$M$2:$M$175,"Not Evaluated") -> 3 | I9: =SUM(C9:H9)-H9 -> 15 | J9: =C9+D9 -> 10 | K9: =IF(I9=0,"",(J9/I9)) -> 0.66666667 | L9: =IF(I9=0,"",MAX(0,(((J9/I9)+1.959963985^2/(2*I9))/(1+1.959963985^2/I9))-((1.959963985*SQRT(((J9/I9)*(1-(J9/I9))/I9)+(1.959963985^2/(4*I9^2))))/(1+1.959963985^2/I9)))) -> 0.41713548 | M9: =IF(I9=0,"",MIN(1,(((J9/I9)+1.959963985^2/(2*I9))/(1+1.959963985^2/I9))+((1.959963985*SQRT(((J9/I9)*(1-(J9/I9))/I9)+(1.959963985^2/(4*I9^2))))/(1+1.959963985^2/I9)))) -> 0.84823676
B10: Monoclonal antibody | C10: =COUNTIFS('Master Data'!$AH$2:$AH$175,"Monoclonal antibody",'Master Data'!$M$2:$M$175,"Positive") -> 5 | D10: =COUNTIFS('Master Data'!$AH$2:$AH$175,"Monoclonal antibody",'Master Data'!$M$2:$M$175,"Restricted Positive") -> 7 | E10: =COUNTIFS('Master Data'!$AH$2:$AH$175,"Monoclonal antibody",'Master Data'!$M$2:$M$175,"Negative") -> 6 | F10: =COUNTIFS('Master Data'!$AH$2:$AH$175,"Monoclonal antibody",'Master Data'!$M$2:$M$175,"Withdrawn") -> 1 | G10: =COUNTIFS('Master Data'!$AH$2:$AH$175,"Monoclonal antibody",'Master Data'!$M$2:$M$175,"Ongoing/Pending") -> 4 | H10: =COUNTIFS('Master Data'!$AH$2:$AH$175,"Monoclonal antibody",'Master Data'!$M$2:$M$175,"Not Evaluated") -> 13 | I10: =SUM(C10:H10)-H10 -> 23 | J10: =C10+D10 -> 12 | K10: =IF(I10=0,"",(J10/I10)) -> 0.52173913 | L10: =IF(I10=0,"",MAX(0,(((J10/I10)+1.959963985^2/(2*I10))/(1+1.959963985^2/I10))-((1.959963985*SQRT(((J10/I10)*(1-(J10/I10))/I10)+(1.959963985^2/(4*I10^2))))/(1+1.959963985^2/I10)))) -> 0.32962737 | M10: =IF(I10=0,"",MIN(1,(((J10/I10)+1.959963985^2/(2*I10))/(1+1.959963985^2/I10))+((1.959963985*SQRT(((J10/I10)*(1-(J10/I10))/I10)+(1.959963985^2/(4*I10^2))))/(1+1.959963985^2/I10)))) -> 0.70762843
B11: Enzyme replacement therapy | C11: =COUNTIFS('Master Data'!$AH$2:$AH$175,"Enzyme replacement therapy",'Master Data'!$M$2:$M$175,"Positive") -> 5 | D11: =COUNTIFS('Master Data'!$AH$2:$AH$175,"Enzyme replacement therapy",'Master Data'!$M$2:$M$175,"Restricted Positive") -> 7 | E11: =COUNTIFS('Master Data'!$AH$2:$AH$175,"Enzyme replacement therapy",'Master Data'!$M$2:$M$175,"Negative") -> 6 | F11: =COUNTIFS('Master Data'!$AH$2:$AH$175,"Enzyme replacement therapy",'Master Data'!$M$2:$M$175,"Withdrawn") -> 0 | G11: =COUNTIFS('Master Data'!$AH$2:$AH$175,"Enzyme replacement therapy",'Master Data'!$M$2:$M$175,"Ongoing/Pending") -> 2 | H11: =COUNTIFS('Master Data'!$AH$2:$AH$175,"Enzyme replacement therapy",'Master Data'!$M$2:$M$175,"Not Evaluated") -> 4 | I11: =SUM(C11:H11)-H11 -> 20 | J11: =C11+D11 -> 12 | K11: =IF(I11=0,"",(J11/I11)) -> 0.6 | L11: =IF(I11=0,"",MAX(0,(((J11/I11)+1.959963985^2/(2*I11))/(1+1.959963985^2/I11))-((1.959963985*SQRT(((J11/I11)*(1-(J11/I11))/I11)+(1.959963985^2/(4*I11^2))))/(1+1.959963985^2/I11)))) -> 0.3865815 | M11: =IF(I11=0,"",MIN(1,(((J11/I11)+1.959963985^2/(2*I11))/(1+1.959963985^2/I11))+((1.959963985*SQRT(((J11/I11)*(1-(J11/I11))/I11)+(1.959963985^2/(4*I11^2))))/(1+1.959963985^2/I11)))) -> 0.78119347
B12: Small molecule | C12: =COUNTIFS('Master Data'!$AH$2:$AH$175,"Small molecule",'Master Data'!$M$2:$M$175,"Positive") -> 13 | D12: =COUNTIFS('Master Data'!$AH$2:$AH$175,"Small molecule",'Master Data'!$M$2:$M$175,"Restricted Positive") -> 10 | E12: =COUNTIFS('Master Data'!$AH$2:$AH$175,"Small molecule",'Master Data'!$M$2:$M$175,"Negative") -> 10 | F12: =COUNTIFS('Master Data'!$AH$2:$AH$175,"Small molecule",'Master Data'!$M$2:$M$175,"Withdrawn") -> 1 | G12: =COUNTIFS('Master Data'!$AH$2:$AH$175,"Small molecule",'Master Data'!$M$2:$M$175,"Ongoing/Pending") -> 1 | H12: =COUNTIFS('Master Data'!$AH$2:$AH$175,"Small molecule",'Master Data'!$M$2:$M$175,"Not Evaluated") -> 1 | I12: =SUM(C12:H12)-H12 -> 35 | J12: =C12+D12 -> 23 | K12: =IF(I12=0,"",(J12/I12)) -> 0.65714286 | L12: =IF(I12=0,"",MAX(0,(((J12/I12)+1.959963985^2/(2*I12))/(1+1.959963985^2/I12))-((1.959963985*SQRT(((J12/I12)*(1-(J12/I12))/I12)+(1.959963985^2/(4*I12^2))))/(1+1.959963985^2/I12)))) -> 0.4915195 | M12: =IF(I12=0,"",MIN(1,(((J12/I12)+1.959963985^2/(2*I12))/(1+1.959963985^2/I12))+((1.959963985*SQRT(((J12/I12)*(1-(J12/I12))/I12)+(1.959963985^2/(4*I12^2))))/(1+1.959963985^2/I12)))) -> 0.79168305
B13: Recombinant protein | C13: =COUNTIFS('Master Data'!$AH$2:$AH$175,"Recombinant protein",'Master Data'!$M$2:$M$175,"Positive") -> 0 | D13: =COUNTIFS('Master Data'!$AH$2:$AH$175,"Recombinant protein",'Master Data'!$M$2:$M$175,"Restricted Positive") -> 3 | E13: =COUNTIFS('Master Data'!$AH$2:$AH$175,"Recombinant protein",'Master Data'!$M$2:$M$175,"Negative") -> 2 | F13: =COUNTIFS('Master Data'!$AH$2:$AH$175,"Recombinant protein",'Master Data'!$M$2:$M$175,"Withdrawn") -> 0 | G13: =COUNTIFS('Master Data'!$AH$2:$AH$175,"Recombinant protein",'Master Data'!$M$2:$M$175,"Ongoing/Pending") -> 0 | H13: =COUNTIFS('Master Data'!$AH$2:$AH$175,"Recombinant protein",'Master Data'!$M$2:$M$175,"Not Evaluated") -> 1 | I13: =SUM(C13:H13)-H13 -> 5 | J13: =C13+D13 -> 3 | K13: =IF(I13=0,"",(J13/I13)) -> 0.6 | L13: =IF(I13=0,"",MAX(0,(((J13/I13)+1.959963985^2/(2*I13))/(1+1.959963985^2/I13))-((1.959963985*SQRT(((J13/I13)*(1-(J13/I13))/I13)+(1.959963985^2/(4*I13^2))))/(1+1.959963985^2/I13)))) -> 0.23072428 | M13: =IF(I13=0,"",MIN(1,(((J13/I13)+1.959963985^2/(2*I13))/(1+1.959963985^2/I13))+((1.959963985*SQRT(((J13/I13)*(1-(J13/I13))/I13)+(1.959963985^2/(4*I13^2))))/(1+1.959963985^2/I13)))) -> 0.88237923
B14: Other biologic | C14: =COUNTIFS('Master Data'!$AH$2:$AH$175,"Other biologic",'Master Data'!$M$2:$M$175,"Positive") -> 0 | D14: =COUNTIFS('Master Data'!$AH$2:$AH$175,"Other biologic",'Master Data'!$M$2:$M$175,"Restricted Positive") -> 0 | E14: =COUNTIFS('Master Data'!$AH$2:$AH$175,"Other biologic",'Master Data'!$M$2:$M$175,"Negative") -> 2 | F14: =COUNTIFS('Master Data'!$AH$2:$AH$175,"Other biologic",'Master Data'!$M$2:$M$175,"Withdrawn") -> 0 | G14: =COUNTIFS('Master Data'!$AH$2:$AH$175,"Other biologic",'Master Data'!$M$2:$M$175,"Ongoing/Pending") -> 1 | H14: =COUNTIFS('Master Data'!$AH$2:$AH$175,"Other biologic",'Master Data'!$M$2:$M$175,"Not Evaluated") -> 0 | I14: =SUM(C14:H14)-H14 -> 3 | J14: =C14+D14 -> 0 | K14: =IF(I14=0,"",(J14/I14)) -> 0 | L14: =IF(I14=0,"",MAX(0,(((J14/I14)+1.959963985^2/(2*I14))/(1+1.959963985^2/I14))-((1.959963985*SQRT(((J14/I14)*(1-(J14/I14))/I14)+(1.959963985^2/(4*I14^2))))/(1+1.959963985^2/I14)))) -> 0 | M14: =IF(I14=0,"",MIN(1,(((J14/I14)+1.959963985^2/(2*I14))/(1+1.959963985^2/I14))+((1.959963985*SQRT(((J14/I14)*(1-(J14/I14))/I14)+(1.959963985^2/(4*I14^2))))/(1+1.959963985^2/I14)))) -> 0.56149703
B17: Table B - % positive access by technology group x country (multivariable)
B18: Technology Group | C18: Sweden | D18: Denmark | E18: Norway
B19: Gene therapy | C19: =IF(COUNTIFS('Master Data'!$AH$2:$AH$175,"Gene therapy",'Master Data'!$I$2:$I$175,"Sweden",'Master Data'!$AD$2:$AD$175,1)=0,"n/a",COUNTIFS('Master Data'!$AH$2:$AH$175,"Gene therapy",'Master Data'!$I$2:$I$175,"Sweden",'Master Data'!$AC$2:$AC$175,1)/COUNTIFS('Master Data'!$AH$2:$AH$175,"Gene therapy",'Master Data'!$I$2:$I$175,"Sweden",'Master Data'!$AD$2:$AD$175,1)) -> 0.1 | D19: =IF(COUNTIFS('Master Data'!$AH$2:$AH$175,"Gene therapy",'Master Data'!$I$2:$I$175,"Denmark",'Master Data'!$AD$2:$AD$175,1)=0,"n/a",COUNTIFS('Master Data'!$AH$2:$AH$175,"Gene therapy",'Master Data'!$I$2:$I$175,"Denmark",'Master Data'!$AC$2:$AC$175,1)/COUNTIFS('Master Data'!$AH$2:$AH$175,"Gene therapy",'Master Data'!$I$2:$I$175,"Denmark",'Master Data'!$AD$2:$AD$175,1)) -> 0.5 | E19: =IF(COUNTIFS('Master Data'!$AH$2:$AH$175,"Gene therapy",'Master Data'!$I$2:$I$175,"Norway",'Master Data'!$AD$2:$AD$175,1)=0,"n/a",COUNTIFS('Master Data'!$AH$2:$AH$175,"Gene therapy",'Master Data'!$I$2:$I$175,"Norway",'Master Data'!$AC$2:$AC$175,1)/COUNTIFS('Master Data'!$AH$2:$AH$175,"Gene therapy",'Master Data'!$I$2:$I$175,"Norway",'Master Data'!$AD$2:$AD$175,1)) -> 0.44444444
B20: Cell therapy | C20: =IF(COUNTIFS('Master Data'!$AH$2:$AH$175,"Cell therapy",'Master Data'!$I$2:$I$175,"Sweden",'Master Data'!$AD$2:$AD$175,1)=0,"n/a",COUNTIFS('Master Data'!$AH$2:$AH$175,"Cell therapy",'Master Data'!$I$2:$I$175,"Sweden",'Master Data'!$AC$2:$AC$175,1)/COUNTIFS('Master Data'!$AH$2:$AH$175,"Cell therapy",'Master Data'!$I$2:$I$175,"Sweden",'Master Data'!$AD$2:$AD$175,1)) -> 0.6 | D20: =IF(COUNTIFS('Master Data'!$AH$2:$AH$175,"Cell therapy",'Master Data'!$I$2:$I$175,"Denmark",'Master Data'!$AD$2:$AD$175,1)=0,"n/a",COUNTIFS('Master Data'!$AH$2:$AH$175,"Cell therapy",'Master Data'!$I$2:$I$175,"Denmark",'Master Data'!$AC$2:$AC$175,1)/COUNTIFS('Master Data'!$AH$2:$AH$175,"Cell therapy",'Master Data'!$I$2:$I$175,"Denmark",'Master Data'!$AD$2:$AD$175,1)) -> 0 | E20: =IF(COUNTIFS('Master Data'!$AH$2:$AH$175,"Cell therapy",'Master Data'!$I$2:$I$175,"Norway",'Master Data'!$AD$2:$AD$175,1)=0,"n/a",COUNTIFS('Master Data'!$AH$2:$AH$175,"Cell therapy",'Master Data'!$I$2:$I$175,"Norway",'Master Data'!$AC$2:$AC$175,1)/COUNTIFS('Master Data'!$AH$2:$AH$175,"Cell therapy",'Master Data'!$I$2:$I$175,"Norway",'Master Data'!$AD$2:$AD$175,1)) -> n/a
